Workbook

Sheet READ_ME
A1: RASMITRA | Commercial feasibility model
A3: Purpose | B3: FY22–FY24 bottom-up NPD diversification model. Illustrative assumptions; NOT verified consumer demand.
A4: Source 1 | B4: Case brief: The Growth Gambit, exhibits 1–6; fictional FY21 financials. Uploaded by team.
A5: Source 2 | B5: Team proposal: 6 products × 2 pack formats; category targets ₹135/₹75/₹60 Cr in FY24.
A6: Scope | B6: Revenue, pack/channel economics, financing, working capital, downside, quarterly concentration, target checks.
A7: Input rule | B7: BLUE numbers + pale-yellow background = editable assumptions; GREEN = links to another workbook tab; BLACK = calculated.
A8: Model logic | B8: Average PRODUCTIVE outlets × weekly unit sales × selling weeks × consumer sell-through = net packs.
A9: Revenue accounting | B9: MRP × (1 − blended channel margin) = company realisation (₹/pack). Trade spend is charged on company sales.
A10: Margin warning | B10: Channel partner margins and trade spend are distinct, and should not be added as percentages of the same base.
A11: Case limits | B11: Category market share is only a cross-check. Market size ≠ captive demand. No evidence to forecast 51% plant utilisation improvement.
A12: Period labels | B12: FY22–FY24 represent the case timeline, not current Indian market prices. Current quotes must be time-normalised.
A13: Scenario toggle | B13: Assumptions!C6 controls Base versus Downside; negative shock hits velocity, COGS, trade charges and DSO.
A14: Input caution | B14: All prices, pack COGS, velocity, outlet ramp, ROI and programme cash spend are planning assumptions unless labelled Case.
... A19: FGD evidence | B19: FGD participation does not establish population-wide price sensitivity, trial conversion, category demand or repurchase rates.
A21: Deck_TopDown tab (added for the submission): the top-down category model that produces the deck base case (18.5% FY24 new-product share, Rs 757.3 Cr revenue). Volumes on the deck come from that tab; margins, budget and working capital from the bottom-up tabs.
A22: Checks tab fix: FY24 target tests previously compared the wrong header column and showed N/A; they now read FY22-FY24 correctly.

Sheet Deck_TopDown
A1: DECK BASE CASE | Top-down category model (team category screen), the numbers used on pages 2-4 of the deck
A2: Blue cells are inputs. Change Scenario (B3) or Third category (B4) to see every scenario in the deck. This tab sets volumes; margins, budget and working capital come from the bottom-up tabs of this workbook.
A3: Scenario | B3: Base
A4: Third category from FY23 | B4: None
A6: Category | B6: Market FY21 (Rs Cr) | C6: 3-yr CAGR | D6: Organised share | E6: Our share by year 3 | F6: Selling months | G6: Sales in Mar-Jul | H6: Contribution margin | I6: Source
A7: Spices | B7: 78000 | C7: 0.11 | D7: 0.42 | E7: 0.03 | F7: 12 | G7: =5/12 -> 0.41666667 | H7: 0.199 | I7: Exhibit 5; team estimates; Excel contribution
A8: Premixes | B8: 6400 | C8: 0.14 | D8: 0.55 | E8: 0.1 | F8: 5 | G8: 0.1 | H8: 0.256 | I8: Exhibit 5; team estimates; Excel contribution
A9: Pickles | B9: 12500 | C9: 0.13 | D9: 0.38 | E9: 0.05 | F9: 12 | G9: =5/12 -> 0.41666667 | H9: 0.224 | I9: Exhibit 5; team estimates; Excel contribution (condiments)
A10: RTC mixes | B10: 9800 | C10: 0.17 | D10: 0.61 | E10: 0.04 | F10: 12 | G10: =5/12 -> 0.41666667 | H10: 0.22 | I10: Exhibit 5; team estimates; contribution team estimate
A12: Net realisation (Rs 147 / Rs 195) | B12: =147/195 -> 0.75384615 | C12: Exhibit 2
A13: Core business FY21 (Rs Cr) | B13: 536.48 | C13: Exhibit 1: Rs 560 Cr less 4.2% new products
A14: Core growth a year | B14: 0.048 | C14: Exhibit 1: FY18-21 CAGR
A15: Today's new products FY21 (Rs Cr) | B15: 23.52 | C15: Exhibit 1: 4.2% of Rs 560 Cr
A16: Today's new products growth | B16: 0.1 | C16: Team estimate
A17: Retail outlets reached | B17: 450000 | C17: Exhibit 1
A18: Share of outlets stocking each new category | B18: 0.5 | C18: Team estimate (velocity check only)
A20: Scenario | B20: Reach FY22 | C20: Reach FY23 | D20: Reach FY24 | E20: Share multiplier | F20: Premix ramp FY22 | G20: FY23 | H20: FY24 | I20: Spices ramp FY22 | J20: FY23 | K20: FY24 | L20: Third ramp FY22 | M20: FY23 | N20: FY24
A21: Base | B21: 0.08 | C21: 0.08 | D21: 0.08 | E21: 1 | F21: 0.3 | G21: 0.75 | H21: 1 | I21: 0.05 | J21: 0.6 | K21: 0.95 | L21: 0 | M21: 0.15 | N21: 0.75
A22: Stretch | B22: 0.08 | C22: 0.09 | D22: 0.1 | E22: 1.5 | F22: 0.3 | G22: 0.75 | H22: 1 | I22: 0.05 | J22: 0.6 | K22: 0.95 | L22: 0 | M22: 0.15 | N22: 0.75
A23: Downside | B23: 0.08 | C23: 0.08 | D23: 0.08 | E23: 0.6 | F23: 0 | G23: 0.3 | H23: 0.75 | I23: 0 | J23: 0.25 | K23: 0.75 | L23: 0 | M23: 0 | N23: 0.3
A24: Selected | B24: =INDEX(B21:B23,MATCH($B$3,$A$21:$A$23,0)) -> 0.08 | C24: =INDEX(C21:C23,MATCH($B$3,$A$21:$A$23,0)) -> 0.08 | D24: =INDEX(D21:D23,MATCH($B$3,$A$21:$A$23,0)) -> 0.08 | E24: =INDEX(E21:E23,MATCH($B$3,$A$21:$A$23,0)) -> 1 | F24: =INDEX(F21:F23,MATCH($B$3,$A$21:$A$23,0)) -> 0.3 | G24: =INDEX(G21:G23,MATCH($B$3,$A$21:$A$23,0)) -> 0.75 | H24: =INDEX(H21:H23,MATCH($B$3,$A$21:$A$23,0)) -> 1 | I24: =INDEX(I21:I23,MATCH($B$3,$A$21:$A$23,0)) -> 0.05 | ... N24: =INDEX(N21:N23,MATCH($B$3,$A$21:$A$23,0)) -> 0.75
A27: Revenue (Rs Cr, net realisation) | B27: FY21 | C27: FY22 | D27: FY23 | E27: FY24 | F27: FY25E | G27: FY26E
A28: Core business | B28: =B13 -> 536.48 | C28: =B28*(1+$B$14) -> 562.23104 | D28: =C28*(1+$B$14) -> 589.21813 | E28: =D28*(1+$B$14) -> 617.5006
A29: Today's new products | B29: =B15 -> 23.52 | C29: =B29*(1+$B$16) -> 25.872 | D29: =C29*(1+$B$16) -> 28.4592 | E29: =D29*(1+$B$16) -> 31.30512
A30: Premixes | B30: 0 | C30: =$B$8*(1+$C$8)^1*$D$8*B$24*$B$12*$E$8*$E$24*F$24 -> 7.2600812 | D30: =$B$8*(1+$C$8)^2*$D$8*C$24*$B$12*$E$8*$E$24*G$24 -> 20.691232 | E30: =$B$8*(1+$C$8)^3*$D$8*D$24*$B$12*$E$8*$E$24*H$24 -> 31.450672 | F30: =E30*(1+$C$8) -> 35.853766 | G30: =F30*(1+$C$8) -> 40.873293
A31: Spices | B31: 0 | C31: =$B$7*(1+$C$7)^1*$D$7*B$24*$B$12*$E$7*$E$24*I$24 -> 3.2895072 | D31: =$B$7*(1+$C$7)^2*$D$7*C$24*$B$12*$E$7*$E$24*J$24 -> 43.816236 | E31: =$B$7*(1+$C$7)^3*$D$7*D$24*$B$12*$E$7*$E$24*K$24 -> 77.007035 | F31: =E31/0.95*(1+$C$7) -> 89.97664 | G31: =F31*(1+$C$7) -> 99.874071
A32: Third category (if chosen) | B32: 0 | C32: =IF($B$4="Pickles",$B$9*(1+$C$9)^1*$D$9*B$24*$B$12*$E$9*$E$24*L$24,IF($B$4="RTC mixes",$B$10*(1+$C$10)^1*$D$10*B$24*$B$12*$E$10*$E$24*L$24,0)) -> 0 | D32: =IF($B$4="Pickles",$B$9*(1+$C$9)^2*$D$9*C$24*$B$12*$E$9*$E$24*M$24,IF($B$4="RTC mixes",$B$10*(1+$C$10)^2*$D$10*C$24*$B$12*$E$10*$E$24*M$24,0)) -> 0 | E32: =IF($B$4="Pickles",$B$9*(1+$C$9)^3*$D$9*D$24*$B$12*$E$9*$E$24*N$24,IF($B$4="RTC mixes",$B$10*(1+$C$10)^3*$D$10*D$24*$B$12*$E$10*$E$24*N$24,0)) -> 0 | F32: =E32*(1+IF($B$4="Pickles",$C$9,IF($B$4="RTC mixes",$C$10,0))) -> 0 | G32: =F32*(1+IF($B$4="Pickles",$C$9,IF($B$4="RTC mixes",$C$10,0))) -> 0
A33: New-category revenue | B33: =SUM(B30:B32) -> 0 | C33: =SUM(C30:C32) -> 10.549588 | D33: =SUM(D30:D32) -> 64.507467 | E33: =SUM(E30:E32) -> 108.45771 | F33: =SUM(F30:F32) -> 125.83041 | G33: =SUM(G30:G32) -> 140.74736
A34: New-product revenue | B34: =B29+B33 -> 23.52 | C34: =C29+C33 -> 36.421588 | D34: =D29+D33 -> 92.966667 | E34: =E29+E33 -> 139.76283
A35: Company revenue | B35: 560 | C35: =C28+C34 -> 598.65263 | D35: =D28+D34 -> 682.1848 | E35: =E28+E34 -> 757.26343
A36: New-product share of revenue | B36: =B34/B35 -> 0.042 | C36: =C34/C35 -> 0.060839269 | D36: =D34/D35 -> 0.13627784 | E36: =E34/E35 -> 0.18456302
A38: FY24 new-product revenue needed for 30% | E38: =0.3/0.7*E28 -> 264.64311
A39: FY24 gap to 30% (positive = short) | E39: =E38-E34 -> 124.88029
A40: FY24 sales earned Mar-Jul | E40: =((E28+E29)*0.58+E30*G8+E31*G7+E32*IF($B$4="Pickles",G9,IF($B$4="RTC mixes",G10,0)))/E35 -> 0.54345507
A41: Company revenue CAGR FY21-24 | E41: =(E35/560)^(1/3)-1 -> 0.10582478
A43: Sense checks, FY24 | B43: Premixes | C43: Spices
A44: Share of national market (MRP basis) | B44: =E30/$B$12/($B$8*(1+$C$8)^3) -> 0.0044 | C44: =E31/$B$12/($B$7*(1+$C$7)^3) -> 0.0009576
A45: Sales per stocking outlet a month at MRP (Rs) | B45: =E30/$B$12*10^7/($B$17*$B$18)/$F$8 -> 370.84692 | C45: =E31/$B$12*10^7/($B$17*$B$18)/$F$7 -> 378.34144
A46: FY24 revenue from one point of our share (Rs Cr, base reach 8%) | B46: =$B$8*(1+$C$8)^3*$D$8*0.08*$B$12*0.01 -> 3.1450672 | C46: =$B$7*(1+$C$7)^3*$D$7*0.08*$B$12*0.01 -> 27.020012
A48: Incremental P&L and cash (Rs Cr) | C48: FY22 | D48: FY23 | E48: FY24 | F48: FY25E | G48: FY26E
A49: Contribution | C49: =C30*$H$8+C31*$H$7+C32*IF($B$4="Pickles",$H$9,IF($B$4="RTC mixes",$H$10,0)) -> 2.5131927 | D49: =D30*$H$8+D31*$H$7+D32*IF($B$4="Pickles",$H$9,IF($B$4="RTC mixes",$H$10,0)) -> 14.016386 | E49: =E30*$H$8+E31*$H$7+E32*IF($B$4="Pickles",$H$9,IF($B$4="RTC mixes",$H$10,0)) -> 23.375772 | F49: =F30*$H$8+F31*$H$7+F32*IF($B$4="Pickles",$H$9,IF($B$4="RTC mixes",$H$10,0)) -> 27.083916 | G49: =G30*$H$8+G31*$H$7+G32*IF($B$4="Pickles",$H$9,IF($B$4="RTC mixes",$H$10,0)) -> 30.338503
A50: Launch A&P | C50: 8 | D50: 14 | E50: 13 | F50: =0.06*F33+3 -> 10.549824 | G50: =0.06*G33+3 -> 11.444842
A51: R&D, testing, QA | C51: 3 | D51: 2 | E51: 2 | F51: 0 | G51: 0
A52: Field selling | C52: 1 | D52: 2 | E52: 2 | F52: 0 | G52: 0
A53: Incremental EBITDA | C53: =C49-SUM(C50:C52) -> -9.4868073 | D53: =D49-SUM(D50:D52) -> -3.9836138 | E53: =E49-SUM(E50:E52) -> 6.3757719 | F53: =F49-SUM(F50:F52) -> 16.534091 | G53: =G49-SUM(G50:G52) -> 18.893661
A54: Net working capital (6.42% of new-category sales) | C54: =C33*0.0642 -> 0.67728358 | D54: =D33*0.0642 -> 4.1413794 | E54: =E33*0.0642 -> 6.9629848 | F54: =F33*0.0642 -> 8.0783121 | G54: =G33*0.0642 -> 9.0359808
A55: Change in working capital | C55: =C54 -> 0.67728358 | D55: =D54-C54 -> 3.4640958 | E55: =E54-D54 -> 2.8216053 | F55: =F54-E54 -> 1.1153273 | G55: =G54-F54 -> 0.95766868
A56: Capex | C56: 1 | D56: 2 | E56: 2 | F56: 1 | G56: 1
A57: Free cash flow | C57: =C53-C55-C56 -> -11.164091 | D57: =D53-D55-D56 -> -9.4477096 | E57: =E53-E55-E56 -> 1.5541665 | F57: =F53-F55-F56 -> 14.418764 | G57: =G53-G55-G56 -> 16.935993
A58: Cumulative free cash flow | C58: =C57 -> -11.164091 | D58: =C58+D57 -> -20.6118 | E58: =D58+E57 -> -19.057634 | F58: =E58+F57 -> -4.6388701 | G58: =F58+G57 -> 12.297123
A59: Payback year | C59: =IFERROR(INDEX(C48:G48,MATCH(TRUE(),INDEX(C58:G58>=0,0),0)),"Not by FY26E") -> FY26E
A61: FY25E-26E: categories grow at market CAGR at full ramp; sustaining A&P 6% of sales plus Rs 3 Cr; capex Rs 1 Cr a year. Programme spend FY22-24 per the Rs 75 Cr plan on the Assumptions tab. Excludes tax, depreciation and financing.

Sheet Dashboard
A1: RASMITRA | three-year growth feasibility dashboard
A3: CASE TARGET: FY24 ₹900Cr topline and ≥30% fresh-product revenue | illustrative editable model
A5: DECISION KPIs — formula-driven
A6: Key performance indicator | B6: FY22 | C6: FY23 | D6: FY24
A7: Total revenue ₹Cr | B7: =Portfolio!C11 -> 612.83354 | C7: =Portfolio!D11 -> 773.63535 | D7: =Portfolio!E11 -> 972.03308
A8: Fresh NPD revenue ₹Cr | B8: =Portfolio!C10 -> 32.833539 | C8: =Portfolio!D10 -> 168.63535 | D8: =Portfolio!E10 -> 342.03308
A9: New share of company sales | B9: =Portfolio!C12 -> 0.053576602 | C9: =Portfolio!D12 -> 0.21797782 | D9: =Portfolio!E12 -> 0.35187391
A10: Spices revenue ₹Cr | B10: =Portfolio!C7 -> 17.711862 | C10: =Portfolio!D7 -> 90.929627 | D10: =Portfolio!E7 -> 184.48265
A11: Winter premixes revenue ₹Cr | B11: =Portfolio!C8 -> 7.1380447 | C11: =Portfolio!D8 -> 36.668846 | D11: =Portfolio!E8 -> 74.395013
A12: Condiments revenue ₹Cr | B12: =Portfolio!C9 -> 7.9836316 | C12: =Portfolio!D9 -> 41.036876 | D12: =Portfolio!E9 -> 83.155415
A13: New-product contribution ₹Cr | B13: =P_and_L!B12 -> 7.1485783 | C13: =P_and_L!C12 -> 36.720708 | D13: =P_and_L!D12 -> 74.469354
A14: New-product EBITDA ₹Cr | B14: =P_and_L!B17 -> -4.8514217 | C14: =P_and_L!C17 -> 18.720708 | D14: =P_and_L!D17 -> 57.469354
A15: Project FCF ₹Cr | B15: =Cash_Flow!B11 -> -30.958459 | C15: =Cash_Flow!C11 -> -0.99356924 | D15: =Cash_Flow!D11 -> 48.340246
A16: Cumulative FCF ₹Cr | B16: =Cash_Flow!B12 -> -30.958459 | C16: =Cash_Flow!C12 -> -31.952029 | D16: =Cash_Flow!D12 -> 16.388217
A17: Net working capital ₹Cr | B17: =Working_Capital!B13 -> 2.1070377 | C17: =Working_Capital!C13 -> 10.821315 | D17: =Working_Capital!D13 -> 21.950424
A18: Budget committed cumulatively ₹Cr | B18: =Cash_Flow!B15 -> 18 | C18: =Cash_Flow!C15 -> 47 | D18: =Cash_Flow!D15 -> 75
A19: Programme budget headroom ₹Cr | B19: =Cash_Flow!B17 -> 57 | C19: =Cash_Flow!C17 -> 28 | D19: =Cash_Flow!D17 -> 0
A22: FY24 board-goal attainment
A23: Company revenue (model) | B23: =Portfolio!E11 -> 972.03308
A24: Company revenue goal | B24: =Assumptions!F11 -> 900
A25: Revenue gap ₹ Cr | B25: =B23-B24 -> 72.033077
A26: Fresh product share (model) | B26: =Portfolio!E12 -> 0.35187391
A27: NPD mix target | B27: =Assumptions!F12 -> 0.3
A28: NPD mix gap (percentage points) | B28: =B26-B27 -> 0.051873907
A29: Category demand vs target (₹Cr) | B29: =Portfolio!E10-SUM(Assumptions!D18:D20) -> 72.033077
A30: FY24 cumulative project cash flow | B30: =Cash_Flow!D12 -> 16.388217
A33: SCENARIO | B33: =Assumptions!C6 -> Base
A35: Budget / cash notes
A36: Budget commitment ≠ P&L expense; working-capital draw is based on actual calculated NWC, not on the reserved line.
A37: Model limitations
A38: FY24 baseline, channel velocities, pricing and gross profits are planning inputs. Plant utilisation and core EBITDA cannot be reliably projected.
A40: FY24 distributor net economic profit (₹Cr) | B40: =Distributor_Econ!J19 -> 6.8383464
A41: Annual net profit per participating distributor (₹) | B41: =Distributor_Econ!K19 -> 175342.21
A42: GT channel partner economic check | B42: =IF(Distributor_Econ!J19>0,"POSITIVE","LOSS") -> POSITIVE

Sheet Assumptions
A1: MASTER ASSUMPTIONS | all editable inputs
A3: Sources: Exhibit = case data; Team = submitted strategy; Illustrative = editable, needs pilot/quotes.
A5: Model control | J5: GT economic detail | K5: Value | L5: Source | M5: Explanation
B6: Selected scenario | C6: Base | E6: FY21 revenue (₹Cr) | F6: 560 | G6: Exhibit 1 | J6: Retailer margin / consumer MRP | K6: 0.18 | L6: Exhibit 2 Products A/B | M6: Illustrative proxy for new foods
B7: Downside unit velocity shock | C7: 0.3 | E7: FY21 new products share | F7: 0.042 | G7: Exhibit 1 | J7: Distributor margin / retailer buy price | K7: 0.08 | L7: Exhibit 2 Products A/B | M7: Do not combine as 26% of consumer MRP
B8: Downside COGS surcharge / sales | C8: 0.03 | E8: FY21 gross margin | F8: 0.36 | G8: Exhibit 1 | J8: Distributor handling cost / trial pack ₹ | K8: 0.4 | L8: Illustrative | M8: Returns, picking, van delivery
B9: Downside extra trade spend | C9: 0.02 | E9: FY21 EBITDA margin | F9: 0.105 | G9: Exhibit 1 | J9: Distributor handling cost / large pack ₹ | K9: 2.2 | L9: Illustrative | M9: Returns, picking, van delivery
B10: Downside extra DSO (days) | C10: 15 | E10: Programme funding ceiling (₹Cr) | F10: 75 | G10: Board mandate | J10: Stockholding days at distributor | K10: 18 | L10: Illustrative | M10: Supply partner interviews required
B11: Annual retail MRP increase | C11: 0 | E11: FY24 sales ambition (₹Cr) | F11: 900 | G11: Board mandate | J11: Distributor cost of funds pa | K11: 0.14 | L11: Illustrative | M11: Interest and inventory finance
B12: Annual unit COGS inflation | C12: 0 | E12: FY24 new-product share target | F12: 0.3 | G12: Board mandate | J12: Distributors participating by FY24 | K12: 390 | L12: Exhibit 1, assumption | M12: Case has 390 distributors; all-participating is unvalidated
B13: Consumer sell-through proxy | C13: 0.95 | J13: Distributor funding cycle days | K13: 21 | L13: Illustrative | M13: Not automatically the same as company DSO
A15: Core business + category planning targets (₹ Cr)
A16: Revenue assumption | B16: FY22 | C16: FY23 | D16: FY24 | E16: Source | F16: Important caveat
A17: Legacy portfolio | B17: 580 | C17: 605 | D17: 630 | E17: Team scenario | F17: Legacy includes FY21 portfolio; these are NOT validated forecasts
A18: Spices target | B18: 10 | C18: 70 | D18: 135 | E18: Team scenario | F18: Comparator only, not forced in formula
A19: Winter premix target | B19: 8 | C19: 40 | D19: 75 | E19: Team scenario | F19: Comparator only, not forced in formula
A20: Condiments target | B20: 2 | C20: 25 | D20: 60 | E20: Team scenario | F20: Comparator only, not forced in formula
A22: SKU/format assumptions — all price and unit COGS inputs are hypothetical
A23: Code | B23: Category | C23: Proposed SKU | D23: Pack format | E23: MRP FY22 ₹ | F23: Unit COGS FY22 ₹ | G23: Weeks/year | H23: Source | I23: Pricing caution
A24: SAB_T | B24: Spices | C24: Everyday Sabzi Masala | D24: 8g trial | E24: 10 | F24: 5.25 | G24: 52 | H24: Illustrative | I24: Trial pack may be uneconomic online
A25: SAB_L | B25: Spices | C25: Everyday Sabzi Masala | D25: 50g pouch | E25: 49 | F25: 23 | G25: 52 | H25: Team + illustrative | I25: ₹49 MRP hypothetical
A26: GAR_T | B26: Spices | C26: Garam Masala | D26: 5g trial | E26: 10 | F26: 5.35 | G26: 52 | H26: Illustrative | I26: Trial pack may be uneconomic online
A27: GAR_L | B27: Spices | C27: Garam Masala | D27: 50g pouch | E27: 49 | F27: 23.5 | G27: 52 | H27: Team + illustrative | I27: ₹49 MRP hypothetical
A28: GIN_T | B28: Premixes | C28: Ginger-Lemon Hot Drink | D28: 15g single sachet | E28: 10 | F28: 4.35 | G28: 26 | H28: Team + illustrative | I28: Check against ginger tea competitors
A29: GIN_L | B29: Premixes | C29: Ginger-Lemon Hot Drink | D29: 10-sachet pack | E29: 99 | F29: 44 | G29: 26 | H29: Team + illustrative | I29: ₹99 may be premium vs incumbent
A30: BAD_T | B30: Premixes | C30: Badam-Elaichi Milk Mix | D30: 15g single sachet | E30: 10 | F30: 4.5 | G30: 26 | H30: Team + illustrative | I30: Customer must additionally buy milk
A31: BAD_L | B31: Premixes | C31: Badam-Elaichi Milk Mix | D31: 150g pouch | E31: 99 | F31: 45.5 | G31: 26 | H31: Team + illustrative | I31: Customer must additionally buy milk
A32: CHU_T | B32: Condiments | C32: Tamarind-Date Chutney | D32: 20g sachet | E32: 10 | F32: 4.8 | G32: 52 | H32: Team + illustrative | I32: Packaging/storage stability to test
A33: CHU_L | B33: Condiments | C33: Tamarind-Date Chutney | D33: 200g pack | E33: 99 | F33: 47 | G33: 52 | H33: Team + illustrative | I33: Shelf-life/cost to test
A34: PIC_T | B34: Condiments | C34: Lime Pickle | D34: 20g sachet | E34: 10 | F34: 4.7 | G34: 52 | H34: Team + illustrative | I34: Sampling and local taste to test
A35: PIC_L | B35: Condiments | C35: Lime Pickle | D35: 200g pack | E35: 99 | F35: 46.5 | G35: 52 | H35: Team + illustrative | I35: Shelf-life/cost to test
A38: Channel economics — case partner margins / trade spend and credit days
A39: Channel | B39: Partner margin / MRP | C39: Trade spend / net revenue | D39: DSO days | E39: Freight ₹/pack | F39: Inventory days | G39: DPO days | H39: Source
A40: GT | B40: 0.25 | C40: 0.065 | D40: 21 | E40: 1 | F40: 28 | G40: 30 | H40: Exhibit 3 margins, trade, credit; other = assumption
A41: Modern | B41: 0.28 | C41: 0.14 | D41: 45 | E41: 1.7 | F41: 35 | G41: 30 | H41: Exhibit 3 margins, trade, credit; other = assumption
A42: QCom | B42: 0.38 | C42: 0.24 | D42: 32 | E42: 2 | F42: 21 | G42: 30 | H42: Exhibit 3 margins, trade, credit; other = assumption
A45: Programme budget: 3-year allocation, ₹ Cr (source: team scenario, EDITABLE)
A46: Budget use | B46: FY22 | C46: FY23 | D46: FY24 | E46: 3-year total | F46: Accounting treatment
A47: Launch A&P, sampling | B47: 8 | C47: 14 | D47: 13 | E47: =SUM(B47:D47) -> 35 | F47: Operating programme expense
A48: Incremental working capital envelope | B48: 4 | C48: 7 | D48: 7 | E48: =SUM(B48:D48) -> 18 | F48: Funding reserve; not operating expense
A49: Development, testing, QA | B49: 3 | C49: 2 | D49: 2 | E49: =SUM(B49:D49) -> 7 | F49: Operating programme expense (simplification)
A50: Field selling and training | B50: 1 | C50: 2 | D50: 2 | E50: =SUM(B50:D50) -> 5 | F50: Operating programme expense
A51: Small capex | B51: 1 | C51: 2 | D51: 2 | E51: =SUM(B51:D51) -> 5 | F51: Cash capex, not immediate EBITDA expense
A52: Contingency / unspent reserve | B52: 1 | C52: 2 | D52: 2 | E52: =SUM(B52:D52) -> 5 | F52: Reserve; expensed only if deployed
A53: TOTAL COMMITMENT | B53: =SUM(B47:B52) -> 18 | C53: =SUM(C47:C52) -> 29 | D53: =SUM(D47:D52) -> 28 | E53: =SUM(E47:E52) -> 75
A55: Quarterly seasonality & sales conversion assumptions
A56: DISTRIBUTION × VELOCITY editable inputs — illustrative, not observed demand | J56: Category | K56: Q1 weight | L56: Q2 weight | M56: Q3 weight | N56: Q4 weight
A57: Fiscal year | B57: SKU code | C57: Channel | D57: Avg productive outlets | E57: Gross packs/outlet/week | F57: Source | G57: Who validates | H57: Data status | J57: Spices | K57: 0.22 | L57: 0.24 | M57: 0.27 | N57: 0.27
A58: FY22 | B58: SAB_T | C58: GT | D58: 10400 | E58: 2.58 | F58: Illustrative (replace with pilot) | G58: Sales + channel partner | H58: Unvalidated | J58: Premixes | K58: 0.02 | L58: 0.04 | M58: 0.5 | N58: 0.44
A59: FY22 | B59: SAB_T | C59: Modern | D59: 364 | E59: 10.32 | F59: Illustrative (replace with pilot) | G59: Sales + channel partner | H59: Unvalidated | J59: Condiments | K59: 0.22 | L59: 0.25 | M59: 0.28 | N59: 0.25
A60: FY22 | B60: SAB_T | C60: QCom | D60: 146 | E60: 30.96 | F60: Illustrative (replace with pilot) | G60: Sales + channel partner | H60: Unvalidated | J60: FY21 core volume | K60: 0.41 | L60: 0.23 | M60: 0.15 | N60: 0.21
A61: FY22 | B61: SAB_L | C61: GT | D61: 12000 | E61: 3.12 | F61: Illustrative (replace with pilot) | G61: Sales + channel partner | H61: Unvalidated
A62: FY22 | B62: SAB_L | C62: Modern | D62: 420 | E62: 12.48 | F62: Illustrative (replace with pilot) | G62: Sales + channel partner | H62: Unvalidated
A63: FY22 | B63: SAB_L | C63: QCom | D63: 168 | E63: 37.44 | F63: Illustrative (replace with pilot) | G63: Sales + channel partner | H63: Unvalidated
A64: FY22 | B64: GAR_T | C64: GT | D64: 9120 | E64: 2.22 | F64: Illustrative (replace with pilot) | G64: Sales + channel partner | H64: Unvalidated
A65: FY22 | B65: GAR_T | C65: Modern | D65: 319 | E65: 8.88 | F65: Illustrative (replace with pilot) | G65: Sales + channel partner | H65: Unvalidated
A66: FY22 | B66: GAR_T | C66: QCom | D66: 128 | E66: 26.64 | F66: Illustrative (replace with pilot) | G66: Sales + channel partner | H66: Unvalidated
A67: FY22 | B67: GAR_L | C67: GT | D67: 11200 | E67: 2.64 | F67: Illustrative (replace with pilot) | G67: Sales + channel partner | H67: Unvalidated
A68: FY22 | B68: GAR_L | C68: Modern | D68: 392 | E68: 10.56 | F68: Illustrative (replace with pilot) | G68: Sales + channel partner | H68: Unvalidated
A69: FY22 | B69: GAR_L | C69: QCom | D69: 157 | E69: 31.68 | F69: Illustrative (replace with pilot) | G69: Sales + channel partner | H69: Unvalidated
A70: FY22 | B70: GIN_T | C70: GT | D70: 8320 | E70: 3.12 | F70: Illustrative (replace with pilot) | G70: Sales + channel partner | H70: Unvalidated
A71: FY22 | B71: GIN_T | C71: Modern | D71: 291 | E71: 12.48 | F71: Illustrative (replace with pilot) | G71: Sales + channel partner | H71: Unvalidated
A72: FY22 | B72: GIN_T | C72: QCom | D72: 116 | E72: 37.44 | F72: Illustrative (replace with pilot) | G72: Sales + channel partner | H72: Unvalidated
... A165: FY24 | B165: PIC_L | C165: QCom | D165: 518 | E165: 26.4 | F165: Illustrative (replace with pilot) | G165: Sales + channel partner | H165: Unvalidated

Sheet SKU_Channel_Model
A1: BOTTOM-UP SALES ENGINE | 12 packs × 3 channels × 3 years
A3: Blue demand assumptions are on Assumptions tab; values here are linked. Sales use consumer offtake proxy, not pipeline stuffing.
A5: FY | B5: SKU code | C5: Category | D5: Channel | E5: MRP ₹ | F5: COGS/pack ₹ | G5: Selling weeks | H5: Avg productive outlets | I5: Packs/outlet/week | J5: Sell-through | K5: Partner margin | L5: Trade spend | M5: Freight/pack ₹ | N5: Gross shipped packs | O5: Net sold packs | P5: Company ₹/pack | Q5: Net revenue ₹Cr | R5: COGS ₹Cr | S5: Trade ₹Cr | T5: Freight ₹Cr | U5: Contribution ₹Cr | V5: Contrib. % | W5: Data source | X5: SKU name / pack
A6: =Assumptions!A58 -> FY22 | B6: =Assumptions!B58 -> SAB_T | C6: =Assumptions!B24 -> Spices | D6: =Assumptions!C58 -> GT | E6: =Assumptions!E24*(1+Assumptions!$C$11)^0 -> 10 | F6: =Assumptions!F24*(1+Assumptions!$C$12)^0 -> 5.25 | G6: =Assumptions!G24 -> 52 | H6: =Assumptions!D58 -> 10400 | I6: =Assumptions!E58 -> 2.58 | J6: =Assumptions!$C$13 -> 0.95 | K6: =Assumptions!B40 -> 0.25 | L6: =Assumptions!C40+IF(Assumptions!$C$6="Downside",Assumptions!$C$9,0) -> 0.065 | M6: =Assumptions!E40 -> 1 | N6: =H6*I6*G6*IF(Assumptions!$C$6="Downside",1-Assumptions!$C$7,1) -> 1395264 | O6: =N6*J6 -> 1325500.8 | P6: =E6*(1-K6) -> 7.5 | Q6: =O6*P6/10000000 -> 0.9941256 | R6: =O6*F6/10000000+IF(Assumptions!$C$6="Downside",Q6*Assumptions!$C$8,0) -> 0.69588792 | S6: =Q6*L6 -> 0.064618164 | T6: =O6*M6/10000000 -> 0.13255008 | U6: =Q6-SUM(R6:T6) -> 0.10106944 | V6: =IFERROR(U6/Q6,0) -> 0.10166667 | W6: =Assumptions!F58 -> Illustrative (replace with pilot) | X6: =Assumptions!C24&" | "&Assumptions!D24 -> Everyday Sabzi Masala | 8g trial
A7: =Assumptions!A59 -> FY22 | B7: =Assumptions!B59 -> SAB_T | C7: =Assumptions!B24 -> Spices | D7: =Assumptions!C59 -> Modern | E7: =Assumptions!E24*(1+Assumptions!$C$11)^0 -> 10 | F7: =Assumptions!F24*(1+Assumptions!$C$12)^0 -> 5.25 | G7: =Assumptions!G24 -> 52 | H7: =Assumptions!D59 -> 364 | I7: =Assumptions!E59 -> 10.32 | J7: =Assumptions!$C$13 -> 0.95 | K7: =Assumptions!B41 -> 0.28 | L7: =Assumptions!C41+IF(Assumptions!$C$6="Downside",Assumptions!$C$9,0) -> 0.14 | M7: =Assumptions!E41 -> 1.7 | N7: =H7*I7*G7*IF(Assumptions!$C$6="Downside",1-Assumptions!$C$7,1) -> 195336.96 | O7: =N7*J7 -> 185570.11 | P7: =E7*(1-K7) -> 7.2 | Q7: =O7*P7/10000000 -> 0.13361048 | R7: =O7*F7/10000000+IF(Assumptions!$C$6="Downside",Q7*Assumptions!$C$8,0) -> 0.097424309 | S7: =Q7*L7 -> 0.018705467 | T7: =O7*M7/10000000 -> 0.031546919 | U7: =Q7-SUM(R7:T7) -> -0.014066214 | V7: =IFERROR(U7/Q7,0) -> -0.10527778 | W7: =Assumptions!F59 -> Illustrative (replace with pilot) | X7: =Assumptions!C24&" | "&Assumptions!D24 -> Everyday Sabzi Masala | 8g trial
A8: =Assumptions!A60 -> FY22 | B8: =Assumptions!B60 -> SAB_T | C8: =Assumptions!B24 -> Spices | D8: =Assumptions!C60 -> QCom | E8: =Assumptions!E24*(1+Assumptions!$C$11)^0 -> 10 | F8: =Assumptions!F24*(1+Assumptions!$C$12)^0 -> 5.25 | G8: =Assumptions!G24 -> 52 | H8: =Assumptions!D60 -> 146 | I8: =Assumptions!E60 -> 30.96 | J8: =Assumptions!$C$13 -> 0.95 | K8: =Assumptions!B42 -> 0.38 | L8: =Assumptions!C42+IF(Assumptions!$C$6="Downside",Assumptions!$C$9,0) -> 0.24 | M8: =Assumptions!E42 -> 2 | N8: =H8*I8*G8*IF(Assumptions!$C$6="Downside",1-Assumptions!$C$7,1) -> 235048.32 | O8: =N8*J8 -> 223295.9 | P8: =E8*(1-K8) -> 6.2 | Q8: =O8*P8/10000000 -> 0.13844346 | R8: =O8*F8/10000000+IF(Assumptions!$C$6="Downside",Q8*Assumptions!$C$8,0) -> 0.11723035 | S8: =Q8*L8 -> 0.033226431 | T8: =O8*M8/10000000 -> 0.044659181 | U8: =Q8-SUM(R8:T8) -> -0.0566725 | V8: =IFERROR(U8/Q8,0) -> -0.40935484 | W8: =Assumptions!F60 -> Illustrative (replace with pilot) | X8: =Assumptions!C24&" | "&Assumptions!D24 -> Everyday Sabzi Masala | 8g trial
A9: =Assumptions!A61 -> FY22 | B9: =Assumptions!B61 -> SAB_L | C9: =Assumptions!B25 -> Spices | D9: =Assumptions!C61 -> GT | E9: =Assumptions!E25*(1+Assumptions!$C$11)^0 -> 49 | F9: =Assumptions!F25*(1+Assumptions!$C$12)^0 -> 23 | G9: =Assumptions!G25 -> 52 | H9: =Assumptions!D61 -> 12000 | I9: =Assumptions!E61 -> 3.12 | J9: =Assumptions!$C$13 -> 0.95 | K9: =Assumptions!B40 -> 0.25 | L9: =Assumptions!C40+IF(Assumptions!$C$6="Downside",Assumptions!$C$9,0) -> 0.065 | M9: =Assumptions!E40 -> 1 | N9: =H9*I9*G9*IF(Assumptions!$C$6="Downside",1-Assumptions!$C$7,1) -> 1946880 | O9: =N9*J9 -> 1849536 | P9: =E9*(1-K9) -> 36.75 | Q9: =O9*P9/10000000 -> 6.7970448 | R9: =O9*F9/10000000+IF(Assumptions!$C$6="Downside",Q9*Assumptions!$C$8,0) -> 4.2539328 | S9: =Q9*L9 -> 0.44180791 | T9: =O9*M9/10000000 -> 0.1849536 | U9: =Q9-SUM(R9:T9) -> 1.9163505 | V9: =IFERROR(U9/Q9,0) -> 0.28193878 | W9: =Assumptions!F61 -> Illustrative (replace with pilot) | X9: =Assumptions!C25&" | "&Assumptions!D25 -> Everyday Sabzi Masala | 50g pouch
A10: =Assumptions!A62 -> FY22 | B10: =Assumptions!B62 -> SAB_L | C10: =Assumptions!B25 -> Spices | D10: =Assumptions!C62 -> Modern | E10: =Assumptions!E25*(1+Assumptions!$C$11)^0 -> 49 | F10: =Assumptions!F25*(1+Assumptions!$C$12)^0 -> 23 | G10: =Assumptions!G25 -> 52 | H10: =Assumptions!D62 -> 420 | I10: =Assumptions!E62 -> 12.48 | J10: =Assumptions!$C$13 -> 0.95 | K10: =Assumptions!B41 -> 0.28 | L10: =Assumptions!C41+IF(Assumptions!$C$6="Downside",Assumptions!$C$9,0) -> 0.14 | M10: =Assumptions!E41 -> 1.7 | N10: =H10*I10*G10*IF(Assumptions!$C$6="Downside",1-Assumptions!$C$7,1) -> 272563.2 | O10: =N10*J10 -> 258935.04 | P10: =E10*(1-K10) -> 35.28 | Q10: =O10*P10/10000000 -> 0.91352282 | R10: =O10*F10/10000000+IF(Assumptions!$C$6="Downside",Q10*Assumptions!$C$8,0) -> 0.59555059 | S10: =Q10*L10 -> 0.12789319 | T10: =O10*M10/10000000 -> 0.044018957 | U10: =Q10-SUM(R10:T10) -> 0.14606008 | V10: =IFERROR(U10/Q10,0) -> 0.15988662 | W10: =Assumptions!F62 -> Illustrative (replace with pilot) | X10: =Assumptions!C25&" | "&Assumptions!D25 -> Everyday Sabzi Masala | 50g pouch
A11: =Assumptions!A63 -> FY22 | B11: =Assumptions!B63 -> SAB_L | C11: =Assumptions!B25 -> Spices | D11: =Assumptions!C63 -> QCom | E11: =Assumptions!E25*(1+Assumptions!$C$11)^0 -> 49 | F11: =Assumptions!F25*(1+Assumptions!$C$12)^0 -> 23 | G11: =Assumptions!G25 -> 52 | H11: =Assumptions!D63 -> 168 | I11: =Assumptions!E63 -> 37.44 | J11: =Assumptions!$C$13 -> 0.95 | K11: =Assumptions!B42 -> 0.38 | L11: =Assumptions!C42+IF(Assumptions!$C$6="Downside",Assumptions!$C$9,0) -> 0.24 | M11: =Assumptions!E42 -> 2 | N11: =H11*I11*G11*IF(Assumptions!$C$6="Downside",1-Assumptions!$C$7,1) -> 327075.84 | O11: =N11*J11 -> 310722.05 | P11: =E11*(1-K11) -> 30.38 | Q11: =O11*P11/10000000 -> 0.94397358 | R11: =O11*F11/10000000+IF(Assumptions!$C$6="Downside",Q11*Assumptions!$C$8,0) -> 0.71466071 | S11: =Q11*L11 -> 0.22655366 | T11: =O11*M11/10000000 -> 0.06214441 | U11: =Q11-SUM(R11:T11) -> -0.059385198 | V11: =IFERROR(U11/Q11,0) -> -0.062909809 | W11: =Assumptions!F63 -> Illustrative (replace with pilot) | X11: =Assumptions!C25&" | "&Assumptions!D25 -> Everyday Sabzi Masala | 50g pouch
A12: =Assumptions!A64 -> FY22 | B12: =Assumptions!B64 -> GAR_T | C12: =Assumptions!B26 -> Spices | D12: =Assumptions!C64 -> GT | E12: =Assumptions!E26*(1+Assumptions!$C$11)^0 -> 10 | F12: =Assumptions!F26*(1+Assumptions!$C$12)^0 -> 5.35 | G12: =Assumptions!G26 -> 52 | H12: =Assumptions!D64 -> 9120 | I12: =Assumptions!E64 -> 2.22 | J12: =Assumptions!$C$13 -> 0.95 | K12: =Assumptions!B40 -> 0.25 | L12: =Assumptions!C40+IF(Assumptions!$C$6="Downside",Assumptions!$C$9,0) -> 0.065 | M12: =Assumptions!E40 -> 1 | N12: =H12*I12*G12*IF(Assumptions!$C$6="Downside",1-Assumptions!$C$7,1) -> 1052812.8 | O12: =N12*J12 -> 1000172.2 | P12: =E12*(1-K12) -> 7.5 | Q12: =O12*P12/10000000 -> 0.75012912 | R12: =O12*F12/10000000+IF(Assumptions!$C$6="Downside",Q12*Assumptions!$C$8,0) -> 0.53509211 | S12: =Q12*L12 -> 0.048758393 | T12: =O12*M12/10000000 -> 0.10001722 | U12: =Q12-SUM(R12:T12) -> 0.066261406 | V12: =IFERROR(U12/Q12,0) -> 0.088333333 | W12: =Assumptions!F64 -> Illustrative (replace with pilot) | X12: =Assumptions!C26&" | "&Assumptions!D26 -> Garam Masala | 5g trial
A13: =Assumptions!A65 -> FY22 | B13: =Assumptions!B65 -> GAR_T | C13: =Assumptions!B26 -> Spices | D13: =Assumptions!C65 -> Modern | E13: =Assumptions!E26*(1+Assumptions!$C$11)^0 -> 10 | F13: =Assumptions!F26*(1+Assumptions!$C$12)^0 -> 5.35 | G13: =Assumptions!G26 -> 52 | H13: =Assumptions!D65 -> 319 | I13: =Assumptions!E65 -> 8.88 | J13: =Assumptions!$C$13 -> 0.95 | K13: =Assumptions!B41 -> 0.28 | L13: =Assumptions!C41+IF(Assumptions!$C$6="Downside",Assumptions!$C$9,0) -> 0.14 | M13: =Assumptions!E41 -> 1.7 | N13: =H13*I13*G13*IF(Assumptions!$C$6="Downside",1-Assumptions!$C$7,1) -> 147301.44 | O13: =N13*J13 -> 139936.37 | P13: =E13*(1-K13) -> 7.2 | Q13: =O13*P13/10000000 -> 0.10075418 | R13: =O13*F13/10000000+IF(Assumptions!$C$6="Downside",Q13*Assumptions!$C$8,0) -> 0.074865957 | S13: =Q13*L13 -> 0.014105586 | T13: =O13*M13/10000000 -> 0.023789183 | U13: =Q13-SUM(R13:T13) -> -0.01200654 | V13: =IFERROR(U13/Q13,0) -> -0.11916667 | W13: =Assumptions!F65 -> Illustrative (replace with pilot) | X13: =Assumptions!C26&" | "&Assumptions!D26 -> Garam Masala | 5g trial
A14: =Assumptions!A66 -> FY22 | B14: =Assumptions!B66 -> GAR_T | C14: =Assumptions!B26 -> Spices | D14: =Assumptions!C66 -> QCom | E14: =Assumptions!E26*(1+Assumptions!$C$11)^0 -> 10 | F14: =Assumptions!F26*(1+Assumptions!$C$12)^0 -> 5.35 | G14: =Assumptions!G26 -> 52 | H14: =Assumptions!D66 -> 128 | I14: =Assumptions!E66 -> 26.64 | J14: =Assumptions!$C$13 -> 0.95 | K14: =Assumptions!B42 -> 0.38 | L14: =Assumptions!C42+IF(Assumptions!$C$6="Downside",Assumptions!$C$9,0) -> 0.24 | M14: =Assumptions!E42 -> 2 | N14: =H14*I14*G14*IF(Assumptions!$C$6="Downside",1-Assumptions!$C$7,1) -> 177315.84 | O14: =N14*J14 -> 168450.05 | P14: =E14*(1-K14) -> 6.2 | Q14: =O14*P14/10000000 -> 0.10443903 | R14: =O14*F14/10000000+IF(Assumptions!$C$6="Downside",Q14*Assumptions!$C$8,0) -> 0.090120776 | S14: =Q14*L14 -> 0.025065367 | T14: =O14*M14/10000000 -> 0.03369001 | U14: =Q14-SUM(R14:T14) -> -0.044437123 | V14: =IFERROR(U14/Q14,0) -> -0.42548387 | W14: =Assumptions!F66 -> Illustrative (replace with pilot) | X14: =Assumptions!C26&" | "&Assumptions!D26 -> Garam Masala | 5g trial
A15: =Assumptions!A67 -> FY22 | B15: =Assumptions!B67 -> GAR_L | C15: =Assumptions!B27 -> Spices | D15: =Assumptions!C67 -> GT | E15: =Assumptions!E27*(1+Assumptions!$C$11)^0 -> 49 | F15: =Assumptions!F27*(1+Assumptions!$C$12)^0 -> 23.5 | G15: =Assumptions!G27 -> 52 | H15: =Assumptions!D67 -> 11200 | I15: =Assumptions!E67 -> 2.64 | J15: =Assumptions!$C$13 -> 0.95 | K15: =Assumptions!B40 -> 0.25 | L15: =Assumptions!C40+IF(Assumptions!$C$6="Downside",Assumptions!$C$9,0) -> 0.065 | M15: =Assumptions!E40 -> 1 | N15: =H15*I15*G15*IF(Assumptions!$C$6="Downside",1-Assumptions!$C$7,1) -> 1537536 | O15: =N15*J15 -> 1460659.2 | P15: =E15*(1-K15) -> 36.75 | Q15: =O15*P15/10000000 -> 5.3679226 | R15: =O15*F15/10000000+IF(Assumptions!$C$6="Downside",Q15*Assumptions!$C$8,0) -> 3.4325491 | S15: =Q15*L15 -> 0.34891497 | T15: =O15*M15/10000000 -> 0.14606592 | U15: =Q15-SUM(R15:T15) -> 1.4403926 | V15: =IFERROR(U15/Q15,0) -> 0.26833333 | W15: =Assumptions!F67 -> Illustrative (replace with pilot) | X15: =Assumptions!C27&" | "&Assumptions!D27 -> Garam Masala | 50g pouch
A16: =Assumptions!A68 -> FY22 | B16: =Assumptions!B68 -> GAR_L | C16: =Assumptions!B27 -> Spices | D16: =Assumptions!C68 -> Modern | E16: =Assumptions!E27*(1+Assumptions!$C$11)^0 -> 49 | F16: =Assumptions!F27*(1+Assumptions!$C$12)^0 -> 23.5 | G16: =Assumptions!G27 -> 52 | H16: =Assumptions!D68 -> 392 | I16: =Assumptions!E68 -> 10.56 | J16: =Assumptions!$C$13 -> 0.95 | K16: =Assumptions!B41 -> 0.28 | L16: =Assumptions!C41+IF(Assumptions!$C$6="Downside",Assumptions!$C$9,0) -> 0.14 | M16: =Assumptions!E41 -> 1.7 | N16: =H16*I16*G16*IF(Assumptions!$C$6="Downside",1-Assumptions!$C$7,1) -> 215255.04 | O16: =N16*J16 -> 204492.29 | P16: =E16*(1-K16) -> 35.28 | Q16: =O16*P16/10000000 -> 0.72144879 | R16: =O16*F16/10000000+IF(Assumptions!$C$6="Downside",Q16*Assumptions!$C$8,0) -> 0.48055688 | S16: =Q16*L16 -> 0.10100283 | T16: =O16*M16/10000000 -> 0.034763689 | U16: =Q16-SUM(R16:T16) -> 0.1051254 | V16: =IFERROR(U16/Q16,0) -> 0.14571429 | W16: =Assumptions!F68 -> Illustrative (replace with pilot) | X16: =Assumptions!C27&" | "&Assumptions!D27 -> Garam Masala | 50g pouch
A17: =Assumptions!A69 -> FY22 | B17: =Assumptions!B69 -> GAR_L | C17: =Assumptions!B27 -> Spices | D17: =Assumptions!C69 -> QCom | E17: =Assumptions!E27*(1+Assumptions!$C$11)^0 -> 49 | F17: =Assumptions!F27*(1+Assumptions!$C$12)^0 -> 23.5 | G17: =Assumptions!G27 -> 52 | H17: =Assumptions!D69 -> 157 | I17: =Assumptions!E69 -> 31.68 | J17: =Assumptions!$C$13 -> 0.95 | K17: =Assumptions!B42 -> 0.38 | L17: =Assumptions!C42+IF(Assumptions!$C$6="Downside",Assumptions!$C$9,0) -> 0.24 | M17: =Assumptions!E42 -> 2 | N17: =H17*I17*G17*IF(Assumptions!$C$6="Downside",1-Assumptions!$C$7,1) -> 258635.52 | O17: =N17*J17 -> 245703.74 | P17: =E17*(1-K17) -> 30.38 | Q17: =O17*P17/10000000 -> 0.74644797 | R17: =O17*F17/10000000+IF(Assumptions!$C$6="Downside",Q17*Assumptions!$C$8,0) -> 0.5774038 | S17: =Q17*L17 -> 0.17914751 | T17: =O17*M17/10000000 -> 0.049140749 | U17: =Q17-SUM(R17:T17) -> -0.059244087 | V17: =IFERROR(U17/Q17,0) -> -0.079368005 | W17: =Assumptions!F69 -> Illustrative (replace with pilot) | X17: =Assumptions!C27&" | "&Assumptions!D27 -> Garam Masala | 50g pouch
A18: =Assumptions!A70 -> FY22 | B18: =Assumptions!B70 -> GIN_T | C18: =Assumptions!B28 -> Premixes | D18: =Assumptions!C70 -> GT | E18: =Assumptions!E28*(1+Assumptions!$C$11)^0 -> 10 | F18: =Assumptions!F28*(1+Assumptions!$C$12)^0 -> 4.35 | G18: =Assumptions!G28 -> 26 | H18: =Assumptions!D70 -> 8320 | I18: =Assumptions!E70 -> 3.12 | J18: =Assumptions!$C$13 -> 0.95 | K18: =Assumptions!B40 -> 0.25 | L18: =Assumptions!C40+IF(Assumptions!$C$6="Downside",Assumptions!$C$9,0) -> 0.065 | M18: =Assumptions!E40 -> 1 | N18: =H18*I18*G18*IF(Assumptions!$C$6="Downside",1-Assumptions!$C$7,1) -> 674918.4 | O18: =N18*J18 -> 641172.48 | P18: =E18*(1-K18) -> 7.5 | Q18: =O18*P18/10000000 -> 0.48087936 | R18: =O18*F18/10000000+IF(Assumptions!$C$6="Downside",Q18*Assumptions!$C$8,0) -> 0.27891003 | S18: =Q18*L18 -> 0.031257158 | T18: =O18*M18/10000000 -> 0.064117248 | U18: =Q18-SUM(R18:T18) -> 0.10659492 | V18: =IFERROR(U18/Q18,0) -> 0.22166667 | W18: =Assumptions!F70 -> Illustrative (replace with pilot) | X18: =Assumptions!C28&" | "&Assumptions!D28 -> Ginger-Lemon Hot Drink | 15g single sachet
A19: =Assumptions!A71 -> FY22 | B19: =Assumptions!B71 -> GIN_T | C19: =Assumptions!B28 -> Premixes | D19: =Assumptions!C71 -> Modern | E19: =Assumptions!E28*(1+Assumptions!$C$11)^0 -> 10 | F19: =Assumptions!F28*(1+Assumptions!$C$12)^0 -> 4.35 | G19: =Assumptions!G28 -> 26 | H19: =Assumptions!D71 -> 291 | I19: =Assumptions!E71 -> 12.48 | J19: =Assumptions!$C$13 -> 0.95 | K19: =Assumptions!B41 -> 0.28 | L19: =Assumptions!C41+IF(Assumptions!$C$6="Downside",Assumptions!$C$9,0) -> 0.14 | M19: =Assumptions!E41 -> 1.7 | N19: =H19*I19*G19*IF(Assumptions!$C$6="Downside",1-Assumptions!$C$7,1) -> 94423.68 | O19: =N19*J19 -> 89702.496 | P19: =E19*(1-K19) -> 7.2 | Q19: =O19*P19/10000000 -> 0.064585797 | R19: =O19*F19/10000000+IF(Assumptions!$C$6="Downside",Q19*Assumptions!$C$8,0) -> 0.039020586 | S19: =Q19*L19 -> 0.0090420116 | T19: =O19*M19/10000000 -> 0.015249424 | U19: =Q19-SUM(R19:T19) -> 0.0012737754 | V19: =IFERROR(U19/Q19,0) -> 0.019722222 | W19: =Assumptions!F71 -> Illustrative (replace with pilot) | X19: =Assumptions!C28&" | "&Assumptions!D28 -> Ginger-Lemon Hot Drink | 15g single sachet
A20: =Assumptions!A72 -> FY22 | B20: =Assumptions!B72 -> GIN_T | C20: =Assumptions!B28 -> Premixes | D20: =Assumptions!C72 -> QCom | E20: =Assumptions!E28*(1+Assumptions!$C$11)^0 -> 10 | F20: =Assumptions!F28*(1+Assumptions!$C$12)^0 -> 4.35 | G20: =Assumptions!G28 -> 26 | H20: =Assumptions!D72 -> 116 | I20: =Assumptions!E72 -> 37.44 | J20: =Assumptions!$C$13 -> 0.95 | K20: =Assumptions!B42 -> 0.38 | L20: =Assumptions!C42+IF(Assumptions!$C$6="Downside",Assumptions!$C$9,0) -> 0.24 | M20: =Assumptions!E42 -> 2 | N20: =H20*I20*G20*IF(Assumptions!$C$6="Downside",1-Assumptions!$C$7,1) -> 112919.04 | O20: =N20*J20 -> 107273.09 | P20: =E20*(1-K20) -> 6.2 | Q20: =O20*P20/10000000 -> 0.066509315 | R20: =O20*F20/10000000+IF(Assumptions!$C$6="Downside",Q20*Assumptions!$C$8,0) -> 0.046663793 | S20: =Q20*L20 -> 0.015962235 | T20: =O20*M20/10000000 -> 0.021454618 | U20: =Q20-SUM(R20:T20) -> -0.017571332 | V20: =IFERROR(U20/Q20,0) -> -0.26419355 | W20: =Assumptions!F72 -> Illustrative (replace with pilot) | X20: =Assumptions!C28&" | "&Assumptions!D28 -> Ginger-Lemon Hot Drink | 15g single sachet
A21: =Assumptions!A73 -> FY22 | B21: =Assumptions!B73 -> GIN_L | C21: =Assumptions!B29 -> Premixes | D21: =Assumptions!C73 -> GT | E21: =Assumptions!E29*(1+Assumptions!$C$11)^0 -> 99 | F21: =Assumptions!F29*(1+Assumptions!$C$12)^0 -> 44 | G21: =Assumptions!G29 -> 26 | H21: =Assumptions!D73 -> 6240 | I21: =Assumptions!E73 -> 2.52 | J21: =Assumptions!$C$13 -> 0.95 | K21: =Assumptions!B40 -> 0.25 | L21: =Assumptions!C40+IF(Assumptions!$C$6="Downside",Assumptions!$C$9,0) -> 0.065 | M21: =Assumptions!E40 -> 1 | N21: =H21*I21*G21*IF(Assumptions!$C$6="Downside",1-Assumptions!$C$7,1) -> 408844.8 | O21: =N21*J21 -> 388402.56 | P21: =E21*(1-K21) -> 74.25 | Q21: =O21*P21/10000000 -> 2.883889 | R21: =O21*F21/10000000+IF(Assumptions!$C$6="Downside",Q21*Assumptions!$C$8,0) -> 1.7089713 | S21: =Q21*L21 -> 0.18745279 | T21: =O21*M21/10000000 -> 0.038840256 | U21: =Q21-SUM(R21:T21) -> 0.9486247 | V21: =IFERROR(U21/Q21,0) -> 0.32893939 | W21: =Assumptions!F73 -> Illustrative (replace with pilot) | X21: =Assumptions!C29&" | "&Assumptions!D29 -> Ginger-Lemon Hot Drink | 10-sachet pack
A22: =Assumptions!A74 -> FY22 | B22: =Assumptions!B74 -> GIN_L | C22: =Assumptions!B29 -> Premixes | D22: =Assumptions!C74 -> Modern | E22: =Assumptions!E29*(1+Assumptions!$C$11)^0 -> 99 | F22: =Assumptions!F29*(1+Assumptions!$C$12)^0 -> 44 | G22: =Assumptions!G29 -> 26 | H22: =Assumptions!D74 -> 218 | I22: =Assumptions!E74 -> 10.08 | J22: =Assumptions!$C$13 -> 0.95 | K22: =Assumptions!B41 -> 0.28 | L22: =Assumptions!C41+IF(Assumptions!$C$6="Downside",Assumptions!$C$9,0) -> 0.14 | M22: =Assumptions!E41 -> 1.7 | N22: =H22*I22*G22*IF(Assumptions!$C$6="Downside",1-Assumptions!$C$7,1) -> 57133.44 | O22: =N22*J22 -> 54276.768 | P22: =E22*(1-K22) -> 71.28 | Q22: =O22*P22/10000000 -> 0.3868848 | R22: =O22*F22/10000000+IF(Assumptions!$C$6="Downside",Q22*Assumptions!$C$8,0) -> 0.23881778 | S22: =Q22*L22 -> 0.054163872 | T22: =O22*M22/10000000 -> 0.0092270506 | U22: =Q22-SUM(R22:T22) -> 0.0846761 | V22: =IFERROR(U22/Q22,0) -> 0.21886644 | W22: =Assumptions!F74 -> Illustrative (replace with pilot) | X22: =Assumptions!C29&" | "&Assumptions!D29 -> Ginger-Lemon Hot Drink | 10-sachet pack
A23: =Assumptions!A75 -> FY22 | B23: =Assumptions!B75 -> GIN_L | C23: =Assumptions!B29 -> Premixes | D23: =Assumptions!C75 -> QCom | E23: =Assumptions!E29*(1+Assumptions!$C$11)^0 -> 99 | F23: =Assumptions!F29*(1+Assumptions!$C$12)^0 -> 44 | G23: =Assumptions!G29 -> 26 | H23: =Assumptions!D75 -> 87 | I23: =Assumptions!E75 -> 30.24 | J23: =Assumptions!$C$13 -> 0.95 | K23: =Assumptions!B42 -> 0.38 | L23: =Assumptions!C42+IF(Assumptions!$C$6="Downside",Assumptions!$C$9,0) -> 0.24 | M23: =Assumptions!E42 -> 2 | N23: =H23*I23*G23*IF(Assumptions!$C$6="Downside",1-Assumptions!$C$7,1) -> 68402.88 | O23: =N23*J23 -> 64982.736 | P23: =E23*(1-K23) -> 61.38 | Q23: =O23*P23/10000000 -> 0.39886403 | R23: =O23*F23/10000000+IF(Assumptions!$C$6="Downside",Q23*Assumptions!$C$8,0) -> 0.28592404 | S23: =Q23*L23 -> 0.095727368 | T23: =O23*M23/10000000 -> 0.012996547 | U23: =Q23-SUM(R23:T23) -> 0.0042160799 | V23: =IFERROR(U23/Q23,0) -> 0.010570218 | W23: =Assumptions!F75 -> Illustrative (replace with pilot) | X23: =Assumptions!C29&" | "&Assumptions!D29 -> Ginger-Lemon Hot Drink | 10-sachet pack
A24: =Assumptions!A76 -> FY22 | B24: =Assumptions!B76 -> BAD_T | C24: =Assumptions!B30 -> Premixes | D24: =Assumptions!C76 -> GT | E24: =Assumptions!E30*(1+Assumptions!$C$11)^0 -> 10 | F24: =Assumptions!F30*(1+Assumptions!$C$12)^0 -> 4.5 | G24: =Assumptions!G30 -> 26 | H24: =Assumptions!D76 -> 6720 | I24: =Assumptions!E76 -> 2.16 | J24: =Assumptions!$C$13 -> 0.95 | K24: =Assumptions!B40 -> 0.25 | L24: =Assumptions!C40+IF(Assumptions!$C$6="Downside",Assumptions!$C$9,0) -> 0.065 | M24: =Assumptions!E40 -> 1 | N24: =H24*I24*G24*IF(Assumptions!$C$6="Downside",1-Assumptions!$C$7,1) -> 377395.2 | O24: =N24*J24 -> 358525.44 | P24: =E24*(1-K24) -> 7.5 | Q24: =O24*P24/10000000 -> 0.26889408 | R24: =O24*F24/10000000+IF(Assumptions!$C$6="Downside",Q24*Assumptions!$C$8,0) -> 0.16133645 | S24: =Q24*L24 -> 0.017478115 | T24: =O24*M24/10000000 -> 0.035852544 | U24: =Q24-SUM(R24:T24) -> 0.054226973 | V24: =IFERROR(U24/Q24,0) -> 0.20166667 | W24: =Assumptions!F76 -> Illustrative (replace with pilot) | X24: =Assumptions!C30&" | "&Assumptions!D30 -> Badam-Elaichi Milk Mix | 15g single sachet
A25: =Assumptions!A77 -> FY22 | B25: =Assumptions!B77 -> BAD_T | C25: =Assumptions!B30 -> Premixes | D25: =Assumptions!C77 -> Modern | E25: =Assumptions!E30*(1+Assumptions!$C$11)^0 -> 10 | F25: =Assumptions!F30*(1+Assumptions!$C$12)^0 -> 4.5 | G25: =Assumptions!G30 -> 26 | H25: =Assumptions!D77 -> 235 | I25: =Assumptions!E77 -> 8.64 | J25: =Assumptions!$C$13 -> 0.95 | K25: =Assumptions!B41 -> 0.28 | L25: =Assumptions!C41+IF(Assumptions!$C$6="Downside",Assumptions!$C$9,0) -> 0.14 | M25: =Assumptions!E41 -> 1.7 | N25: =H25*I25*G25*IF(Assumptions!$C$6="Downside",1-Assumptions!$C$7,1) -> 52790.4 | O25: =N25*J25 -> 50150.88 | P25: =E25*(1-K25) -> 7.2 | Q25: =O25*P25/10000000 -> 0.036108634 | R25: =O25*F25/10000000+IF(Assumptions!$C$6="Downside",Q25*Assumptions!$C$8,0) -> 0.022567896 | S25: =Q25*L25 -> 0.0050552087 | T25: =O25*M25/10000000 -> 0.0085256496 | U25: =Q25-SUM(R25:T25) -> -4.0120704e-05 | V25: =IFERROR(U25/Q25,0) -> -0.0011111111 | W25: =Assumptions!F77 -> Illustrative (replace with pilot) | X25: =Assumptions!C30&" | "&Assumptions!D30 -> Badam-Elaichi Milk Mix | 15g single sachet
A26: =Assumptions!A78 -> FY22 | B26: =Assumptions!B78 -> BAD_T | C26: =Assumptions!B30 -> Premixes | D26: =Assumptions!C78 -> QCom | E26: =Assumptions!E30*(1+Assumptions!$C$11)^0 -> 10 | F26: =Assumptions!F30*(1+Assumptions!$C$12)^0 -> 4.5 | G26: =Assumptions!G30 -> 26 | H26: =Assumptions!D78 -> 94 | I26: =Assumptions!E78 -> 25.92 | J26: =Assumptions!$C$13 -> 0.95 | K26: =Assumptions!B42 -> 0.38 | L26: =Assumptions!C42+IF(Assumptions!$C$6="Downside",Assumptions!$C$9,0) -> 0.24 | M26: =Assumptions!E42 -> 2 | N26: =H26*I26*G26*IF(Assumptions!$C$6="Downside",1-Assumptions!$C$7,1) -> 63348.48 | O26: =N26*J26 -> 60181.056 | P26: =E26*(1-K26) -> 6.2 | Q26: =O26*P26/10000000 -> 0.037312255 | R26: =O26*F26/10000000+IF(Assumptions!$C$6="Downside",Q26*Assumptions!$C$8,0) -> 0.027081475 | S26: =Q26*L26 -> 0.0089549411 | T26: =O26*M26/10000000 -> 0.012036211 | U26: =Q26-SUM(R26:T26) -> -0.010760373 | V26: =IFERROR(U26/Q26,0) -> -0.2883871 | W26: =Assumptions!F78 -> Illustrative (replace with pilot) | X26: =Assumptions!C30&" | "&Assumptions!D30 -> Badam-Elaichi Milk Mix | 15g single sachet
A27: =Assumptions!A79 -> FY22 | B27: =Assumptions!B79 -> BAD_L | C27: =Assumptions!B31 -> Premixes | D27: =Assumptions!C79 -> GT | E27: =Assumptions!E31*(1+Assumptions!$C$11)^0 -> 99 | F27: =Assumptions!F31*(1+Assumptions!$C$12)^0 -> 45.5 | G27: =Assumptions!G31 -> 26 | H27: =Assumptions!D79 -> 5440 | I27: =Assumptions!E79 -> 1.98 | J27: =Assumptions!$C$13 -> 0.95 | K27: =Assumptions!B40 -> 0.25 | L27: =Assumptions!C40+IF(Assumptions!$C$6="Downside",Assumptions!$C$9,0) -> 0.065 | M27: =Assumptions!E40 -> 1 | N27: =H27*I27*G27*IF(Assumptions!$C$6="Downside",1-Assumptions!$C$7,1) -> 280051.2 | O27: =N27*J27 -> 266048.64 | P27: =E27*(1-K27) -> 74.25 | Q27: =O27*P27/10000000 -> 1.9754112 | R27: =O27*F27/10000000+IF(Assumptions!$C$6="Downside",Q27*Assumptions!$C$8,0) -> 1.2105213 | S27: =Q27*L27 -> 0.12840172 | T27: =O27*M27/10000000 -> 0.026604864 | U27: =Q27-SUM(R27:T27) -> 0.60988325 | V27: =IFERROR(U27/Q27,0) -> 0.30873737 | W27: =Assumptions!F79 -> Illustrative (replace with pilot) | X27: =Assumptions!C31&" | "&Assumptions!D31 -> Badam-Elaichi Milk Mix | 150g pouch
A28: =Assumptions!A80 -> FY22 | B28: =Assumptions!B80 -> BAD_L | C28: =Assumptions!B31 -> Premixes | D28: =Assumptions!C80 -> Modern | E28: =Assumptions!E31*(1+Assumptions!$C$11)^0 -> 99 | F28: =Assumptions!F31*(1+Assumptions!$C$12)^0 -> 45.5 | G28: =Assumptions!G31 -> 26 | H28: =Assumptions!D80 -> 190 | I28: =Assumptions!E80 -> 7.92 | J28: =Assumptions!$C$13 -> 0.95 | K28: =Assumptions!B41 -> 0.28 | L28: =Assumptions!C41+IF(Assumptions!$C$6="Downside",Assumptions!$C$9,0) -> 0.14 | M28: =Assumptions!E41 -> 1.7 | N28: =H28*I28*G28*IF(Assumptions!$C$6="Downside",1-Assumptions!$C$7,1) -> 39124.8 | O28: =N28*J28 -> 37168.56 | P28: =E28*(1-K28) -> 71.28 | Q28: =O28*P28/10000000 -> 0.2649375 | R28: =O28*F28/10000000+IF(Assumptions!$C$6="Downside",Q28*Assumptions!$C$8,0) -> 0.16911695 | S28: =Q28*L28 -> 0.037091249 | T28: =O28*M28/10000000 -> 0.0063186552 | U28: =Q28-SUM(R28:T28) -> 0.052410643 | V28: =IFERROR(U28/Q28,0) -> 0.19782267 | W28: =Assumptions!F80 -> Illustrative (replace with pilot) | X28: =Assumptions!C31&" | "&Assumptions!D31 -> Badam-Elaichi Milk Mix | 150g pouch
A29: =Assumptions!A81 -> FY22 | B29: =Assumptions!B81 -> BAD_L | C29: =Assumptions!B31 -> Premixes | D29: =Assumptions!C81 -> QCom | E29: =Assumptions!E31*(1+Assumptions!$C$11)^0 -> 99 | F29: =Assumptions!F31*(1+Assumptions!$C$12)^0 -> 45.5 | G29: =Assumptions!G31 -> 26 | H29: =Assumptions!D81 -> 76 | I29: =Assumptions!E81 -> 23.76 | J29: =Assumptions!$C$13 -> 0.95 | K29: =Assumptions!B42 -> 0.38 | L29: =Assumptions!C42+IF(Assumptions!$C$6="Downside",Assumptions!$C$9,0) -> 0.24 | M29: =Assumptions!E42 -> 2 | N29: =H29*I29*G29*IF(Assumptions!$C$6="Downside",1-Assumptions!$C$7,1) -> 46949.76 | O29: =N29*J29 -> 44602.272 | P29: =E29*(1-K29) -> 61.38 | Q29: =O29*P29/10000000 -> 0.27376875 | R29: =O29*F29/10000000+IF(Assumptions!$C$6="Downside",Q29*Assumptions!$C$8,0) -> 0.20294034 | S29: =Q29*L29 -> 0.065704499 | T29: =O29*M29/10000000 -> 0.0089204544 | U29: =Q29-SUM(R29:T29) -> -0.0037965454 | V29: =IFERROR(U29/Q29,0) -> -0.013867709 | W29: =Assumptions!F81 -> Illustrative (replace with pilot) | X29: =Assumptions!C31&" | "&Assumptions!D31 -> Badam-Elaichi Milk Mix | 150g pouch
A30: =Assumptions!A82 -> FY22 | B30: =Assumptions!B82 -> CHU_T | C30: =Assumptions!B32 -> Condiments | D30: =Assumptions!C82 -> GT | E30: =Assumptions!E32*(1+Assumptions!$C$11)^0 -> 10 | F30: =Assumptions!F32*(1+Assumptions!$C$12)^0 -> 4.8 | G30: =Assumptions!G32 -> 52 | H30: =Assumptions!D82 -> 6880 | I30: =Assumptions!E82 -> 1.74 | J30: =Assumptions!$C$13 -> 0.95 | K30: =Assumptions!B40 -> 0.25 | L30: =Assumptions!C40+IF(Assumptions!$C$6="Downside",Assumptions!$C$9,0) -> 0.065 | M30: =Assumptions!E40 -> 1 | N30: =H30*I30*G30*IF(Assumptions!$C$6="Downside",1-Assumptions!$C$7,1) -> 622502.4 | O30: =N30*J30 -> 591377.28 | P30: =E30*(1-K30) -> 7.5 | Q30: =O30*P30/10000000 -> 0.44353296 | R30: =O30*F30/10000000+IF(Assumptions!$C$6="Downside",Q30*Assumptions!$C$8,0) -> 0.28386109 | S30: =Q30*L30 -> 0.028829642 | T30: =O30*M30/10000000 -> 0.059137728 | U30: =Q30-SUM(R30:T30) -> 0.071704495 | V30: =IFERROR(U30/Q30,0) -> 0.16166667 | W30: =Assumptions!F82 -> Illustrative (replace with pilot) | X30: =Assumptions!C32&" | "&Assumptions!D32 -> Tamarind-Date Chutney | 20g sachet
A31: =Assumptions!A83 -> FY22 | B31: =Assumptions!B83 -> CHU_T | C31: =Assumptions!B32 -> Condiments | D31: =Assumptions!C83 -> Modern | E31: =Assumptions!E32*(1+Assumptions!$C$11)^0 -> 10 | F31: =Assumptions!F32*(1+Assumptions!$C$12)^0 -> 4.8 | G31: =Assumptions!G32 -> 52 | H31: =Assumptions!D83 -> 241 | I31: =Assumptions!E83 -> 6.96 | J31: =Assumptions!$C$13 -> 0.95 | K31: =Assumptions!B41 -> 0.28 | L31: =Assumptions!C41+IF(Assumptions!$C$6="Downside",Assumptions!$C$9,0) -> 0.14 | M31: =Assumptions!E41 -> 1.7 | N31: =H31*I31*G31*IF(Assumptions!$C$6="Downside",1-Assumptions!$C$7,1) -> 87222.72 | O31: =N31*J31 -> 82861.584 | P31: =E31*(1-K31) -> 7.2 | Q31: =O31*P31/10000000 -> 0.05966034 | R31: =O31*F31/10000000+IF(Assumptions!$C$6="Downside",Q31*Assumptions!$C$8,0) -> 0.03977356 | S31: =Q31*L31 -> 0.0083524477 | T31: =O31*M31/10000000 -> 0.014086469 | U31: =Q31-SUM(R31:T31) -> -0.0025521368 | V31: =IFERROR(U31/Q31,0) -> -0.042777778 | W31: =Assumptions!F83 -> Illustrative (replace with pilot) | X31: =Assumptions!C32&" | "&Assumptions!D32 -> Tamarind-Date Chutney | 20g sachet
A32: =Assumptions!A84 -> FY22 | B32: =Assumptions!B84 -> CHU_T | C32: =Assumptions!B32 -> Condiments | D32: =Assumptions!C84 -> QCom | E32: =Assumptions!E32*(1+Assumptions!$C$11)^0 -> 10 | F32: =Assumptions!F32*(1+Assumptions!$C$12)^0 -> 4.8 | G32: =Assumptions!G32 -> 52 | H32: =Assumptions!D84 -> 96 | I32: =Assumptions!E84 -> 20.88 | J32: =Assumptions!$C$13 -> 0.95 | K32: =Assumptions!B42 -> 0.38 | L32: =Assumptions!C42+IF(Assumptions!$C$6="Downside",Assumptions!$C$9,0) -> 0.24 | M32: =Assumptions!E42 -> 2 | N32: =H32*I32*G32*IF(Assumptions!$C$6="Downside",1-Assumptions!$C$7,1) -> 104232.96 | O32: =N32*J32 -> 99021.312 | P32: =E32*(1-K32) -> 6.2 | Q32: =O32*P32/10000000 -> 0.061393213 | R32: =O32*F32/10000000+IF(Assumptions!$C$6="Downside",Q32*Assumptions!$C$8,0) -> 0.04753023 | S32: =Q32*L32 -> 0.014734371 | T32: =O32*M32/10000000 -> 0.019804262 | U32: =Q32-SUM(R32:T32) -> -0.02067565 | V32: =IFERROR(U32/Q32,0) -> -0.33677419 | W32: =Assumptions!F84 -> Illustrative (replace with pilot) | X32: =Assumptions!C32&" | "&Assumptions!D32 -> Tamarind-Date Chutney | 20g sachet
A33: =Assumptions!A85 -> FY22 | B33: =Assumptions!B85 -> CHU_L | C33: =Assumptions!B33 -> Condiments | D33: =Assumptions!C85 -> GT | E33: =Assumptions!E33*(1+Assumptions!$C$11)^0 -> 99 | F33: =Assumptions!F33*(1+Assumptions!$C$12)^0 -> 47 | G33: =Assumptions!G33 -> 52 | H33: =Assumptions!D85 -> 5280 | I33: =Assumptions!E85 -> 1.32 | J33: =Assumptions!$C$13 -> 0.95 | K33: =Assumptions!B40 -> 0.25 | L33: =Assumptions!C40+IF(Assumptions!$C$6="Downside",Assumptions!$C$9,0) -> 0.065 | M33: =Assumptions!E40 -> 1 | N33: =H33*I33*G33*IF(Assumptions!$C$6="Downside",1-Assumptions!$C$7,1) -> 362419.2 | O33: =N33*J33 -> 344298.24 | P33: =E33*(1-K33) -> 74.25 | Q33: =O33*P33/10000000 -> 2.5564144 | R33: =O33*F33/10000000+IF(Assumptions!$C$6="Downside",Q33*Assumptions!$C$8,0) -> 1.6182017 | S33: =Q33*L33 -> 0.16616694 | T33: =O33*M33/10000000 -> 0.034429824 | U33: =Q33-SUM(R33:T33) -> 0.73761594 | V33: =IFERROR(U33/Q33,0) -> 0.28853535 | W33: =Assumptions!F85 -> Illustrative (replace with pilot) | X33: =Assumptions!C33&" | "&Assumptions!D33 -> Tamarind-Date Chutney | 200g pack
A34: =Assumptions!A86 -> FY22 | B34: =Assumptions!B86 -> CHU_L | C34: =Assumptions!B33 -> Condiments | D34: =Assumptions!C86 -> Modern | E34: =Assumptions!E33*(1+Assumptions!$C$11)^0 -> 99 | F34: =Assumptions!F33*(1+Assumptions!$C$12)^0 -> 47 | G34: =Assumptions!G33 -> 52 | H34: =Assumptions!D86 -> 185 | I34: =Assumptions!E86 -> 5.28 | J34: =Assumptions!$C$13 -> 0.95 | K34: =Assumptions!B41 -> 0.28 | L34: =Assumptions!C41+IF(Assumptions!$C$6="Downside",Assumptions!$C$9,0) -> 0.14 | M34: =Assumptions!E41 -> 1.7 | N34: =H34*I34*G34*IF(Assumptions!$C$6="Downside",1-Assumptions!$C$7,1) -> 50793.6 | O34: =N34*J34 -> 48253.92 | P34: =E34*(1-K34) -> 71.28 | Q34: =O34*P34/10000000 -> 0.34395394 | R34: =O34*F34/10000000+IF(Assumptions!$C$6="Downside",Q34*Assumptions!$C$8,0) -> 0.22679342 | S34: =Q34*L34 -> 0.048153552 | T34: =O34*M34/10000000 -> 0.0082031664 | U34: =Q34-SUM(R34:T34) -> 0.0608038 | V34: =IFERROR(U34/Q34,0) -> 0.1767789 | W34: =Assumptions!F86 -> Illustrative (replace with pilot) | X34: =Assumptions!C33&" | "&Assumptions!D33 -> Tamarind-Date Chutney | 200g pack
A35: =Assumptions!A87 -> FY22 | B35: =Assumptions!B87 -> CHU_L | C35: =Assumptions!B33 -> Condiments | D35: =Assumptions!C87 -> QCom | E35: =Assumptions!E33*(1+Assumptions!$C$11)^0 -> 99 | F35: =Assumptions!F33*(1+Assumptions!$C$12)^0 -> 47 | G35: =Assumptions!G33 -> 52 | H35: =Assumptions!D87 -> 74 | I35: =Assumptions!E87 -> 15.84 | J35: =Assumptions!$C$13 -> 0.95 | K35: =Assumptions!B42 -> 0.38 | L35: =Assumptions!C42+IF(Assumptions!$C$6="Downside",Assumptions!$C$9,0) -> 0.24 | M35: =Assumptions!E42 -> 2 | N35: =H35*I35*G35*IF(Assumptions!$C$6="Downside",1-Assumptions!$C$7,1) -> 60952.32 | O35: =N35*J35 -> 57904.704 | P35: =E35*(1-K35) -> 61.38 | Q35: =O35*P35/10000000 -> 0.35541907 | R35: =O35*F35/10000000+IF(Assumptions!$C$6="Downside",Q35*Assumptions!$C$8,0) -> 0.27215211 | S35: =Q35*L35 -> 0.085300578 | T35: =O35*M35/10000000 -> 0.011580941 | U35: =Q35-SUM(R35:T35) -> -0.013614554 | V35: =IFERROR(U35/Q35,0) -> -0.038305637 | W35: =Assumptions!F87 -> Illustrative (replace with pilot) | X35: =Assumptions!C33&" | "&Assumptions!D33 -> Tamarind-Date Chutney | 200g pack
A36: =Assumptions!A88 -> FY22 | B36: =Assumptions!B88 -> PIC_T | C36: =Assumptions!B34 -> Condiments | D36: =Assumptions!C88 -> GT | E36: =Assumptions!E34*(1+Assumptions!$C$11)^0 -> 10 | F36: =Assumptions!F34*(1+Assumptions!$C$12)^0 -> 4.7 | G36: =Assumptions!G34 -> 52 | H36: =Assumptions!D88 -> 6720 | I36: =Assumptions!E88 -> 1.62 | J36: =Assumptions!$C$13 -> 0.95 | K36: =Assumptions!B40 -> 0.25 | L36: =Assumptions!C40+IF(Assumptions!$C$6="Downside",Assumptions!$C$9,0) -> 0.065 | M36: =Assumptions!E40 -> 1 | N36: =H36*I36*G36*IF(Assumptions!$C$6="Downside",1-Assumptions!$C$7,1) -> 566092.8 | O36: =N36*J36 -> 537788.16 | P36: =E36*(1-K36) -> 7.5 | Q36: =O36*P36/10000000 -> 0.40334112 | R36: =O36*F36/10000000+IF(Assumptions!$C$6="Downside",Q36*Assumptions!$C$8,0) -> 0.25276044 | S36: =Q36*L36 -> 0.026217173 | T36: =O36*M36/10000000 -> 0.053778816 | U36: =Q36-SUM(R36:T36) -> 0.070584696 | V36: =IFERROR(U36/Q36,0) -> 0.175 | W36: =Assumptions!F88 -> Illustrative (replace with pilot) | X36: =Assumptions!C34&" | "&Assumptions!D34 -> Lime Pickle | 20g sachet
A37: =Assumptions!A89 -> FY22 | B37: =Assumptions!B89 -> PIC_T | C37: =Assumptions!B34 -> Condiments | D37: =Assumptions!C89 -> Modern | E37: =Assumptions!E34*(1+Assumptions!$C$11)^0 -> 10 | F37: =Assumptions!F34*(1+Assumptions!$C$12)^0 -> 4.7 | G37: =Assumptions!G34 -> 52 | H37: =Assumptions!D89 -> 235 | I37: =Assumptions!E89 -> 6.48 | J37: =Assumptions!$C$13 -> 0.95 | K37: =Assumptions!B41 -> 0.28 | L37: =Assumptions!C41+IF(Assumptions!$C$6="Downside",Assumptions!$C$9,0) -> 0.14 | M37: =Assumptions!E41 -> 1.7 | N37: =H37*I37*G37*IF(Assumptions!$C$6="Downside",1-Assumptions!$C$7,1) -> 79185.6 | O37: =N37*J37 -> 75226.32 | P37: =E37*(1-K37) -> 7.2 | Q37: =O37*P37/10000000 -> 0.05416295 | R37: =O37*F37/10000000+IF(Assumptions!$C$6="Downside",Q37*Assumptions!$C$8,0) -> 0.03535637 | S37: =Q37*L37 -> 0.0075828131 | T37: =O37*M37/10000000 -> 0.012788474 | U37: =Q37-SUM(R37:T37) -> -0.0015647075 | V37: =IFERROR(U37/Q37,0) -> -0.028888889 | W37: =Assumptions!F89 -> Illustrative (replace with pilot) | X37: =Assumptions!C34&" | "&Assumptions!D34 -> Lime Pickle | 20g sachet
A38: =Assumptions!A90 -> FY22 | B38: =Assumptions!B90 -> PIC_T | C38: =Assumptions!B34 -> Condiments | D38: =Assumptions!C90 -> QCom | E38: =Assumptions!E34*(1+Assumptions!$C$11)^0 -> 10 | F38: =Assumptions!F34*(1+Assumptions!$C$12)^0 -> 4.7 | G38: =Assumptions!G34 -> 52 | H38: =Assumptions!D90 -> 94 | I38: =Assumptions!E90 -> 19.44 | J38: =Assumptions!$C$13 -> 0.95 | K38: =Assumptions!B42 -> 0.38 | L38: =Assumptions!C42+IF(Assumptions!$C$6="Downside",Assumptions!$C$9,0) -> 0.24 | M38: =Assumptions!E42 -> 2 | N38: =H38*I38*G38*IF(Assumptions!$C$6="Downside",1-Assumptions!$C$7,1) -> 95022.72 | O38: =N38*J38 -> 90271.584 | P38: =E38*(1-K38) -> 6.2 | Q38: =O38*P38/10000000 -> 0.055968382 | R38: =O38*F38/10000000+IF(Assumptions!$C$6="Downside",Q38*Assumptions!$C$8,0) -> 0.042427644 | S38: =Q38*L38 -> 0.013432412 | T38: =O38*M38/10000000 -> 0.018054317 | U38: =Q38-SUM(R38:T38) -> -0.017945991 | V38: =IFERROR(U38/Q38,0) -> -0.32064516 | W38: =Assumptions!F90 -> Illustrative (replace with pilot) | X38: =Assumptions!C34&" | "&Assumptions!D34 -> Lime Pickle | 20g sachet
A39: =Assumptions!A91 -> FY22 | B39: =Assumptions!B91 -> PIC_L | C39: =Assumptions!B35 -> Condiments | D39: =Assumptions!C91 -> GT | E39: =Assumptions!E35*(1+Assumptions!$C$11)^0 -> 99 | F39: =Assumptions!F35*(1+Assumptions!$C$12)^0 -> 46.5 | G39: =Assumptions!G35 -> 52 | H39: =Assumptions!D91 -> 5920 | I39: =Assumptions!E91 -> 1.32 | J39: =Assumptions!$C$13 -> 0.95 | K39: =Assumptions!B40 -> 0.25 | L39: =Assumptions!C40+IF(Assumptions!$C$6="Downside",Assumptions!$C$9,0) -> 0.065 | M39: =Assumptions!E40 -> 1 | N39: =H39*I39*G39*IF(Assumptions!$C$6="Downside",1-Assumptions!$C$7,1) -> 406348.8 | O39: =N39*J39 -> 386031.36 | P39: =E39*(1-K39) -> 74.25 | Q39: =O39*P39/10000000 -> 2.8662828 | R39: =O39*F39/10000000+IF(Assumptions!$C$6="Downside",Q39*Assumptions!$C$8,0) -> 1.7950458 | S39: =Q39*L39 -> 0.18630839 | T39: =O39*M39/10000000 -> 0.038603136 | U39: =Q39-SUM(R39:T39) -> 0.8463255 | V39: =IFERROR(U39/Q39,0) -> 0.29526936 | W39: =Assumptions!F91 -> Illustrative (replace with pilot) | X39: =Assumptions!C35&" | "&Assumptions!D35 -> Lime Pickle | 200g pack
A40: =Assumptions!A92 -> FY22 | B40: =Assumptions!B92 -> PIC_L | C40: =Assumptions!B35 -> Condiments | D40: =Assumptions!C92 -> Modern | E40: =Assumptions!E35*(1+Assumptions!$C$11)^0 -> 99 | F40: =Assumptions!F35*(1+Assumptions!$C$12)^0 -> 46.5 | G40: =Assumptions!G35 -> 52 | H40: =Assumptions!D92 -> 207 | I40: =Assumptions!E92 -> 5.28 | J40: =Assumptions!$C$13 -> 0.95 | K40: =Assumptions!B41 -> 0.28 | L40: =Assumptions!C41+IF(Assumptions!$C$6="Downside",Assumptions!$C$9,0) -> 0.14 | M40: =Assumptions!E41 -> 1.7 | N40: =H40*I40*G40*IF(Assumptions!$C$6="Downside",1-Assumptions!$C$7,1) -> 56833.92 | O40: =N40*J40 -> 53992.224 | P40: =E40*(1-K40) -> 71.28 | Q40: =O40*P40/10000000 -> 0.38485657 | R40: =O40*F40/10000000+IF(Assumptions!$C$6="Downside",Q40*Assumptions!$C$8,0) -> 0.25106384 | S40: =Q40*L40 -> 0.05387992 | T40: =O40*M40/10000000 -> 0.0091786781 | U40: =Q40-SUM(R40:T40) -> 0.070734133 | V40: =IFERROR(U40/Q40,0) -> 0.18379349 | W40: =Assumptions!F92 -> Illustrative (replace with pilot) | X40: =Assumptions!C35&" | "&Assumptions!D35 -> Lime Pickle | 200g pack
A41: =Assumptions!A93 -> FY22 | B41: =Assumptions!B93 -> PIC_L | C41: =Assumptions!B35 -> Condiments | D41: =Assumptions!C93 -> QCom | E41: =Assumptions!E35*(1+Assumptions!$C$11)^0 -> 99 | F41: =Assumptions!F35*(1+Assumptions!$C$12)^0 -> 46.5 | G41: =Assumptions!G35 -> 52 | H41: =Assumptions!D93 -> 83 | I41: =Assumptions!E93 -> 15.84 | J41: =Assumptions!$C$13 -> 0.95 | K41: =Assumptions!B42 -> 0.38 | L41: =Assumptions!C42+IF(Assumptions!$C$6="Downside",Assumptions!$C$9,0) -> 0.24 | M41: =Assumptions!E42 -> 2 | N41: =H41*I41*G41*IF(Assumptions!$C$6="Downside",1-Assumptions!$C$7,1) -> 68365.44 | O41: =N41*J41 -> 64947.168 | P41: =E41*(1-K41) -> 61.38 | Q41: =O41*P41/10000000 -> 0.39864572 | R41: =O41*F41/10000000+IF(Assumptions!$C$6="Downside",Q41*Assumptions!$C$8,0) -> 0.30200433 | S41: =Q41*L41 -> 0.095674972 | T41: =O41*M41/10000000 -> 0.012989434 | U41: =Q41-SUM(R41:T41) -> -0.01202302 | V41: =IFERROR(U41/Q41,0) -> -0.030159661 | W41: =Assumptions!F93 -> Illustrative (replace with pilot) | X41: =Assumptions!C35&" | "&Assumptions!D35 -> Lime Pickle | 200g pack
A42: =Assumptions!A94 -> FY23 | B42: =Assumptions!B94 -> SAB_T | C42: =Assumptions!B24 -> Spices | D42: =Assumptions!C94 -> GT | E42: =Assumptions!E24*(1+Assumptions!$C$11)^1 -> 10 | F42: =Assumptions!F24*(1+Assumptions!$C$12)^1 -> 5.25 | G42: =Assumptions!G24 -> 52 | H42: =Assumptions!D94 -> 36400 | I42: =Assumptions!E94 -> 3.78 | J42: =Assumptions!$C$13 -> 0.95 | K42: =Assumptions!B40 -> 0.25 | L42: =Assumptions!C40+IF(Assumptions!$C$6="Downside",Assumptions!$C$9,0) -> 0.065 | M42: =Assumptions!E40 -> 1 | N42: =H42*I42*G42*IF(Assumptions!$C$6="Downside",1-Assumptions!$C$7,1) -> 7154784 | O42: =N42*J42 -> 6797044.8 | P42: =E42*(1-K42) -> 7.5 | Q42: =O42*P42/10000000 -> 5.0977836 | R42: =O42*F42/10000000+IF(Assumptions!$C$6="Downside",Q42*Assumptions!$C$8,0) -> 3.5684485 | S42: =Q42*L42 -> 0.33135593 | T42: =O42*M42/10000000 -> 0.67970448 | U42: =Q42-SUM(R42:T42) -> 0.51827467 | V42: =IFERROR(U42/Q42,0) -> 0.10166667 | W42: =Assumptions!F94 -> Illustrative (replace with pilot) | X42: =Assumptions!C24&" | "&Assumptions!D24 -> Everyday Sabzi Masala | 8g trial
A43: =Assumptions!A95 -> FY23 | B43: =Assumptions!B95 -> SAB_T | C43: =Assumptions!B24 -> Spices | D43: =Assumptions!C95 -> Modern | E43: =Assumptions!E24*(1+Assumptions!$C$11)^1 -> 10 | F43: =Assumptions!F24*(1+Assumptions!$C$12)^1 -> 5.25 | G43: =Assumptions!G24 -> 52 | H43: =Assumptions!D95 -> 1274 | I43: =Assumptions!E95 -> 15.14 | J43: =Assumptions!$C$13 -> 0.95 | K43: =Assumptions!B41 -> 0.28 | L43: =Assumptions!C41+IF(Assumptions!$C$6="Downside",Assumptions!$C$9,0) -> 0.14 | M43: =Assumptions!E41 -> 1.7 | N43: =H43*I43*G43*IF(Assumptions!$C$6="Downside",1-Assumptions!$C$7,1) -> 1002994.7 | O43: =N43*J43 -> 952844.98 | P43: =E43*(1-K43) -> 7.2 | Q43: =O43*P43/10000000 -> 0.68604839 | R43: =O43*F43/10000000+IF(Assumptions!$C$6="Downside",Q43*Assumptions!$C$8,0) -> 0.50024362 | S43: =Q43*L43 -> 0.096046774 | T43: =O43*M43/10000000 -> 0.16198365 | U43: =Q43-SUM(R43:T43) -> -0.07222565 | V43: =IFERROR(U43/Q43,0) -> -0.10527778 | W43: =Assumptions!F95 -> Illustrative (replace with pilot) | X43: =Assumptions!C24&" | "&Assumptions!D24 -> Everyday Sabzi Masala | 8g trial
A44: =Assumptions!A96 -> FY23 | B44: =Assumptions!B96 -> SAB_T | C44: =Assumptions!B24 -> Spices | D44: =Assumptions!C96 -> QCom | E44: =Assumptions!E24*(1+Assumptions!$C$11)^1 -> 10 | F44: =Assumptions!F24*(1+Assumptions!$C$12)^1 -> 5.25 | G44: =Assumptions!G24 -> 52 | H44: =Assumptions!D96 -> 510 | I44: =Assumptions!E96 -> 45.41 | J44: =Assumptions!$C$13 -> 0.95 | K44: =Assumptions!B42 -> 0.38 | L44: =Assumptions!C42+IF(Assumptions!$C$6="Downside",Assumptions!$C$9,0) -> 0.24 | M44: =Assumptions!E42 -> 2 | N44: =H44*I44*G44*IF(Assumptions!$C$6="Downside",1-Assumptions!$C$7,1) -> 1204273.2 | O44: =N44*J44 -> 1144059.5 | P44: =E44*(1-K44) -> 6.2 | Q44: =O44*P44/10000000 -> 0.70931691 | R44: =O44*F44/10000000+IF(Assumptions!$C$6="Downside",Q44*Assumptions!$C$8,0) -> 0.60063126 | S44: =Q44*L44 -> 0.17023606 | T44: =O44*M44/10000000 -> 0.22881191 | U44: =Q44-SUM(R44:T44) -> -0.29036231 | V44: =IFERROR(U44/Q44,0) -> -0.40935484 | W44: =Assumptions!F96 -> Illustrative (replace with pilot) | X44: =Assumptions!C24&" | "&Assumptions!D24 -> Everyday Sabzi Masala | 8g trial
A45: =Assumptions!A97 -> FY23 | B45: =Assumptions!B97 -> SAB_L | C45: =Assumptions!B25 -> Spices | D45: =Assumptions!C97 -> GT | E45: =Assumptions!E25*(1+Assumptions!$C$11)^1 -> 49 | F45: =Assumptions!F25*(1+Assumptions!$C$12)^1 -> 23 | G45: =Assumptions!G25 -> 52 | H45: =Assumptions!D97 -> 42000 | I45: =Assumptions!E97 -> 4.58 | J45: =Assumptions!$C$13 -> 0.95 | K45: =Assumptions!B40 -> 0.25 | L45: =Assumptions!C40+IF(Assumptions!$C$6="Downside",Assumptions!$C$9,0) -> 0.065 | M45: =Assumptions!E40 -> 1 | N45: =H45*I45*G45*IF(Assumptions!$C$6="Downside",1-Assumptions!$C$7,1) -> 10002720 | O45: =N45*J45 -> 9502584 | P45: =E45*(1-K45) -> 36.75 | Q45: =O45*P45/10000000 -> 34.921996 | R45: =O45*F45/10000000+IF(Assumptions!$C$6="Downside",Q45*Assumptions!$C$8,0) -> 21.855943 | S45: =Q45*L45 -> 2.2699298 | T45: =O45*M45/10000000 -> 0.9502584 | U45: =Q45-SUM(R45:T45) -> 9.8458648 | V45: =IFERROR(U45/Q45,0) -> 0.28193878 | W45: =Assumptions!F97 -> Illustrative (replace with pilot) | X45: =Assumptions!C25&" | "&Assumptions!D25 -> Everyday Sabzi Masala | 50g pouch
A46: =Assumptions!A98 -> FY23 | B46: =Assumptions!B98 -> SAB_L | C46: =Assumptions!B25 -> Spices | D46: =Assumptions!C98 -> Modern | E46: =Assumptions!E25*(1+Assumptions!$C$11)^1 -> 49 | F46: =Assumptions!F25*(1+Assumptions!$C$12)^1 -> 23 | G46: =Assumptions!G25 -> 52 | H46: =Assumptions!D98 -> 1470 | I46: =Assumptions!E98 -> 18.3 | J46: =Assumptions!$C$13 -> 0.95 | K46: =Assumptions!B41 -> 0.28 | L46: =Assumptions!C41+IF(Assumptions!$C$6="Downside",Assumptions!$C$9,0) -> 0.14 | M46: =Assumptions!E41 -> 1.7 | N46: =H46*I46*G46*IF(Assumptions!$C$6="Downside",1-Assumptions!$C$7,1) -> 1398852 | O46: =N46*J46 -> 1328909.4 | P46: =E46*(1-K46) -> 35.28 | Q46: =O46*P46/10000000 -> 4.6883924 | R46: =O46*F46/10000000+IF(Assumptions!$C$6="Downside",Q46*Assumptions!$C$8,0) -> 3.0564916 | S46: =Q46*L46 -> 0.65637493 | T46: =O46*M46/10000000 -> 0.2259146 | U46: =Q46-SUM(R46:T46) -> 0.74961121 | V46: =IFERROR(U46/Q46,0) -> 0.15988662 | W46: =Assumptions!F98 -> Illustrative (replace with pilot) | X46: =Assumptions!C25&" | "&Assumptions!D25 -> Everyday Sabzi Masala | 50g pouch
A47: =Assumptions!A99 -> FY23 | B47: =Assumptions!B99 -> SAB_L | C47: =Assumptions!B25 -> Spices | D47: =Assumptions!C99 -> QCom | E47: =Assumptions!E25*(1+Assumptions!$C$11)^1 -> 49 | F47: =Assumptions!F25*(1+Assumptions!$C$12)^1 -> 23 | G47: =Assumptions!G25 -> 52 | H47: =Assumptions!D99 -> 588 | I47: =Assumptions!E99 -> 54.91 | J47: =Assumptions!$C$13 -> 0.95 | K47: =Assumptions!B42 -> 0.38 | L47: =Assumptions!C42+IF(Assumptions!$C$6="Downside",Assumptions!$C$9,0) -> 0.24 | M47: =Assumptions!E42 -> 2 | N47: =H47*I47*G47*IF(Assumptions!$C$6="Downside",1-Assumptions!$C$7,1) -> 1678928.2 | O47: =N47*J47 -> 1594981.8 | P47: =E47*(1-K47) -> 30.38 | Q47: =O47*P47/10000000 -> 4.8455546 | R47: =O47*F47/10000000+IF(Assumptions!$C$6="Downside",Q47*Assumptions!$C$8,0) -> 3.668458 | S47: =Q47*L47 -> 1.1629331 | T47: =O47*M47/10000000 -> 0.31899635 | U47: =Q47-SUM(R47:T47) -> -0.30483291 | V47: =IFERROR(U47/Q47,0) -> -0.062909809 | W47: =Assumptions!F99 -> Illustrative (replace with pilot) | X47: =Assumptions!C25&" | "&Assumptions!D25 -> Everyday Sabzi Masala | 50g pouch
A48: =Assumptions!A100 -> FY23 | B48: =Assumptions!B100 -> GAR_T | C48: =Assumptions!B26 -> Spices | D48: =Assumptions!C100 -> GT | E48: =Assumptions!E26*(1+Assumptions!$C$11)^1 -> 10 | F48: =Assumptions!F26*(1+Assumptions!$C$12)^1 -> 5.35 | G48: =Assumptions!G26 -> 52 | H48: =Assumptions!D100 -> 31920 | I48: =Assumptions!E100 -> 3.26 | J48: =Assumptions!$C$13 -> 0.95 | K48: =Assumptions!B40 -> 0.25 | L48: =Assumptions!C40+IF(Assumptions!$C$6="Downside",Assumptions!$C$9,0) -> 0.065 | M48: =Assumptions!E40 -> 1 | N48: =H48*I48*G48*IF(Assumptions!$C$6="Downside",1-Assumptions!$C$7,1) -> 5411078.4 | O48: =N48*J48 -> 5140524.5 | P48: =E48*(1-K48) -> 7.5 | Q48: =O48*P48/10000000 -> 3.8553934 | R48: =O48*F48/10000000+IF(Assumptions!$C$6="Downside",Q48*Assumptions!$C$8,0) -> 2.7501806 | S48: =Q48*L48 -> 0.25060057 | T48: =O48*M48/10000000 -> 0.51405245 | U48: =Q48-SUM(R48:T48) -> 0.34055975 | V48: =IFERROR(U48/Q48,0) -> 0.088333333 | W48: =Assumptions!F100 -> Illustrative (replace with pilot) | X48: =Assumptions!C26&" | "&Assumptions!D26 -> Garam Masala | 5g trial
A49: =Assumptions!A101 -> FY23 | B49: =Assumptions!B101 -> GAR_T | C49: =Assumptions!B26 -> Spices | D49: =Assumptions!C101 -> Modern | E49: =Assumptions!E26*(1+Assumptions!$C$11)^1 -> 10 | F49: =Assumptions!F26*(1+Assumptions!$C$12)^1 -> 5.35 | G49: =Assumptions!G26 -> 52 | H49: =Assumptions!D101 -> 1117 | I49: =Assumptions!E101 -> 13.02 | J49: =Assumptions!$C$13 -> 0.95 | K49: =Assumptions!B41 -> 0.28 | L49: =Assumptions!C41+IF(Assumptions!$C$6="Downside",Assumptions!$C$9,0) -> 0.14 | M49: =Assumptions!E41 -> 1.7 | N49: =H49*I49*G49*IF(Assumptions!$C$6="Downside",1-Assumptions!$C$7,1) -> 756253.68 | O49: =N49*J49 -> 718441 | P49: =E49*(1-K49) -> 7.2 | Q49: =O49*P49/10000000 -> 0.51727752 | R49: =O49*F49/10000000+IF(Assumptions!$C$6="Downside",Q49*Assumptions!$C$8,0) -> 0.38436593 | S49: =Q49*L49 -> 0.072418852 | T49: =O49*M49/10000000 -> 0.12213497 | U49: =Q49-SUM(R49:T49) -> -0.061642237 | V49: =IFERROR(U49/Q49,0) -> -0.11916667 | W49: =Assumptions!F101 -> Illustrative (replace with pilot) | X49: =Assumptions!C26&" | "&Assumptions!D26 -> Garam Masala | 5g trial
A50: =Assumptions!A102 -> FY23 | B50: =Assumptions!B102 -> GAR_T | C50: =Assumptions!B26 -> Spices | D50: =Assumptions!C102 -> QCom | E50: =Assumptions!E26*(1+Assumptions!$C$11)^1 -> 10 | F50: =Assumptions!F26*(1+Assumptions!$C$12)^1 -> 5.35 | G50: =Assumptions!G26 -> 52 | H50: =Assumptions!D102 -> 447 | I50: =Assumptions!E102 -> 39.07 | J50: =Assumptions!$C$13 -> 0.95 | K50: =Assumptions!B42 -> 0.38 | L50: =Assumptions!C42+IF(Assumptions!$C$6="Downside",Assumptions!$C$9,0) -> 0.24 | M50: =Assumptions!E42 -> 2 | N50: =H50*I50*G50*IF(Assumptions!$C$6="Downside",1-Assumptions!$C$7,1) -> 908143.08 | O50: =N50*J50 -> 862735.93 | P50: =E50*(1-K50) -> 6.2 | Q50: =O50*P50/10000000 -> 0.53489627 | R50: =O50*F50/10000000+IF(Assumptions!$C$6="Downside",Q50*Assumptions!$C$8,0) -> 0.46156372 | S50: =Q50*L50 -> 0.12837511 | T50: =O50*M50/10000000 -> 0.17254719 | U50: =Q50-SUM(R50:T50) -> -0.22758974 | V50: =IFERROR(U50/Q50,0) -> -0.42548387 | W50: =Assumptions!F102 -> Illustrative (replace with pilot) | X50: =Assumptions!C26&" | "&Assumptions!D26 -> Garam Masala | 5g trial
A51: =Assumptions!A103 -> FY23 | B51: =Assumptions!B103 -> GAR_L | C51: =Assumptions!B27 -> Spices | D51: =Assumptions!C103 -> GT | E51: =Assumptions!E27*(1+Assumptions!$C$11)^1 -> 49 | F51: =Assumptions!F27*(1+Assumptions!$C$12)^1 -> 23.5 | G51: =Assumptions!G27 -> 52 | H51: =Assumptions!D103 -> 39200 | I51: =Assumptions!E103 -> 3.87 | J51: =Assumptions!$C$13 -> 0.95 | K51: =Assumptions!B40 -> 0.25 | L51: =Assumptions!C40+IF(Assumptions!$C$6="Downside",Assumptions!$C$9,0) -> 0.065 | M51: =Assumptions!E40 -> 1 | N51: =H51*I51*G51*IF(Assumptions!$C$6="Downside",1-Assumptions!$C$7,1) -> 7888608 | O51: =N51*J51 -> 7494177.6 | P51: =E51*(1-K51) -> 36.75 | Q51: =O51*P51/10000000 -> 27.541103 | R51: =O51*F51/10000000+IF(Assumptions!$C$6="Downside",Q51*Assumptions!$C$8,0) -> 17.611317 | S51: =Q51*L51 -> 1.7901717 | T51: =O51*M51/10000000 -> 0.74941776 | U51: =Q51-SUM(R51:T51) -> 7.3901959 | V51: =IFERROR(U51/Q51,0) -> 0.26833333 | W51: =Assumptions!F103 -> Illustrative (replace with pilot) | X51: =Assumptions!C27&" | "&Assumptions!D27 -> Garam Masala | 50g pouch
A52: =Assumptions!A104 -> FY23 | B52: =Assumptions!B104 -> GAR_L | C52: =Assumptions!B27 -> Spices | D52: =Assumptions!C104 -> Modern | E52: =Assumptions!E27*(1+Assumptions!$C$11)^1 -> 49 | F52: =Assumptions!F27*(1+Assumptions!$C$12)^1 -> 23.5 | G52: =Assumptions!G27 -> 52 | H52: =Assumptions!D104 -> 1372 | I52: =Assumptions!E104 -> 15.49 | J52: =Assumptions!$C$13 -> 0.95 | K52: =Assumptions!B41 -> 0.28 | L52: =Assumptions!C41+IF(Assumptions!$C$6="Downside",Assumptions!$C$9,0) -> 0.14 | M52: =Assumptions!E41 -> 1.7 | N52: =H52*I52*G52*IF(Assumptions!$C$6="Downside",1-Assumptions!$C$7,1) -> 1105118.6 | O52: =N52*J52 -> 1049862.6 | P52: =E52*(1-K52) -> 35.28 | Q52: =O52*P52/10000000 -> 3.7039154 | R52: =O52*F52/10000000+IF(Assumptions!$C$6="Downside",Q52*Assumptions!$C$8,0) -> 2.4671772 | S52: =Q52*L52 -> 0.51854815 | T52: =O52*M52/10000000 -> 0.17847665 | U52: =Q52-SUM(R52:T52) -> 0.53971338 | V52: =IFERROR(U52/Q52,0) -> 0.14571429 | W52: =Assumptions!F104 -> Illustrative (replace with pilot) | X52: =Assumptions!C27&" | "&Assumptions!D27 -> Garam Masala | 50g pouch
A53: =Assumptions!A105 -> FY23 | B53: =Assumptions!B105 -> GAR_L | C53: =Assumptions!B27 -> Spices | D53: =Assumptions!C105 -> QCom | E53: =Assumptions!E27*(1+Assumptions!$C$11)^1 -> 49 | F53: =Assumptions!F27*(1+Assumptions!$C$12)^1 -> 23.5 | G53: =Assumptions!G27 -> 52 | H53: =Assumptions!D105 -> 549 | I53: =Assumptions!E105 -> 46.46 | J53: =Assumptions!$C$13 -> 0.95 | K53: =Assumptions!B42 -> 0.38 | L53: =Assumptions!C42+IF(Assumptions!$C$6="Downside",Assumptions!$C$9,0) -> 0.24 | M53: =Assumptions!E42 -> 2 | N53: =H53*I53*G53*IF(Assumptions!$C$6="Downside",1-Assumptions!$C$7,1) -> 1326340.1 | O53: =N53*J53 -> 1260023.1 | P53: =E53*(1-K53) -> 30.38 | Q53: =O53*P53/10000000 -> 3.8279501 | R53: =O53*F53/10000000+IF(Assumptions!$C$6="Downside",Q53*Assumptions!$C$8,0) -> 2.9610542 | S53: =Q53*L53 -> 0.91870803 | T53: =O53*M53/10000000 -> 0.25200462 | U53: =Q53-SUM(R53:T53) -> -0.30381676 | V53: =IFERROR(U53/Q53,0) -> -0.079368005 | W53: =Assumptions!F105 -> Illustrative (replace with pilot) | X53: =Assumptions!C27&" | "&Assumptions!D27 -> Garam Masala | 50g pouch
A54: =Assumptions!A106 -> FY23 | B54: =Assumptions!B106 -> GIN_T | C54: =Assumptions!B28 -> Premixes | D54: =Assumptions!C106 -> GT | E54: =Assumptions!E28*(1+Assumptions!$C$11)^1 -> 10 | F54: =Assumptions!F28*(1+Assumptions!$C$12)^1 -> 4.35 | G54: =Assumptions!G28 -> 26 | H54: =Assumptions!D106 -> 29120 | I54: =Assumptions!E106 -> 4.58 | J54: =Assumptions!$C$13 -> 0.95 | K54: =Assumptions!B40 -> 0.25 | L54: =Assumptions!C40+IF(Assumptions!$C$6="Downside",Assumptions!$C$9,0) -> 0.065 | M54: =Assumptions!E40 -> 1 | N54: =H54*I54*G54*IF(Assumptions!$C$6="Downside",1-Assumptions!$C$7,1) -> 3467609.6 | O54: =N54*J54 -> 3294229.1 | P54: =E54*(1-K54) -> 7.5 | Q54: =O54*P54/10000000 -> 2.4706718 | R54: =O54*F54/10000000+IF(Assumptions!$C$6="Downside",Q54*Assumptions!$C$8,0) -> 1.4329897 | S54: =Q54*L54 -> 0.16059367 | T54: =O54*M54/10000000 -> 0.32942291 | U54: =Q54-SUM(R54:T54) -> 0.54766559 | V54: =IFERROR(U54/Q54,0) -> 0.22166667 | W54: =Assumptions!F106 -> Illustrative (replace with pilot) | X54: =Assumptions!C28&" | "&Assumptions!D28 -> Ginger-Lemon Hot Drink | 15g single sachet
A55: =Assumptions!A107 -> FY23 | B55: =Assumptions!B107 -> GIN_T | C55: =Assumptions!B28 -> Premixes | D55: =Assumptions!C107 -> Modern | E55: =Assumptions!E28*(1+Assumptions!$C$11)^1 -> 10 | F55: =Assumptions!F28*(1+Assumptions!$C$12)^1 -> 4.35 | G55: =Assumptions!G28 -> 26 | H55: =Assumptions!D107 -> 1019 | I55: =Assumptions!E107 -> 18.3 | J55: =Assumptions!$C$13 -> 0.95 | K55: =Assumptions!B41 -> 0.28 | L55: =Assumptions!C41+IF(Assumptions!$C$6="Downside",Assumptions!$C$9,0) -> 0.14 | M55: =Assumptions!E41 -> 1.7 | N55: =H55*I55*G55*IF(Assumptions!$C$6="Downside",1-Assumptions!$C$7,1) -> 484840.2 | O55: =N55*J55 -> 460598.19 | P55: =E55*(1-K55) -> 7.2 | Q55: =O55*P55/10000000 -> 0.3316307 | R55: =O55*F55/10000000+IF(Assumptions!$C$6="Downside",Q55*Assumptions!$C$8,0) -> 0.20036021 | S55: =Q55*L55 -> 0.046428298 | T55: =O55*M55/10000000 -> 0.078301692 | U55: =Q55-SUM(R55:T55) -> 0.0065404943 | V55: =IFERROR(U55/Q55,0) -> 0.019722222 | W55: =Assumptions!F107 -> Illustrative (replace with pilot) | X55: =Assumptions!C28&" | "&Assumptions!D28 -> Ginger-Lemon Hot Drink | 15g single sachet
A56: =Assumptions!A108 -> FY23 | B56: =Assumptions!B108 -> GIN_T | C56: =Assumptions!B28 -> Premixes | D56: =Assumptions!C108 -> QCom | E56: =Assumptions!E28*(1+Assumptions!$C$11)^1 -> 10 | F56: =Assumptions!F28*(1+Assumptions!$C$12)^1 -> 4.35 | G56: =Assumptions!G28 -> 26 | H56: =Assumptions!D108 -> 408 | I56: =Assumptions!E108 -> 54.91 | J56: =Assumptions!$C$13 -> 0.95 | K56: =Assumptions!B42 -> 0.38 | L56: =Assumptions!C42+IF(Assumptions!$C$6="Downside",Assumptions!$C$9,0) -> 0.24 | M56: =Assumptions!E42 -> 2 | N56: =H56*I56*G56*IF(Assumptions!$C$6="Downside",1-Assumptions!$C$7,1) -> 582485.28 | O56: =N56*J56 -> 553361.02 | P56: =E56*(1-K56) -> 6.2 | Q56: =O56*P56/10000000 -> 0.34308383 | R56: =O56*F56/10000000+IF(Assumptions!$C$6="Downside",Q56*Assumptions!$C$8,0) -> 0.24071204 | S56: =Q56*L56 -> 0.082340119 | T56: =O56*M56/10000000 -> 0.1106722 | U56: =Q56-SUM(R56:T56) -> -0.090640534 | V56: =IFERROR(U56/Q56,0) -> -0.26419355 | W56: =Assumptions!F108 -> Illustrative (replace with pilot) | X56: =Assumptions!C28&" | "&Assumptions!D28 -> Ginger-Lemon Hot Drink | 15g single sachet
A57: =Assumptions!A109 -> FY23 | B57: =Assumptions!B109 -> GIN_L | C57: =Assumptions!B29 -> Premixes | D57: =Assumptions!C109 -> GT | E57: =Assumptions!E29*(1+Assumptions!$C$11)^1 -> 99 | F57: =Assumptions!F29*(1+Assumptions!$C$12)^1 -> 44 | G57: =Assumptions!G29 -> 26 | H57: =Assumptions!D109 -> 21840 | I57: =Assumptions!E109 -> 3.7 | J57: =Assumptions!$C$13 -> 0.95 | K57: =Assumptions!B40 -> 0.25 | L57: =Assumptions!C40+IF(Assumptions!$C$6="Downside",Assumptions!$C$9,0) -> 0.065 | M57: =Assumptions!E40 -> 1 | N57: =H57*I57*G57*IF(Assumptions!$C$6="Downside",1-Assumptions!$C$7,1) -> 2101008 | O57: =N57*J57 -> 1995957.6 | P57: =E57*(1-K57) -> 74.25 | Q57: =O57*P57/10000000 -> 14.819985 | R57: =O57*F57/10000000+IF(Assumptions!$C$6="Downside",Q57*Assumptions!$C$8,0) -> 8.7822134 | S57: =Q57*L57 -> 0.96329904 | T57: =O57*M57/10000000 -> 0.19959576 | U57: =Q57-SUM(R57:T57) -> 4.8748769 | V57: =IFERROR(U57/Q57,0) -> 0.32893939 | W57: =Assumptions!F109 -> Illustrative (replace with pilot) | X57: =Assumptions!C29&" | "&Assumptions!D29 -> Ginger-Lemon Hot Drink | 10-sachet pack
A58: =Assumptions!A110 -> FY23 | B58: =Assumptions!B110 -> GIN_L | C58: =Assumptions!B29 -> Premixes | D58: =Assumptions!C110 -> Modern | E58: =Assumptions!E29*(1+Assumptions!$C$11)^1 -> 99 | F58: =Assumptions!F29*(1+Assumptions!$C$12)^1 -> 44 | G58: =Assumptions!G29 -> 26 | H58: =Assumptions!D110 -> 764 | I58: =Assumptions!E110 -> 14.78 | J58: =Assumptions!$C$13 -> 0.95 | K58: =Assumptions!B41 -> 0.28 | L58: =Assumptions!C41+IF(Assumptions!$C$6="Downside",Assumptions!$C$9,0) -> 0.14 | M58: =Assumptions!E41 -> 1.7 | N58: =H58*I58*G58*IF(Assumptions!$C$6="Downside",1-Assumptions!$C$7,1) -> 293589.92 | O58: =N58*J58 -> 278910.42 | P58: =E58*(1-K58) -> 71.28 | Q58: =O58*P58/10000000 -> 1.9880735 | R58: =O58*F58/10000000+IF(Assumptions!$C$6="Downside",Q58*Assumptions!$C$8,0) -> 1.2272059 | S58: =Q58*L58 -> 0.27833029 | T58: =O58*M58/10000000 -> 0.047414772 | U58: =Q58-SUM(R58:T58) -> 0.43512257 | V58: =IFERROR(U58/Q58,0) -> 0.21886644 | W58: =Assumptions!F110 -> Illustrative (replace with pilot) | X58: =Assumptions!C29&" | "&Assumptions!D29 -> Ginger-Lemon Hot Drink | 10-sachet pack
A59: =Assumptions!A111 -> FY23 | B59: =Assumptions!B111 -> GIN_L | C59: =Assumptions!B29 -> Premixes | D59: =Assumptions!C111 -> QCom | E59: =Assumptions!E29*(1+Assumptions!$C$11)^1 -> 99 | F59: =Assumptions!F29*(1+Assumptions!$C$12)^1 -> 44 | G59: =Assumptions!G29 -> 26 | H59: =Assumptions!D111 -> 306 | I59: =Assumptions!E111 -> 44.35 | J59: =Assumptions!$C$13 -> 0.95 | K59: =Assumptions!B42 -> 0.38 | L59: =Assumptions!C42+IF(Assumptions!$C$6="Downside",Assumptions!$C$9,0) -> 0.24 | M59: =Assumptions!E42 -> 2 | N59: =H59*I59*G59*IF(Assumptions!$C$6="Downside",1-Assumptions!$C$7,1) -> 352848.6 | O59: =N59*J59 -> 335206.17 | P59: =E59*(1-K59) -> 61.38 | Q59: =O59*P59/10000000 -> 2.0574955 | R59: =O59*F59/10000000+IF(Assumptions!$C$6="Downside",Q59*Assumptions!$C$8,0) -> 1.4749071 | S59: =Q59*L59 -> 0.49379891 | T59: =O59*M59/10000000 -> 0.067041234 | U59: =Q59-SUM(R59:T59) -> 0.021748176 | V59: =IFERROR(U59/Q59,0) -> 0.010570218 | W59: =Assumptions!F111 -> Illustrative (replace with pilot) | X59: =Assumptions!C29&" | "&Assumptions!D29 -> Ginger-Lemon Hot Drink | 10-sachet pack
A60: =Assumptions!A112 -> FY23 | B60: =Assumptions!B112 -> BAD_T | C60: =Assumptions!B30 -> Premixes | D60: =Assumptions!C112 -> GT | E60: =Assumptions!E30*(1+Assumptions!$C$11)^1 -> 10 | F60: =Assumptions!F30*(1+Assumptions!$C$12)^1 -> 4.5 | G60: =Assumptions!G30 -> 26 | H60: =Assumptions!D112 -> 23520 | I60: =Assumptions!E112 -> 3.17 | J60: =Assumptions!$C$13 -> 0.95 | K60: =Assumptions!B40 -> 0.25 | L60: =Assumptions!C40+IF(Assumptions!$C$6="Downside",Assumptions!$C$9,0) -> 0.065 | M60: =Assumptions!E40 -> 1 | N60: =H60*I60*G60*IF(Assumptions!$C$6="Downside",1-Assumptions!$C$7,1) -> 1938518.4 | O60: =N60*J60 -> 1841592.5 | P60: =E60*(1-K60) -> 7.5 | Q60: =O60*P60/10000000 -> 1.3811944 | R60: =O60*F60/10000000+IF(Assumptions!$C$6="Downside",Q60*Assumptions!$C$8,0) -> 0.82871662 | S60: =Q60*L60 -> 0.089777633 | T60: =O60*M60/10000000 -> 0.18415925 | U60: =Q60-SUM(R60:T60) -> 0.27854086 | V60: =IFERROR(U60/Q60,0) -> 0.20166667 | W60: =Assumptions!F112 -> Illustrative (replace with pilot) | X60: =Assumptions!C30&" | "&Assumptions!D30 -> Badam-Elaichi Milk Mix | 15g single sachet
A61: =Assumptions!A113 -> FY23 | B61: =Assumptions!B113 -> BAD_T | C61: =Assumptions!B30 -> Premixes | D61: =Assumptions!C113 -> Modern | E61: =Assumptions!E30*(1+Assumptions!$C$11)^1 -> 10 | F61: =Assumptions!F30*(1+Assumptions!$C$12)^1 -> 4.5 | G61: =Assumptions!G30 -> 26 | H61: =Assumptions!D113 -> 823 | I61: =Assumptions!E113 -> 12.67 | J61: =Assumptions!$C$13 -> 0.95 | K61: =Assumptions!B41 -> 0.28 | L61: =Assumptions!C41+IF(Assumptions!$C$6="Downside",Assumptions!$C$9,0) -> 0.14 | M61: =Assumptions!E41 -> 1.7 | N61: =H61*I61*G61*IF(Assumptions!$C$6="Downside",1-Assumptions!$C$7,1) -> 271112.66 | O61: =N61*J61 -> 257557.03 | P61: =E61*(1-K61) -> 7.2 | Q61: =O61*P61/10000000 -> 0.18544106 | R61: =O61*F61/10000000+IF(Assumptions!$C$6="Downside",Q61*Assumptions!$C$8,0) -> 0.11590066 | S61: =Q61*L61 -> 0.025961748 | T61: =O61*M61/10000000 -> 0.043784695 | U61: =Q61-SUM(R61:T61) -> -0.00020604562 | V61: =IFERROR(U61/Q61,0) -> -0.0011111111 | W61: =Assumptions!F113 -> Illustrative (replace with pilot) | X61: =Assumptions!C30&" | "&Assumptions!D30 -> Badam-Elaichi Milk Mix | 15g single sachet
A62: =Assumptions!A114 -> FY23 | B62: =Assumptions!B114 -> BAD_T | C62: =Assumptions!B30 -> Premixes | D62: =Assumptions!C114 -> QCom | E62: =Assumptions!E30*(1+Assumptions!$C$11)^1 -> 10 | F62: =Assumptions!F30*(1+Assumptions!$C$12)^1 -> 4.5 | G62: =Assumptions!G30 -> 26 | H62: =Assumptions!D114 -> 329 | I62: =Assumptions!E114 -> 38.02 | J62: =Assumptions!$C$13 -> 0.95 | K62: =Assumptions!B42 -> 0.38 | L62: =Assumptions!C42+IF(Assumptions!$C$6="Downside",Assumptions!$C$9,0) -> 0.24 | M62: =Assumptions!E42 -> 2 | N62: =H62*I62*G62*IF(Assumptions!$C$6="Downside",1-Assumptions!$C$7,1) -> 325223.08 | O62: =N62*J62 -> 308961.93 | P62: =E62*(1-K62) -> 6.2 | Q62: =O62*P62/10000000 -> 0.19155639 | R62: =O62*F62/10000000+IF(Assumptions!$C$6="Downside",Q62*Assumptions!$C$8,0) -> 0.13903287 | S62: =Q62*L62 -> 0.045973535 | T62: =O62*M62/10000000 -> 0.061792385 | U62: =Q62-SUM(R62:T62) -> -0.055242392 | V62: =IFERROR(U62/Q62,0) -> -0.2883871 | W62: =Assumptions!F114 -> Illustrative (replace with pilot) | X62: =Assumptions!C30&" | "&Assumptions!D30 -> Badam-Elaichi Milk Mix | 15g single sachet
A63: =Assumptions!A115 -> FY23 | B63: =Assumptions!B115 -> BAD_L | C63: =Assumptions!B31 -> Premixes | D63: =Assumptions!C115 -> GT | E63: =Assumptions!E31*(1+Assumptions!$C$11)^1 -> 99 | F63: =Assumptions!F31*(1+Assumptions!$C$12)^1 -> 45.5 | G63: =Assumptions!G31 -> 26 | H63: =Assumptions!D115 -> 19040 | I63: =Assumptions!E115 -> 2.9 | J63: =Assumptions!$C$13 -> 0.95 | K63: =Assumptions!B40 -> 0.25 | L63: =Assumptions!C40+IF(Assumptions!$C$6="Downside",Assumptions!$C$9,0) -> 0.065 | M63: =Assumptions!E40 -> 1 | N63: =H63*I63*G63*IF(Assumptions!$C$6="Downside",1-Assumptions!$C$7,1) -> 1435616 | O63: =N63*J63 -> 1363835.2 | P63: =E63*(1-K63) -> 74.25 | Q63: =O63*P63/10000000 -> 10.126476 | R63: =O63*F63/10000000+IF(Assumptions!$C$6="Downside",Q63*Assumptions!$C$8,0) -> 6.2054502 | S63: =Q63*L63 -> 0.65822096 | T63: =O63*M63/10000000 -> 0.13638352 | U63: =Q63-SUM(R63:T63) -> 3.1264217 | V63: =IFERROR(U63/Q63,0) -> 0.30873737 | W63: =Assumptions!F115 -> Illustrative (replace with pilot) | X63: =Assumptions!C31&" | "&Assumptions!D31 -> Badam-Elaichi Milk Mix | 150g pouch
A64: =Assumptions!A116 -> FY23 | B64: =Assumptions!B116 -> BAD_L | C64: =Assumptions!B31 -> Premixes | D64: =Assumptions!C116 -> Modern | E64: =Assumptions!E31*(1+Assumptions!$C$11)^1 -> 99 | F64: =Assumptions!F31*(1+Assumptions!$C$12)^1 -> 45.5 | G64: =Assumptions!G31 -> 26 | H64: =Assumptions!D116 -> 666 | I64: =Assumptions!E116 -> 11.62 | J64: =Assumptions!$C$13 -> 0.95 | K64: =Assumptions!B41 -> 0.28 | L64: =Assumptions!C41+IF(Assumptions!$C$6="Downside",Assumptions!$C$9,0) -> 0.14 | M64: =Assumptions!E41 -> 1.7 | N64: =H64*I64*G64*IF(Assumptions!$C$6="Downside",1-Assumptions!$C$7,1) -> 201211.92 | O64: =N64*J64 -> 191151.32 | P64: =E64*(1-K64) -> 71.28 | Q64: =O64*P64/10000000 -> 1.3625266 | R64: =O64*F64/10000000+IF(Assumptions!$C$6="Downside",Q64*Assumptions!$C$8,0) -> 0.86973852 | S64: =Q64*L64 -> 0.19075373 | T64: =O64*M64/10000000 -> 0.032495725 | U64: =Q64-SUM(R64:T64) -> 0.26953866 | V64: =IFERROR(U64/Q64,0) -> 0.19782267 | W64: =Assumptions!F116 -> Illustrative (replace with pilot) | X64: =Assumptions!C31&" | "&Assumptions!D31 -> Badam-Elaichi Milk Mix | 150g pouch
A65: =Assumptions!A117 -> FY23 | B65: =Assumptions!B117 -> BAD_L | C65: =Assumptions!B31 -> Premixes | D65: =Assumptions!C117 -> QCom | E65: =Assumptions!E31*(1+Assumptions!$C$11)^1 -> 99 | F65: =Assumptions!F31*(1+Assumptions!$C$12)^1 -> 45.5 | G65: =Assumptions!G31 -> 26 | H65: =Assumptions!D117 -> 267 | I65: =Assumptions!E117 -> 34.85 | J65: =Assumptions!$C$13 -> 0.95 | K65: =Assumptions!B42 -> 0.38 | L65: =Assumptions!C42+IF(Assumptions!$C$6="Downside",Assumptions!$C$9,0) -> 0.24 | M65: =Assumptions!E42 -> 2 | N65: =H65*I65*G65*IF(Assumptions!$C$6="Downside",1-Assumptions!$C$7,1) -> 241928.7 | O65: =N65*J65 -> 229832.27 | P65: =E65*(1-K65) -> 61.38 | Q65: =O65*P65/10000000 -> 1.4107104 | R65: =O65*F65/10000000+IF(Assumptions!$C$6="Downside",Q65*Assumptions!$C$8,0) -> 1.0457368 | S65: =Q65*L65 -> 0.33857051 | T65: =O65*M65/10000000 -> 0.045966453 | U65: =Q65-SUM(R65:T65) -> -0.019563322 | V65: =IFERROR(U65/Q65,0) -> -0.013867709 | W65: =Assumptions!F117 -> Illustrative (replace with pilot) | X65: =Assumptions!C31&" | "&Assumptions!D31 -> Badam-Elaichi Milk Mix | 150g pouch
A66: =Assumptions!A118 -> FY23 | B66: =Assumptions!B118 -> CHU_T | C66: =Assumptions!B32 -> Condiments | D66: =Assumptions!C118 -> GT | E66: =Assumptions!E32*(1+Assumptions!$C$11)^1 -> 10 | F66: =Assumptions!F32*(1+Assumptions!$C$12)^1 -> 4.8 | G66: =Assumptions!G32 -> 52 | H66: =Assumptions!D118 -> 24080 | I66: =Assumptions!E118 -> 2.55 | J66: =Assumptions!$C$13 -> 0.95 | K66: =Assumptions!B40 -> 0.25 | L66: =Assumptions!C40+IF(Assumptions!$C$6="Downside",Assumptions!$C$9,0) -> 0.065 | M66: =Assumptions!E40 -> 1 | N66: =H66*I66*G66*IF(Assumptions!$C$6="Downside",1-Assumptions!$C$7,1) -> 3193008 | O66: =N66*J66 -> 3033357.6 | P66: =E66*(1-K66) -> 7.5 | Q66: =O66*P66/10000000 -> 2.2750182 | R66: =O66*F66/10000000+IF(Assumptions!$C$6="Downside",Q66*Assumptions!$C$8,0) -> 1.4560116 | S66: =Q66*L66 -> 0.14787618 | T66: =O66*M66/10000000 -> 0.30333576 | U66: =Q66-SUM(R66:T66) -> 0.36779461 | V66: =IFERROR(U66/Q66,0) -> 0.16166667 | W66: =Assumptions!F118 -> Illustrative (replace with pilot) | X66: =Assumptions!C32&" | "&Assumptions!D32 -> Tamarind-Date Chutney | 20g sachet
A67: =Assumptions!A119 -> FY23 | B67: =Assumptions!B119 -> CHU_T | C67: =Assumptions!B32 -> Condiments | D67: =Assumptions!C119 -> Modern | E67: =Assumptions!E32*(1+Assumptions!$C$11)^1 -> 10 | F67: =Assumptions!F32*(1+Assumptions!$C$12)^1 -> 4.8 | G67: =Assumptions!G32 -> 52 | H67: =Assumptions!D119 -> 843 | I67: =Assumptions!E119 -> 10.21 | J67: =Assumptions!$C$13 -> 0.95 | K67: =Assumptions!B41 -> 0.28 | L67: =Assumptions!C41+IF(Assumptions!$C$6="Downside",Assumptions!$C$9,0) -> 0.14 | M67: =Assumptions!E41 -> 1.7 | N67: =H67*I67*G67*IF(Assumptions!$C$6="Downside",1-Assumptions!$C$7,1) -> 447565.56 | O67: =N67*J67 -> 425187.28 | P67: =E67*(1-K67) -> 7.2 | Q67: =O67*P67/10000000 -> 0.30613484 | R67: =O67*F67/10000000+IF(Assumptions!$C$6="Downside",Q67*Assumptions!$C$8,0) -> 0.2040899 | S67: =Q67*L67 -> 0.042858878 | T67: =O67*M67/10000000 -> 0.072281838 | U67: =Q67-SUM(R67:T67) -> -0.013095768 | V67: =IFERROR(U67/Q67,0) -> -0.042777778 | W67: =Assumptions!F119 -> Illustrative (replace with pilot) | X67: =Assumptions!C32&" | "&Assumptions!D32 -> Tamarind-Date Chutney | 20g sachet
A68: =Assumptions!A120 -> FY23 | B68: =Assumptions!B120 -> CHU_T | C68: =Assumptions!B32 -> Condiments | D68: =Assumptions!C120 -> QCom | E68: =Assumptions!E32*(1+Assumptions!$C$11)^1 -> 10 | F68: =Assumptions!F32*(1+Assumptions!$C$12)^1 -> 4.8 | G68: =Assumptions!G32 -> 52 | H68: =Assumptions!D120 -> 337 | I68: =Assumptions!E120 -> 30.62 | J68: =Assumptions!$C$13 -> 0.95 | K68: =Assumptions!B42 -> 0.38 | L68: =Assumptions!C42+IF(Assumptions!$C$6="Downside",Assumptions!$C$9,0) -> 0.24 | M68: =Assumptions!E42 -> 2 | N68: =H68*I68*G68*IF(Assumptions!$C$6="Downside",1-Assumptions!$C$7,1) -> 536584.88 | O68: =N68*J68 -> 509755.64 | P68: =E68*(1-K68) -> 6.2 | Q68: =O68*P68/10000000 -> 0.31604849 | R68: =O68*F68/10000000+IF(Assumptions!$C$6="Downside",Q68*Assumptions!$C$8,0) -> 0.24468271 | S68: =Q68*L68 -> 0.075851639 | T68: =O68*M68/10000000 -> 0.10195113 | U68: =Q68-SUM(R68:T68) -> -0.10643698 | V68: =IFERROR(U68/Q68,0) -> -0.33677419 | W68: =Assumptions!F120 -> Illustrative (replace with pilot) | X68: =Assumptions!C32&" | "&Assumptions!D32 -> Tamarind-Date Chutney | 20g sachet
A69: =Assumptions!A121 -> FY23 | B69: =Assumptions!B121 -> CHU_L | C69: =Assumptions!B33 -> Condiments | D69: =Assumptions!C121 -> GT | E69: =Assumptions!E33*(1+Assumptions!$C$11)^1 -> 99 | F69: =Assumptions!F33*(1+Assumptions!$C$12)^1 -> 47 | G69: =Assumptions!G33 -> 52 | H69: =Assumptions!D121 -> 18480 | I69: =Assumptions!E121 -> 1.94 | J69: =Assumptions!$C$13 -> 0.95 | K69: =Assumptions!B40 -> 0.25 | L69: =Assumptions!C40+IF(Assumptions!$C$6="Downside",Assumptions!$C$9,0) -> 0.065 | M69: =Assumptions!E40 -> 1 | N69: =H69*I69*G69*IF(Assumptions!$C$6="Downside",1-Assumptions!$C$7,1) -> 1864262.4 | O69: =N69*J69 -> 1771049.3 | P69: =E69*(1-K69) -> 74.25 | Q69: =O69*P69/10000000 -> 13.150041 | R69: =O69*F69/10000000+IF(Assumptions!$C$6="Downside",Q69*Assumptions!$C$8,0) -> 8.3239316 | S69: =Q69*L69 -> 0.85475266 | T69: =O69*M69/10000000 -> 0.17710493 | U69: =Q69-SUM(R69:T69) -> 3.7942517 | V69: =IFERROR(U69/Q69,0) -> 0.28853535 | W69: =Assumptions!F121 -> Illustrative (replace with pilot) | X69: =Assumptions!C33&" | "&Assumptions!D33 -> Tamarind-Date Chutney | 200g pack
A70: =Assumptions!A122 -> FY23 | B70: =Assumptions!B122 -> CHU_L | C70: =Assumptions!B33 -> Condiments | D70: =Assumptions!C122 -> Modern | E70: =Assumptions!E33*(1+Assumptions!$C$11)^1 -> 99 | F70: =Assumptions!F33*(1+Assumptions!$C$12)^1 -> 47 | G70: =Assumptions!G33 -> 52 | H70: =Assumptions!D122 -> 647 | I70: =Assumptions!E122 -> 7.74 | J70: =Assumptions!$C$13 -> 0.95 | K70: =Assumptions!B41 -> 0.28 | L70: =Assumptions!C41+IF(Assumptions!$C$6="Downside",Assumptions!$C$9,0) -> 0.14 | M70: =Assumptions!E41 -> 1.7 | N70: =H70*I70*G70*IF(Assumptions!$C$6="Downside",1-Assumptions!$C$7,1) -> 260404.56 | O70: =N70*J70 -> 247384.33 | P70: =E70*(1-K70) -> 71.28 | Q70: =O70*P70/10000000 -> 1.7633555 | R70: =O70*F70/10000000+IF(Assumptions!$C$6="Downside",Q70*Assumptions!$C$8,0) -> 1.1627064 | S70: =Q70*L70 -> 0.24686977 | T70: =O70*M70/10000000 -> 0.042055336 | U70: =Q70-SUM(R70:T70) -> 0.31172405 | V70: =IFERROR(U70/Q70,0) -> 0.1767789 | W70: =Assumptions!F122 -> Illustrative (replace with pilot) | X70: =Assumptions!C33&" | "&Assumptions!D33 -> Tamarind-Date Chutney | 200g pack
A71: =Assumptions!A123 -> FY23 | B71: =Assumptions!B123 -> CHU_L | C71: =Assumptions!B33 -> Condiments | D71: =Assumptions!C123 -> QCom | E71: =Assumptions!E33*(1+Assumptions!$C$11)^1 -> 99 | F71: =Assumptions!F33*(1+Assumptions!$C$12)^1 -> 47 | G71: =Assumptions!G33 -> 52 | H71: =Assumptions!D123 -> 259 | I71: =Assumptions!E123 -> 23.23 | J71: =Assumptions!$C$13 -> 0.95 | K71: =Assumptions!B42 -> 0.38 | L71: =Assumptions!C42+IF(Assumptions!$C$6="Downside",Assumptions!$C$9,0) -> 0.24 | M71: =Assumptions!E42 -> 2 | N71: =H71*I71*G71*IF(Assumptions!$C$6="Downside",1-Assumptions!$C$7,1) -> 312861.64 | O71: =N71*J71 -> 297218.56 | P71: =E71*(1-K71) -> 61.38 | Q71: =O71*P71/10000000 -> 1.8243275 | R71: =O71*F71/10000000+IF(Assumptions!$C$6="Downside",Q71*Assumptions!$C$8,0) -> 1.3969272 | S71: =Q71*L71 -> 0.4378386 | T71: =O71*M71/10000000 -> 0.059443712 | U71: =Q71-SUM(R71:T71) -> -0.069882027 | V71: =IFERROR(U71/Q71,0) -> -0.038305637 | W71: =Assumptions!F123 -> Illustrative (replace with pilot) | X71: =Assumptions!C33&" | "&Assumptions!D33 -> Tamarind-Date Chutney | 200g pack
A72: =Assumptions!A124 -> FY23 | B72: =Assumptions!B124 -> PIC_T | C72: =Assumptions!B34 -> Condiments | D72: =Assumptions!C124 -> GT | E72: =Assumptions!E34*(1+Assumptions!$C$11)^1 -> 10 | F72: =Assumptions!F34*(1+Assumptions!$C$12)^1 -> 4.7 | G72: =Assumptions!G34 -> 52 | H72: =Assumptions!D124 -> 23520 | I72: =Assumptions!E124 -> 2.38 | J72: =Assumptions!$C$13 -> 0.95 | K72: =Assumptions!B40 -> 0.25 | L72: =Assumptions!C40+IF(Assumptions!$C$6="Downside",Assumptions!$C$9,0) -> 0.065 | M72: =Assumptions!E40 -> 1 | N72: =H72*I72*G72*IF(Assumptions!$C$6="Downside",1-Assumptions!$C$7,1) -> 2910835.2 | O72: =N72*J72 -> 2765293.4 | P72: =E72*(1-K72) -> 7.5 | Q72: =O72*P72/10000000 -> 2.0739701 | R72: =O72*F72/10000000+IF(Assumptions!$C$6="Downside",Q72*Assumptions!$C$8,0) -> 1.2996879 | S72: =Q72*L72 -> 0.13480806 | T72: =O72*M72/10000000 -> 0.27652934 | U72: =Q72-SUM(R72:T72) -> 0.36294476 | V72: =IFERROR(U72/Q72,0) -> 0.175 | W72: =Assumptions!F124 -> Illustrative (replace with pilot) | X72: =Assumptions!C34&" | "&Assumptions!D34 -> Lime Pickle | 20g sachet
A73: =Assumptions!A125 -> FY23 | B73: =Assumptions!B125 -> PIC_T | C73: =Assumptions!B34 -> Condiments | D73: =Assumptions!C125 -> Modern | E73: =Assumptions!E34*(1+Assumptions!$C$11)^1 -> 10 | F73: =Assumptions!F34*(1+Assumptions!$C$12)^1 -> 4.7 | G73: =Assumptions!G34 -> 52 | H73: =Assumptions!D125 -> 823 | I73: =Assumptions!E125 -> 9.5 | J73: =Assumptions!$C$13 -> 0.95 | K73: =Assumptions!B41 -> 0.28 | L73: =Assumptions!C41+IF(Assumptions!$C$6="Downside",Assumptions!$C$9,0) -> 0.14 | M73: =Assumptions!E41 -> 1.7 | N73: =H73*I73*G73*IF(Assumptions!$C$6="Downside",1-Assumptions!$C$7,1) -> 406562 | O73: =N73*J73 -> 386233.9 | P73: =E73*(1-K73) -> 7.2 | Q73: =O73*P73/10000000 -> 0.27808841 | R73: =O73*F73/10000000+IF(Assumptions!$C$6="Downside",Q73*Assumptions!$C$8,0) -> 0.18152993 | S73: =Q73*L73 -> 0.038932377 | T73: =O73*M73/10000000 -> 0.065659763 | U73: =Q73-SUM(R73:T73) -> -0.0080336651 | V73: =IFERROR(U73/Q73,0) -> -0.028888889 | W73: =Assumptions!F125 -> Illustrative (replace with pilot) | X73: =Assumptions!C34&" | "&Assumptions!D34 -> Lime Pickle | 20g sachet
A74: =Assumptions!A126 -> FY23 | B74: =Assumptions!B126 -> PIC_T | C74: =Assumptions!B34 -> Condiments | D74: =Assumptions!C126 -> QCom | E74: =Assumptions!E34*(1+Assumptions!$C$11)^1 -> 10 | F74: =Assumptions!F34*(1+Assumptions!$C$12)^1 -> 4.7 | G74: =Assumptions!G34 -> 52 | H74: =Assumptions!D126 -> 329 | I74: =Assumptions!E126 -> 28.51 | J74: =Assumptions!$C$13 -> 0.95 | K74: =Assumptions!B42 -> 0.38 | L74: =Assumptions!C42+IF(Assumptions!$C$6="Downside",Assumptions!$C$9,0) -> 0.24 | M74: =Assumptions!E42 -> 2 | N74: =H74*I74*G74*IF(Assumptions!$C$6="Downside",1-Assumptions!$C$7,1) -> 487749.08 | O74: =N74*J74 -> 463361.63 | P74: =E74*(1-K74) -> 6.2 | Q74: =O74*P74/10000000 -> 0.28728421 | R74: =O74*F74/10000000+IF(Assumptions!$C$6="Downside",Q74*Assumptions!$C$8,0) -> 0.21777996 | S74: =Q74*L74 -> 0.06894821 | T74: =O74*M74/10000000 -> 0.092672325 | U74: =Q74-SUM(R74:T74) -> -0.092116291 | V74: =IFERROR(U74/Q74,0) -> -0.32064516 | W74: =Assumptions!F126 -> Illustrative (replace with pilot) | X74: =Assumptions!C34&" | "&Assumptions!D34 -> Lime Pickle | 20g sachet
A75: =Assumptions!A127 -> FY23 | B75: =Assumptions!B127 -> PIC_L | C75: =Assumptions!B35 -> Condiments | D75: =Assumptions!C127 -> GT | E75: =Assumptions!E35*(1+Assumptions!$C$11)^1 -> 99 | F75: =Assumptions!F35*(1+Assumptions!$C$12)^1 -> 46.5 | G75: =Assumptions!G35 -> 52 | H75: =Assumptions!D127 -> 20720 | I75: =Assumptions!E127 -> 1.94 | J75: =Assumptions!$C$13 -> 0.95 | K75: =Assumptions!B40 -> 0.25 | L75: =Assumptions!C40+IF(Assumptions!$C$6="Downside",Assumptions!$C$9,0) -> 0.065 | M75: =Assumptions!E40 -> 1 | N75: =H75*I75*G75*IF(Assumptions!$C$6="Downside",1-Assumptions!$C$7,1) -> 2090233.6 | O75: =N75*J75 -> 1985721.9 | P75: =E75*(1-K75) -> 74.25 | Q75: =O75*P75/10000000 -> 14.743985 | R75: =O75*F75/10000000+IF(Assumptions!$C$6="Downside",Q75*Assumptions!$C$8,0) -> 9.2336069 | S75: =Q75*L75 -> 0.95835904 | T75: =O75*M75/10000000 -> 0.19857219 | U75: =Q75-SUM(R75:T75) -> 4.3534471 | V75: =IFERROR(U75/Q75,0) -> 0.29526936 | W75: =Assumptions!F127 -> Illustrative (replace with pilot) | X75: =Assumptions!C35&" | "&Assumptions!D35 -> Lime Pickle | 200g pack
A76: =Assumptions!A128 -> FY23 | B76: =Assumptions!B128 -> PIC_L | C76: =Assumptions!B35 -> Condiments | D76: =Assumptions!C128 -> Modern | E76: =Assumptions!E35*(1+Assumptions!$C$11)^1 -> 99 | F76: =Assumptions!F35*(1+Assumptions!$C$12)^1 -> 46.5 | G76: =Assumptions!G35 -> 52 | H76: =Assumptions!D128 -> 725 | I76: =Assumptions!E128 -> 7.74 | J76: =Assumptions!$C$13 -> 0.95 | K76: =Assumptions!B41 -> 0.28 | L76: =Assumptions!C41+IF(Assumptions!$C$6="Downside",Assumptions!$C$9,0) -> 0.14 | M76: =Assumptions!E41 -> 1.7 | N76: =H76*I76*G76*IF(Assumptions!$C$6="Downside",1-Assumptions!$C$7,1) -> 291798 | O76: =N76*J76 -> 277208.1 | P76: =E76*(1-K76) -> 71.28 | Q76: =O76*P76/10000000 -> 1.9759393 | R76: =O76*F76/10000000+IF(Assumptions!$C$6="Downside",Q76*Assumptions!$C$8,0) -> 1.2890177 | S76: =Q76*L76 -> 0.27663151 | T76: =O76*M76/10000000 -> 0.047125377 | U76: =Q76-SUM(R76:T76) -> 0.36316479 | V76: =IFERROR(U76/Q76,0) -> 0.18379349 | W76: =Assumptions!F128 -> Illustrative (replace with pilot) | X76: =Assumptions!C35&" | "&Assumptions!D35 -> Lime Pickle | 200g pack
A77: =Assumptions!A129 -> FY23 | B77: =Assumptions!B129 -> PIC_L | C77: =Assumptions!B35 -> Condiments | D77: =Assumptions!C129 -> QCom | E77: =Assumptions!E35*(1+Assumptions!$C$11)^1 -> 99 | F77: =Assumptions!F35*(1+Assumptions!$C$12)^1 -> 46.5 | G77: =Assumptions!G35 -> 52 | H77: =Assumptions!D129 -> 290 | I77: =Assumptions!E129 -> 23.23 | J77: =Assumptions!$C$13 -> 0.95 | K77: =Assumptions!B42 -> 0.38 | L77: =Assumptions!C42+IF(Assumptions!$C$6="Downside",Assumptions!$C$9,0) -> 0.24 | M77: =Assumptions!E42 -> 2 | N77: =H77*I77*G77*IF(Assumptions!$C$6="Downside",1-Assumptions!$C$7,1) -> 350308.4 | O77: =N77*J77 -> 332792.98 | P77: =E77*(1-K77) -> 61.38 | Q77: =O77*P77/10000000 -> 2.0426833 | R77: =O77*F77/10000000+IF(Assumptions!$C$6="Downside",Q77*Assumptions!$C$8,0) -> 1.5474874 | S77: =Q77*L77 -> 0.49024399 | T77: =O77*M77/10000000 -> 0.066558596 | U77: =Q77-SUM(R77:T77) -> -0.061606636 | V77: =IFERROR(U77/Q77,0) -> -0.030159661 | W77: =Assumptions!F129 -> Illustrative (replace with pilot) | X77: =Assumptions!C35&" | "&Assumptions!D35 -> Lime Pickle | 200g pack
A78: =Assumptions!A130 -> FY24 | B78: =Assumptions!B130 -> SAB_T | C78: =Assumptions!B24 -> Spices | D78: =Assumptions!C130 -> GT | E78: =Assumptions!E24*(1+Assumptions!$C$11)^2 -> 10 | F78: =Assumptions!F24*(1+Assumptions!$C$12)^2 -> 5.25 | G78: =Assumptions!G24 -> 52 | H78: =Assumptions!D130 -> 65000 | I78: =Assumptions!E130 -> 4.3 | J78: =Assumptions!$C$13 -> 0.95 | K78: =Assumptions!B40 -> 0.25 | L78: =Assumptions!C40+IF(Assumptions!$C$6="Downside",Assumptions!$C$9,0) -> 0.065 | M78: =Assumptions!E40 -> 1 | N78: =H78*I78*G78*IF(Assumptions!$C$6="Downside",1-Assumptions!$C$7,1) -> 14534000 | O78: =N78*J78 -> 13807300 | P78: =E78*(1-K78) -> 7.5 | Q78: =O78*P78/10000000 -> 10.355475 | R78: =O78*F78/10000000+IF(Assumptions!$C$6="Downside",Q78*Assumptions!$C$8,0) -> 7.2488325 | S78: =Q78*L78 -> 0.67310587 | T78: =O78*M78/10000000 -> 1.38073 | U78: =Q78-SUM(R78:T78) -> 1.0528066 | V78: =IFERROR(U78/Q78,0) -> 0.10166667 | W78: =Assumptions!F130 -> Illustrative (replace with pilot) | X78: =Assumptions!C24&" | "&Assumptions!D24 -> Everyday Sabzi Masala | 8g trial
A79: =Assumptions!A131 -> FY24 | B79: =Assumptions!B131 -> SAB_T | C79: =Assumptions!B24 -> Spices | D79: =Assumptions!C131 -> Modern | E79: =Assumptions!E24*(1+Assumptions!$C$11)^2 -> 10 | F79: =Assumptions!F24*(1+Assumptions!$C$12)^2 -> 5.25 | G79: =Assumptions!G24 -> 52 | H79: =Assumptions!D131 -> 2275 | I79: =Assumptions!E131 -> 17.2 | J79: =Assumptions!$C$13 -> 0.95 | K79: =Assumptions!B41 -> 0.28 | L79: =Assumptions!C41+IF(Assumptions!$C$6="Downside",Assumptions!$C$9,0) -> 0.14 | M79: =Assumptions!E41 -> 1.7 | N79: =H79*I79*G79*IF(Assumptions!$C$6="Downside",1-Assumptions!$C$7,1) -> 2034760 | O79: =N79*J79 -> 1933022 | P79: =E79*(1-K79) -> 7.2 | Q79: =O79*P79/10000000 -> 1.3917758 | R79: =O79*F79/10000000+IF(Assumptions!$C$6="Downside",Q79*Assumptions!$C$8,0) -> 1.0148366 | S79: =Q79*L79 -> 0.19484862 | T79: =O79*M79/10000000 -> 0.32861374 | U79: =Q79-SUM(R79:T79) -> -0.14652307 | V79: =IFERROR(U79/Q79,0) -> -0.10527778 | W79: =Assumptions!F131 -> Illustrative (replace with pilot) | X79: =Assumptions!C24&" | "&Assumptions!D24 -> Everyday Sabzi Masala | 8g trial
A80: =Assumptions!A132 -> FY24 | B80: =Assumptions!B132 -> SAB_T | C80: =Assumptions!B24 -> Spices | D80: =Assumptions!C132 -> QCom | E80: =Assumptions!E24*(1+Assumptions!$C$11)^2 -> 10 | F80: =Assumptions!F24*(1+Assumptions!$C$12)^2 -> 5.25 | G80: =Assumptions!G24 -> 52 | H80: =Assumptions!D132 -> 910 | I80: =Assumptions!E132 -> 51.6 | J80: =Assumptions!$C$13 -> 0.95 | K80: =Assumptions!B42 -> 0.38 | L80: =Assumptions!C42+IF(Assumptions!$C$6="Downside",Assumptions!$C$9,0) -> 0.24 | M80: =Assumptions!E42 -> 2 | N80: =H80*I80*G80*IF(Assumptions!$C$6="Downside",1-Assumptions!$C$7,1) -> 2441712 | O80: =N80*J80 -> 2319626.4 | P80: =E80*(1-K80) -> 6.2 | Q80: =O80*P80/10000000 -> 1.4381684 | R80: =O80*F80/10000000+IF(Assumptions!$C$6="Downside",Q80*Assumptions!$C$8,0) -> 1.2178039 | S80: =Q80*L80 -> 0.34516041 | T80: =O80*M80/10000000 -> 0.46392528 | U80: =Q80-SUM(R80:T80) -> -0.58872118 | V80: =IFERROR(U80/Q80,0) -> -0.40935484 | W80: =Assumptions!F132 -> Illustrative (replace with pilot) | X80: =Assumptions!C24&" | "&Assumptions!D24 -> Everyday Sabzi Masala | 8g trial
A81: =Assumptions!A133 -> FY24 | B81: =Assumptions!B133 -> SAB_L | C81: =Assumptions!B25 -> Spices | D81: =Assumptions!C133 -> GT | E81: =Assumptions!E25*(1+Assumptions!$C$11)^2 -> 49 | F81: =Assumptions!F25*(1+Assumptions!$C$12)^2 -> 23 | G81: =Assumptions!G25 -> 52 | H81: =Assumptions!D133 -> 75000 | I81: =Assumptions!E133 -> 5.2 | J81: =Assumptions!$C$13 -> 0.95 | K81: =Assumptions!B40 -> 0.25 | L81: =Assumptions!C40+IF(Assumptions!$C$6="Downside",Assumptions!$C$9,0) -> 0.065 | M81: =Assumptions!E40 -> 1 | N81: =H81*I81*G81*IF(Assumptions!$C$6="Downside",1-Assumptions!$C$7,1) -> 20280000 | O81: =N81*J81 -> 19266000 | P81: =E81*(1-K81) -> 36.75 | Q81: =O81*P81/10000000 -> 70.80255 | R81: =O81*F81/10000000+IF(Assumptions!$C$6="Downside",Q81*Assumptions!$C$8,0) -> 44.3118 | S81: =Q81*L81 -> 4.6021658 | T81: =O81*M81/10000000 -> 1.9266 | U81: =Q81-SUM(R81:T81) -> 19.961984 | V81: =IFERROR(U81/Q81,0) -> 0.28193878 | W81: =Assumptions!F133 -> Illustrative (replace with pilot) | X81: =Assumptions!C25&" | "&Assumptions!D25 -> Everyday Sabzi Masala | 50g pouch
A82: =Assumptions!A134 -> FY24 | B82: =Assumptions!B134 -> SAB_L | C82: =Assumptions!B25 -> Spices | D82: =Assumptions!C134 -> Modern | E82: =Assumptions!E25*(1+Assumptions!$C$11)^2 -> 49 | F82: =Assumptions!F25*(1+Assumptions!$C$12)^2 -> 23 | G82: =Assumptions!G25 -> 52 | H82: =Assumptions!D134 -> 2625 | I82: =Assumptions!E134 -> 20.8 | J82: =Assumptions!$C$13 -> 0.95 | K82: =Assumptions!B41 -> 0.28 | L82: =Assumptions!C41+IF(Assumptions!$C$6="Downside",Assumptions!$C$9,0) -> 0.14 | M82: =Assumptions!E41 -> 1.7 | N82: =H82*I82*G82*IF(Assumptions!$C$6="Downside",1-Assumptions!$C$7,1) -> 2839200 | O82: =N82*J82 -> 2697240 | P82: =E82*(1-K82) -> 35.28 | Q82: =O82*P82/10000000 -> 9.5158627 | R82: =O82*F82/10000000+IF(Assumptions!$C$6="Downside",Q82*Assumptions!$C$8,0) -> 6.203652 | S82: =Q82*L82 -> 1.3322208 | T82: =O82*M82/10000000 -> 0.4585308 | U82: =Q82-SUM(R82:T82) -> 1.5214591 | V82: =IFERROR(U82/Q82,0) -> 0.15988662 | W82: =Assumptions!F134 -> Illustrative (replace with pilot) | X82: =Assumptions!C25&" | "&Assumptions!D25 -> Everyday Sabzi Masala | 50g pouch
A83: =Assumptions!A135 -> FY24 | B83: =Assumptions!B135 -> SAB_L | C83: =Assumptions!B25 -> Spices | D83: =Assumptions!C135 -> QCom | E83: =Assumptions!E25*(1+Assumptions!$C$11)^2 -> 49 | F83: =Assumptions!F25*(1+Assumptions!$C$12)^2 -> 23 | G83: =Assumptions!G25 -> 52 | H83: =Assumptions!D135 -> 1050 | I83: =Assumptions!E135 -> 62.4 | J83: =Assumptions!$C$13 -> 0.95 | K83: =Assumptions!B42 -> 0.38 | L83: =Assumptions!C42+IF(Assumptions!$C$6="Downside",Assumptions!$C$9,0) -> 0.24 | M83: =Assumptions!E42 -> 2 | N83: =H83*I83*G83*IF(Assumptions!$C$6="Downside",1-Assumptions!$C$7,1) -> 3407040 | O83: =N83*J83 -> 3236688 | P83: =E83*(1-K83) -> 30.38 | Q83: =O83*P83/10000000 -> 9.8330581 | R83: =O83*F83/10000000+IF(Assumptions!$C$6="Downside",Q83*Assumptions!$C$8,0) -> 7.4443824 | S83: =Q83*L83 -> 2.359934 | T83: =O83*M83/10000000 -> 0.6473376 | U83: =Q83-SUM(R83:T83) -> -0.61859581 | V83: =IFERROR(U83/Q83,0) -> -0.062909809 | W83: =Assumptions!F135 -> Illustrative (replace with pilot) | X83: =Assumptions!C25&" | "&Assumptions!D25 -> Everyday Sabzi Masala | 50g pouch
A84: =Assumptions!A136 -> FY24 | B84: =Assumptions!B136 -> GAR_T | C84: =Assumptions!B26 -> Spices | D84: =Assumptions!C136 -> GT | E84: =Assumptions!E26*(1+Assumptions!$C$11)^2 -> 10 | F84: =Assumptions!F26*(1+Assumptions!$C$12)^2 -> 5.35 | G84: =Assumptions!G26 -> 52 | H84: =Assumptions!D136 -> 57000 | I84: =Assumptions!E136 -> 3.7 | J84: =Assumptions!$C$13 -> 0.95 | K84: =Assumptions!B40 -> 0.25 | L84: =Assumptions!C40+IF(Assumptions!$C$6="Downside",Assumptions!$C$9,0) -> 0.065 | M84: =Assumptions!E40 -> 1 | N84: =H84*I84*G84*IF(Assumptions!$C$6="Downside",1-Assumptions!$C$7,1) -> 10966800 | O84: =N84*J84 -> 10418460 | P84: =E84*(1-K84) -> 7.5 | Q84: =O84*P84/10000000 -> 7.813845 | R84: =O84*F84/10000000+IF(Assumptions!$C$6="Downside",Q84*Assumptions!$C$8,0) -> 5.5738761 | S84: =Q84*L84 -> 0.50789993 | T84: =O84*M84/10000000 -> 1.041846 | U84: =Q84-SUM(R84:T84) -> 0.69022297 | V84: =IFERROR(U84/Q84,0) -> 0.088333333 | W84: =Assumptions!F136 -> Illustrative (replace with pilot) | X84: =Assumptions!C26&" | "&Assumptions!D26 -> Garam Masala | 5g trial
A85: =Assumptions!A137 -> FY24 | B85: =Assumptions!B137 -> GAR_T | C85: =Assumptions!B26 -> Spices | D85: =Assumptions!C137 -> Modern | E85: =Assumptions!E26*(1+Assumptions!$C$11)^2 -> 10 | F85: =Assumptions!F26*(1+Assumptions!$C$12)^2 -> 5.35 | G85: =Assumptions!G26 -> 52 | H85: =Assumptions!D137 -> 1995 | I85: =Assumptions!E137 -> 14.8 | J85: =Assumptions!$C$13 -> 0.95 | K85: =Assumptions!B41 -> 0.28 | L85: =Assumptions!C41+IF(Assumptions!$C$6="Downside",Assumptions!$C$9,0) -> 0.14 | M85: =Assumptions!E41 -> 1.7 | N85: =H85*I85*G85*IF(Assumptions!$C$6="Downside",1-Assumptions!$C$7,1) -> 1535352 | O85: =N85*J85 -> 1458584.4 | P85: =E85*(1-K85) -> 7.2 | Q85: =O85*P85/10000000 -> 1.0501808 | R85: =O85*F85/10000000+IF(Assumptions!$C$6="Downside",Q85*Assumptions!$C$8,0) -> 0.78034265 | S85: =Q85*L85 -> 0.14702531 | T85: =O85*M85/10000000 -> 0.24795935 | U85: =Q85-SUM(R85:T85) -> -0.12514654 | V85: =IFERROR(U85/Q85,0) -> -0.11916667 | W85: =Assumptions!F137 -> Illustrative (replace with pilot) | X85: =Assumptions!C26&" | "&Assumptions!D26 -> Garam Masala | 5g trial
A86: =Assumptions!A138 -> FY24 | B86: =Assumptions!B138 -> GAR_T | C86: =Assumptions!B26 -> Spices | D86: =Assumptions!C138 -> QCom | E86: =Assumptions!E26*(1+Assumptions!$C$11)^2 -> 10 | F86: =Assumptions!F26*(1+Assumptions!$C$12)^2 -> 5.35 | G86: =Assumptions!G26 -> 52 | H86: =Assumptions!D138 -> 798 | I86: =Assumptions!E138 -> 44.4 | J86: =Assumptions!$C$13 -> 0.95 | K86: =Assumptions!B42 -> 0.38 | L86: =Assumptions!C42+IF(Assumptions!$C$6="Downside",Assumptions!$C$9,0) -> 0.24 | M86: =Assumptions!E42 -> 2 | N86: =H86*I86*G86*IF(Assumptions!$C$6="Downside",1-Assumptions!$C$7,1) -> 1842422.4 | O86: =N86*J86 -> 1750301.3 | P86: =E86*(1-K86) -> 6.2 | Q86: =O86*P86/10000000 -> 1.0851868 | R86: =O86*F86/10000000+IF(Assumptions!$C$6="Downside",Q86*Assumptions!$C$8,0) -> 0.93641118 | S86: =Q86*L86 -> 0.26044483 | T86: =O86*M86/10000000 -> 0.35006026 | U86: =Q86-SUM(R86:T86) -> -0.46172948 | V86: =IFERROR(U86/Q86,0) -> -0.42548387 | W86: =Assumptions!F138 -> Illustrative (replace with pilot) | X86: =Assumptions!C26&" | "&Assumptions!D26 -> Garam Masala | 5g trial
A87: =Assumptions!A139 -> FY24 | B87: =Assumptions!B139 -> GAR_L | C87: =Assumptions!B27 -> Spices | D87: =Assumptions!C139 -> GT | E87: =Assumptions!E27*(1+Assumptions!$C$11)^2 -> 49 | F87: =Assumptions!F27*(1+Assumptions!$C$12)^2 -> 23.5 | G87: =Assumptions!G27 -> 52 | H87: =Assumptions!D139 -> 70000 | I87: =Assumptions!E139 -> 4.4 | J87: =Assumptions!$C$13 -> 0.95 | K87: =Assumptions!B40 -> 0.25 | L87: =Assumptions!C40+IF(Assumptions!$C$6="Downside",Assumptions!$C$9,0) -> 0.065 | M87: =Assumptions!E40 -> 1 | N87: =H87*I87*G87*IF(Assumptions!$C$6="Downside",1-Assumptions!$C$7,1) -> 16016000 | O87: =N87*J87 -> 15215200 | P87: =E87*(1-K87) -> 36.75 | Q87: =O87*P87/10000000 -> 55.91586 | R87: =O87*F87/10000000+IF(Assumptions!$C$6="Downside",Q87*Assumptions!$C$8,0) -> 35.75572 | S87: =Q87*L87 -> 3.6345309 | T87: =O87*M87/10000000 -> 1.52152 | U87: =Q87-SUM(R87:T87) -> 15.004089 | V87: =IFERROR(U87/Q87,0) -> 0.26833333 | W87: =Assumptions!F139 -> Illustrative (replace with pilot) | X87: =Assumptions!C27&" | "&Assumptions!D27 -> Garam Masala | 50g pouch
A88: =Assumptions!A140 -> FY24 | B88: =Assumptions!B140 -> GAR_L | C88: =Assumptions!B27 -> Spices | D88: =Assumptions!C140 -> Modern | E88: =Assumptions!E27*(1+Assumptions!$C$11)^2 -> 49 | F88: =Assumptions!F27*(1+Assumptions!$C$12)^2 -> 23.5 | G88: =Assumptions!G27 -> 52 | H88: =Assumptions!D140 -> 2450 | I88: =Assumptions!E140 -> 17.6 | J88: =Assumptions!$C$13 -> 0.95 | K88: =Assumptions!B41 -> 0.28 | L88: =Assumptions!C41+IF(Assumptions!$C$6="Downside",Assumptions!$C$9,0) -> 0.14 | M88: =Assumptions!E41 -> 1.7 | N88: =H88*I88*G88*IF(Assumptions!$C$6="Downside",1-Assumptions!$C$7,1) -> 2242240 | O88: =N88*J88 -> 2130128 | P88: =E88*(1-K88) -> 35.28 | Q88: =O88*P88/10000000 -> 7.5150916 | R88: =O88*F88/10000000+IF(Assumptions!$C$6="Downside",Q88*Assumptions!$C$8,0) -> 5.0058008 | S88: =Q88*L88 -> 1.0521128 | T88: =O88*M88/10000000 -> 0.36212176 | U88: =Q88-SUM(R88:T88) -> 1.0950562 | V88: =IFERROR(U88/Q88,0) -> 0.14571429 | W88: =Assumptions!F140 -> Illustrative (replace with pilot) | X88: =Assumptions!C27&" | "&Assumptions!D27 -> Garam Masala | 50g pouch
A89: =Assumptions!A141 -> FY24 | B89: =Assumptions!B141 -> GAR_L | C89: =Assumptions!B27 -> Spices | D89: =Assumptions!C141 -> QCom | E89: =Assumptions!E27*(1+Assumptions!$C$11)^2 -> 49 | F89: =Assumptions!F27*(1+Assumptions!$C$12)^2 -> 23.5 | G89: =Assumptions!G27 -> 52 | H89: =Assumptions!D141 -> 980 | I89: =Assumptions!E141 -> 52.8 | J89: =Assumptions!$C$13 -> 0.95 | K89: =Assumptions!B42 -> 0.38 | L89: =Assumptions!C42+IF(Assumptions!$C$6="Downside",Assumptions!$C$9,0) -> 0.24 | M89: =Assumptions!E42 -> 2 | N89: =H89*I89*G89*IF(Assumptions!$C$6="Downside",1-Assumptions!$C$7,1) -> 2690688 | O89: =N89*J89 -> 2556153.6 | P89: =E89*(1-K89) -> 30.38 | Q89: =O89*P89/10000000 -> 7.7655946 | R89: =O89*F89/10000000+IF(Assumptions!$C$6="Downside",Q89*Assumptions!$C$8,0) -> 6.006961 | S89: =Q89*L89 -> 1.8637427 | T89: =O89*M89/10000000 -> 0.51123072 | U89: =Q89-SUM(R89:T89) -> -0.61633976 | V89: =IFERROR(U89/Q89,0) -> -0.079368005 | W89: =Assumptions!F141 -> Illustrative (replace with pilot) | X89: =Assumptions!C27&" | "&Assumptions!D27 -> Garam Masala | 50g pouch
A90: =Assumptions!A142 -> FY24 | B90: =Assumptions!B142 -> GIN_T | C90: =Assumptions!B28 -> Premixes | D90: =Assumptions!C142 -> GT | E90: =Assumptions!E28*(1+Assumptions!$C$11)^2 -> 10 | F90: =Assumptions!F28*(1+Assumptions!$C$12)^2 -> 4.35 | G90: =Assumptions!G28 -> 26 | H90: =Assumptions!D142 -> 52000 | I90: =Assumptions!E142 -> 5.2 | J90: =Assumptions!$C$13 -> 0.95 | K90: =Assumptions!B40 -> 0.25 | L90: =Assumptions!C40+IF(Assumptions!$C$6="Downside",Assumptions!$C$9,0) -> 0.065 | M90: =Assumptions!E40 -> 1 | N90: =H90*I90*G90*IF(Assumptions!$C$6="Downside",1-Assumptions!$C$7,1) -> 7030400 | O90: =N90*J90 -> 6678880 | P90: =E90*(1-K90) -> 7.5 | Q90: =O90*P90/10000000 -> 5.00916 | R90: =O90*F90/10000000+IF(Assumptions!$C$6="Downside",Q90*Assumptions!$C$8,0) -> 2.9053128 | S90: =Q90*L90 -> 0.3255954 | T90: =O90*M90/10000000 -> 0.667888 | U90: =Q90-SUM(R90:T90) -> 1.1103638 | V90: =IFERROR(U90/Q90,0) -> 0.22166667 | W90: =Assumptions!F142 -> Illustrative (replace with pilot) | X90: =Assumptions!C28&" | "&Assumptions!D28 -> Ginger-Lemon Hot Drink | 15g single sachet
A91: =Assumptions!A143 -> FY24 | B91: =Assumptions!B143 -> GIN_T | C91: =Assumptions!B28 -> Premixes | D91: =Assumptions!C143 -> Modern | E91: =Assumptions!E28*(1+Assumptions!$C$11)^2 -> 10 | F91: =Assumptions!F28*(1+Assumptions!$C$12)^2 -> 4.35 | G91: =Assumptions!G28 -> 26 | H91: =Assumptions!D143 -> 1820 | I91: =Assumptions!E143 -> 20.8 | J91: =Assumptions!$C$13 -> 0.95 | K91: =Assumptions!B41 -> 0.28 | L91: =Assumptions!C41+IF(Assumptions!$C$6="Downside",Assumptions!$C$9,0) -> 0.14 | M91: =Assumptions!E41 -> 1.7 | N91: =H91*I91*G91*IF(Assumptions!$C$6="Downside",1-Assumptions!$C$7,1) -> 984256 | O91: =N91*J91 -> 935043.2 | P91: =E91*(1-K91) -> 7.2 | Q91: =O91*P91/10000000 -> 0.6732311 | R91: =O91*F91/10000000+IF(Assumptions!$C$6="Downside",Q91*Assumptions!$C$8,0) -> 0.40674379 | S91: =Q91*L91 -> 0.094252355 | T91: =O91*M91/10000000 -> 0.15895734 | U91: =Q91-SUM(R91:T91) -> 0.013277613 | V91: =IFERROR(U91/Q91,0) -> 0.019722222 | W91: =Assumptions!F143 -> Illustrative (replace with pilot) | X91: =Assumptions!C28&" | "&Assumptions!D28 -> Ginger-Lemon Hot Drink | 15g single sachet
A92: =Assumptions!A144 -> FY24 | B92: =Assumptions!B144 -> GIN_T | C92: =Assumptions!B28 -> Premixes | D92: =Assumptions!C144 -> QCom | E92: =Assumptions!E28*(1+Assumptions!$C$11)^2 -> 10 | F92: =Assumptions!F28*(1+Assumptions!$C$12)^2 -> 4.35 | G92: =Assumptions!G28 -> 26 | H92: =Assumptions!D144 -> 728 | I92: =Assumptions!E144 -> 62.4 | J92: =Assumptions!$C$13 -> 0.95 | K92: =Assumptions!B42 -> 0.38 | L92: =Assumptions!C42+IF(Assumptions!$C$6="Downside",Assumptions!$C$9,0) -> 0.24 | M92: =Assumptions!E42 -> 2 | N92: =H92*I92*G92*IF(Assumptions!$C$6="Downside",1-Assumptions!$C$7,1) -> 1181107.2 | O92: =N92*J92 -> 1122051.8 | P92: =E92*(1-K92) -> 6.2 | Q92: =O92*P92/10000000 -> 0.69567214 | R92: =O92*F92/10000000+IF(Assumptions!$C$6="Downside",Q92*Assumptions!$C$8,0) -> 0.48809255 | S92: =Q92*L92 -> 0.16696131 | T92: =O92*M92/10000000 -> 0.22441037 | U92: =Q92-SUM(R92:T92) -> -0.18379209 | V92: =IFERROR(U92/Q92,0) -> -0.26419355 | W92: =Assumptions!F144 -> Illustrative (replace with pilot) | X92: =Assumptions!C28&" | "&Assumptions!D28 -> Ginger-Lemon Hot Drink | 15g single sachet
A93: =Assumptions!A145 -> FY24 | B93: =Assumptions!B145 -> GIN_L | C93: =Assumptions!B29 -> Premixes | D93: =Assumptions!C145 -> GT | E93: =Assumptions!E29*(1+Assumptions!$C$11)^2 -> 99 | F93: =Assumptions!F29*(1+Assumptions!$C$12)^2 -> 44 | G93: =Assumptions!G29 -> 26 | H93: =Assumptions!D145 -> 39000 | I93: =Assumptions!E145 -> 4.2 | J93: =Assumptions!$C$13 -> 0.95 | K93: =Assumptions!B40 -> 0.25 | L93: =Assumptions!C40+IF(Assumptions!$C$6="Downside",Assumptions!$C$9,0) -> 0.065 | M93: =Assumptions!E40 -> 1 | N93: =H93*I93*G93*IF(Assumptions!$C$6="Downside",1-Assumptions!$C$7,1) -> 4258800 | O93: =N93*J93 -> 4045860 | P93: =E93*(1-K93) -> 74.25 | Q93: =O93*P93/10000000 -> 30.04051 | R93: =O93*F93/10000000+IF(Assumptions!$C$6="Downside",Q93*Assumptions!$C$8,0) -> 17.801784 | S93: =Q93*L93 -> 1.9526332 | T93: =O93*M93/10000000 -> 0.404586 | U93: =Q93-SUM(R93:T93) -> 9.8815073 | V93: =IFERROR(U93/Q93,0) -> 0.32893939 | W93: =Assumptions!F145 -> Illustrative (replace with pilot) | X93: =Assumptions!C29&" | "&Assumptions!D29 -> Ginger-Lemon Hot Drink | 10-sachet pack
A94: =Assumptions!A146 -> FY24 | B94: =Assumptions!B146 -> GIN_L | C94: =Assumptions!B29 -> Premixes | D94: =Assumptions!C146 -> Modern | E94: =Assumptions!E29*(1+Assumptions!$C$11)^2 -> 99 | F94: =Assumptions!F29*(1+Assumptions!$C$12)^2 -> 44 | G94: =Assumptions!G29 -> 26 | H94: =Assumptions!D146 -> 1365 | I94: =Assumptions!E146 -> 16.8 | J94: =Assumptions!$C$13 -> 0.95 | K94: =Assumptions!B41 -> 0.28 | L94: =Assumptions!C41+IF(Assumptions!$C$6="Downside",Assumptions!$C$9,0) -> 0.14 | M94: =Assumptions!E41 -> 1.7 | N94: =H94*I94*G94*IF(Assumptions!$C$6="Downside",1-Assumptions!$C$7,1) -> 596232 | O94: =N94*J94 -> 566420.4 | P94: =E94*(1-K94) -> 71.28 | Q94: =O94*P94/10000000 -> 4.0374446 | R94: =O94*F94/10000000+IF(Assumptions!$C$6="Downside",Q94*Assumptions!$C$8,0) -> 2.4922498 | S94: =Q94*L94 -> 0.56524225 | T94: =O94*M94/10000000 -> 0.096291468 | U94: =Q94-SUM(R94:T94) -> 0.88366114 | V94: =IFERROR(U94/Q94,0) -> 0.21886644 | W94: =Assumptions!F146 -> Illustrative (replace with pilot) | X94: =Assumptions!C29&" | "&Assumptions!D29 -> Ginger-Lemon Hot Drink | 10-sachet pack
A95: =Assumptions!A147 -> FY24 | B95: =Assumptions!B147 -> GIN_L | C95: =Assumptions!B29 -> Premixes | D95: =Assumptions!C147 -> QCom | E95: =Assumptions!E29*(1+Assumptions!$C$11)^2 -> 99 | F95: =Assumptions!F29*(1+Assumptions!$C$12)^2 -> 44 | G95: =Assumptions!G29 -> 26 | H95: =Assumptions!D147 -> 546 | I95: =Assumptions!E147 -> 50.4 | J95: =Assumptions!$C$13 -> 0.95 | K95: =Assumptions!B42 -> 0.38 | L95: =Assumptions!C42+IF(Assumptions!$C$6="Downside",Assumptions!$C$9,0) -> 0.24 | M95: =Assumptions!E42 -> 2 | N95: =H95*I95*G95*IF(Assumptions!$C$6="Downside",1-Assumptions!$C$7,1) -> 715478.4 | O95: =N95*J95 -> 679704.48 | P95: =E95*(1-K95) -> 61.38 | Q95: =O95*P95/10000000 -> 4.1720261 | R95: =O95*F95/10000000+IF(Assumptions!$C$6="Downside",Q95*Assumptions!$C$8,0) -> 2.9906997 | S95: =Q95*L95 -> 1.0012863 | T95: =O95*M95/10000000 -> 0.1359409 | U95: =Q95-SUM(R95:T95) -> 0.044099227 | V95: =IFERROR(U95/Q95,0) -> 0.010570218 | W95: =Assumptions!F147 -> Illustrative (replace with pilot) | X95: =Assumptions!C29&" | "&Assumptions!D29 -> Ginger-Lemon Hot Drink | 10-sachet pack
A96: =Assumptions!A148 -> FY24 | B96: =Assumptions!B148 -> BAD_T | C96: =Assumptions!B30 -> Premixes | D96: =Assumptions!C148 -> GT | E96: =Assumptions!E30*(1+Assumptions!$C$11)^2 -> 10 | F96: =Assumptions!F30*(1+Assumptions!$C$12)^2 -> 4.5 | G96: =Assumptions!G30 -> 26 | H96: =Assumptions!D148 -> 42000 | I96: =Assumptions!E148 -> 3.6 | J96: =Assumptions!$C$13 -> 0.95 | K96: =Assumptions!B40 -> 0.25 | L96: =Assumptions!C40+IF(Assumptions!$C$6="Downside",Assumptions!$C$9,0) -> 0.065 | M96: =Assumptions!E40 -> 1 | N96: =H96*I96*G96*IF(Assumptions!$C$6="Downside",1-Assumptions!$C$7,1) -> 3931200 | O96: =N96*J96 -> 3734640 | P96: =E96*(1-K96) -> 7.5 | Q96: =O96*P96/10000000 -> 2.80098 | R96: =O96*F96/10000000+IF(Assumptions!$C$6="Downside",Q96*Assumptions!$C$8,0) -> 1.680588 | S96: =Q96*L96 -> 0.1820637 | T96: =O96*M96/10000000 -> 0.373464 | U96: =Q96-SUM(R96:T96) -> 0.5648643 | V96: =IFERROR(U96/Q96,0) -> 0.20166667 | W96: =Assumptions!F148 -> Illustrative (replace with pilot) | X96: =Assumptions!C30&" | "&Assumptions!D30 -> Badam-Elaichi Milk Mix | 15g single sachet
A97: =Assumptions!A149 -> FY24 | B97: =Assumptions!B149 -> BAD_T | C97: =Assumptions!B30 -> Premixes | D97: =Assumptions!C149 -> Modern | E97: =Assumptions!E30*(1+Assumptions!$C$11)^2 -> 10 | F97: =Assumptions!F30*(1+Assumptions!$C$12)^2 -> 4.5 | G97: =Assumptions!G30 -> 26 | H97: =Assumptions!D149 -> 1470 | I97: =Assumptions!E149 -> 14.4 | J97: =Assumptions!$C$13 -> 0.95 | K97: =Assumptions!B41 -> 0.28 | L97: =Assumptions!C41+IF(Assumptions!$C$6="Downside",Assumptions!$C$9,0) -> 0.14 | M97: =Assumptions!E41 -> 1.7 | N97: =H97*I97*G97*IF(Assumptions!$C$6="Downside",1-Assumptions!$C$7,1) -> 550368 | O97: =N97*J97 -> 522849.6 | P97: =E97*(1-K97) -> 7.2 | Q97: =O97*P97/10000000 -> 0.37645171 | R97: =O97*F97/10000000+IF(Assumptions!$C$6="Downside",Q97*Assumptions!$C$8,0) -> 0.23528232 | S97: =Q97*L97 -> 0.05270324 | T97: =O97*M97/10000000 -> 0.088884432 | U97: =Q97-SUM(R97:T97) -> -0.00041827968 | V97: =IFERROR(U97/Q97,0) -> -0.0011111111 | W97: =Assumptions!F149 -> Illustrative (replace with pilot) | X97: =Assumptions!C30&" | "&Assumptions!D30 -> Badam-Elaichi Milk Mix | 15g single sachet
A98: =Assumptions!A150 -> FY24 | B98: =Assumptions!B150 -> BAD_T | C98: =Assumptions!B30 -> Premixes | D98: =Assumptions!C150 -> QCom | E98: =Assumptions!E30*(1+Assumptions!$C$11)^2 -> 10 | F98: =Assumptions!F30*(1+Assumptions!$C$12)^2 -> 4.5 | G98: =Assumptions!G30 -> 26 | H98: =Assumptions!D150 -> 588 | I98: =Assumptions!E150 -> 43.2 | J98: =Assumptions!$C$13 -> 0.95 | K98: =Assumptions!B42 -> 0.38 | L98: =Assumptions!C42+IF(Assumptions!$C$6="Downside",Assumptions!$C$9,0) -> 0.24 | M98: =Assumptions!E42 -> 2 | N98: =H98*I98*G98*IF(Assumptions!$C$6="Downside",1-Assumptions!$C$7,1) -> 660441.6 | O98: =N98*J98 -> 627419.52 | P98: =E98*(1-K98) -> 6.2 | Q98: =O98*P98/10000000 -> 0.3890001 | R98: =O98*F98/10000000+IF(Assumptions!$C$6="Downside",Q98*Assumptions!$C$8,0) -> 0.28233878 | S98: =Q98*L98 -> 0.093360025 | T98: =O98*M98/10000000 -> 0.1254839 | U98: =Q98-SUM(R98:T98) -> -0.11218261 | V98: =IFERROR(U98/Q98,0) -> -0.2883871 | W98: =Assumptions!F150 -> Illustrative (replace with pilot) | X98: =Assumptions!C30&" | "&Assumptions!D30 -> Badam-Elaichi Milk Mix | 15g single sachet
A99: =Assumptions!A151 -> FY24 | B99: =Assumptions!B151 -> BAD_L | C99: =Assumptions!B31 -> Premixes | D99: =Assumptions!C151 -> GT | E99: =Assumptions!E31*(1+Assumptions!$C$11)^2 -> 99 | F99: =Assumptions!F31*(1+Assumptions!$C$12)^2 -> 45.5 | G99: =Assumptions!G31 -> 26 | H99: =Assumptions!D151 -> 34000 | I99: =Assumptions!E151 -> 3.3 | J99: =Assumptions!$C$13 -> 0.95 | K99: =Assumptions!B40 -> 0.25 | L99: =Assumptions!C40+IF(Assumptions!$C$6="Downside",Assumptions!$C$9,0) -> 0.065 | M99: =Assumptions!E40 -> 1 | N99: =H99*I99*G99*IF(Assumptions!$C$6="Downside",1-Assumptions!$C$7,1) -> 2917200 | O99: =N99*J99 -> 2771340 | P99: =E99*(1-K99) -> 74.25 | Q99: =O99*P99/10000000 -> 20.577199 | R99: =O99*F99/10000000+IF(Assumptions!$C$6="Downside",Q99*Assumptions!$C$8,0) -> 12.609597 | S99: =Q99*L99 -> 1.337518 | T99: =O99*M99/10000000 -> 0.277134 | U99: =Q99-SUM(R99:T99) -> 6.3529505 | V99: =IFERROR(U99/Q99,0) -> 0.30873737 | W99: =Assumptions!F151 -> Illustrative (replace with pilot) | X99: =Assumptions!C31&" | "&Assumptions!D31 -> Badam-Elaichi Milk Mix | 150g pouch
A100: =Assumptions!A152 -> FY24 | B100: =Assumptions!B152 -> BAD_L | C100: =Assumptions!B31 -> Premixes | D100: =Assumptions!C152 -> Modern | E100: =Assumptions!E31*(1+Assumptions!$C$11)^2 -> 99 | F100: =Assumptions!F31*(1+Assumptions!$C$12)^2 -> 45.5 | G100: =Assumptions!G31 -> 26 | H100: =Assumptions!D152 -> 1190 | I100: =Assumptions!E152 -> 13.2 | J100: =Assumptions!$C$13 -> 0.95 | K100: =Assumptions!B41 -> 0.28 | L100: =Assumptions!C41+IF(Assumptions!$C$6="Downside",Assumptions!$C$9,0) -> 0.14 | M100: =Assumptions!E41 -> 1.7 | N100: =H100*I100*G100*IF(Assumptions!$C$6="Downside",1-Assumptions!$C$7,1) -> 408408 | O100: =N100*J100 -> 387987.6 | P100: =E100*(1-K100) -> 71.28 | Q100: =O100*P100/10000000 -> 2.7655756 | R100: =O100*F100/10000000+IF(Assumptions!$C$6="Downside",Q100*Assumptions!$C$8,0) -> 1.7653436 | S100: =Q100*L100 -> 0.38718059 | T100: =O100*M100/10000000 -> 0.065957892 | U100: =Q100-SUM(R100:T100) -> 0.54709356 | V100: =IFERROR(U100/Q100,0) -> 0.19782267 | W100: =Assumptions!F152 -> Illustrative (replace with pilot) | X100: =Assumptions!C31&" | "&Assumptions!D31 -> Badam-Elaichi Milk Mix | 150g pouch
A101: =Assumptions!A153 -> FY24 | B101: =Assumptions!B153 -> BAD_L | C101: =Assumptions!B31 -> Premixes | D101: =Assumptions!C153 -> QCom | E101: =Assumptions!E31*(1+Assumptions!$C$11)^2 -> 99 | F101: =Assumptions!F31*(1+Assumptions!$C$12)^2 -> 45.5 | G101: =Assumptions!G31 -> 26 | H101: =Assumptions!D153 -> 476 | I101: =Assumptions!E153 -> 39.6 | J101: =Assumptions!$C$13 -> 0.95 | K101: =Assumptions!B42 -> 0.38 | L101: =Assumptions!C42+IF(Assumptions!$C$6="Downside",Assumptions!$C$9,0) -> 0.24 | M101: =Assumptions!E42 -> 2 | N101: =H101*I101*G101*IF(Assumptions!$C$6="Downside",1-Assumptions!$C$7,1) -> 490089.6 | O101: =N101*J101 -> 465585.12 | P101: =E101*(1-K101) -> 61.38 | Q101: =O101*P101/10000000 -> 2.8577615 | R101: =O101*F101/10000000+IF(Assumptions!$C$6="Downside",Q101*Assumptions!$C$8,0) -> 2.1184123 | S101: =Q101*L101 -> 0.68586275 | T101: =O101*M101/10000000 -> 0.093117024 | U101: =Q101-SUM(R101:T101) -> -0.039630605 | V101: =IFERROR(U101/Q101,0) -> -0.013867709 | W101: =Assumptions!F153 -> Illustrative (replace with pilot) | X101: =Assumptions!C31&" | "&Assumptions!D31 -> Badam-Elaichi Milk Mix | 150g pouch
A102: =Assumptions!A154 -> FY24 | B102: =Assumptions!B154 -> CHU_T | C102: =Assumptions!B32 -> Condiments | D102: =Assumptions!C154 -> GT | E102: =Assumptions!E32*(1+Assumptions!$C$11)^2 -> 10 | F102: =Assumptions!F32*(1+Assumptions!$C$12)^2 -> 4.8 | G102: =Assumptions!G32 -> 52 | H102: =Assumptions!D154 -> 43000 | I102: =Assumptions!E154 -> 2.9 | J102: =Assumptions!$C$13 -> 0.95 | K102: =Assumptions!B40 -> 0.25 | L102: =Assumptions!C40+IF(Assumptions!$C$6="Downside",Assumptions!$C$9,0) -> 0.065 | M102: =Assumptions!E40 -> 1 | N102: =H102*I102*G102*IF(Assumptions!$C$6="Downside",1-Assumptions!$C$7,1) -> 6484400 | O102: =N102*J102 -> 6160180 | P102: =E102*(1-K102) -> 7.5 | Q102: =O102*P102/10000000 -> 4.620135 | R102: =O102*F102/10000000+IF(Assumptions!$C$6="Downside",Q102*Assumptions!$C$8,0) -> 2.9568864 | S102: =Q102*L102 -> 0.30030877 | T102: =O102*M102/10000000 -> 0.616018 | U102: =Q102-SUM(R102:T102) -> 0.74692183 | V102: =IFERROR(U102/Q102,0) -> 0.16166667 | W102: =Assumptions!F154 -> Illustrative (replace with pilot) | X102: =Assumptions!C32&" | "&Assumptions!D32 -> Tamarind-Date Chutney | 20g sachet
...

Sheet Portfolio
A1: PORTFOLIO | company revenue bridge & FY24 targets
A5: Revenue bridge (₹Cr) | B5: FY21 actual | C5: FY22 | D5: FY23 | E5: FY24
A6: Legacy portfolio | B6: =Assumptions!F6 -> 560 | C6: =Assumptions!B17 -> 580 | D6: =Assumptions!C17 -> 605 | E6: =Assumptions!D17 -> 630
A7: Spices — new | C7: =SUMIFS(SKU_Channel_Model!$Q$6:$Q$113,SKU_Channel_Model!$A$6:$A$113,"FY22",SKU_Channel_Model!$C$6:$C$113,"Spices") -> 17.711862 | D7: =SUMIFS(SKU_Channel_Model!$Q$6:$Q$113,SKU_Channel_Model!$A$6:$A$113,"FY23",SKU_Channel_Model!$C$6:$C$113,"Spices") -> 90.929627 | E7: =SUMIFS(SKU_Channel_Model!$Q$6:$Q$113,SKU_Channel_Model!$A$6:$A$113,"FY24",SKU_Channel_Model!$C$6:$C$113,"Spices") -> 184.48265
A8: Winter premixes — new | C8: =SUMIFS(SKU_Channel_Model!$Q$6:$Q$113,SKU_Channel_Model!$A$6:$A$113,"FY22",SKU_Channel_Model!$C$6:$C$113,"Premixes") -> 7.1380447 | D8: =SUMIFS(SKU_Channel_Model!$Q$6:$Q$113,SKU_Channel_Model!$A$6:$A$113,"FY23",SKU_Channel_Model!$C$6:$C$113,"Premixes") -> 36.668846 | E8: =SUMIFS(SKU_Channel_Model!$Q$6:$Q$113,SKU_Channel_Model!$A$6:$A$113,"FY24",SKU_Channel_Model!$C$6:$C$113,"Premixes") -> 74.395013
A9: Condiments — new | C9: =SUMIFS(SKU_Channel_Model!$Q$6:$Q$113,SKU_Channel_Model!$A$6:$A$113,"FY22",SKU_Channel_Model!$C$6:$C$113,"Condiments") -> 7.9836316 | D9: =SUMIFS(SKU_Channel_Model!$Q$6:$Q$113,SKU_Channel_Model!$A$6:$A$113,"FY23",SKU_Channel_Model!$C$6:$C$113,"Condiments") -> 41.036876 | E9: =SUMIFS(SKU_Channel_Model!$Q$6:$Q$113,SKU_Channel_Model!$A$6:$A$113,"FY24",SKU_Channel_Model!$C$6:$C$113,"Condiments") -> 83.155415
A10: NEW product sales | B10: =Assumptions!F6*Assumptions!F7 -> 23.52 | C10: =SUM(C7:C9) -> 32.833539 | D10: =SUM(D7:D9) -> 168.63535 | E10: =SUM(E7:E9) -> 342.03308
A11: Company total (model) | B11: =B6 -> 560 | C11: =SUM(C6,C10) -> 612.83354 | D11: =SUM(D6,D10) -> 773.63535 | E11: =SUM(E6,E10) -> 972.03308
A12: New share of total | B12: =Assumptions!F7 -> 0.042 | C12: =IFERROR(C10/C11,0) -> 0.053576602 | D12: =IFERROR(D10/D11,0) -> 0.21797782 | E12: =IFERROR(E10/E11,0) -> 0.35187391
A13: Company revenue growth | B13: =Assumptions!C7*0 -> 0 | C13: =IFERROR(C11/Assumptions!F6-1,0) -> 0.094345605 | D13: =IFERROR(D11/C11-1,0) -> 0.26239068 | E13: =IFERROR(E11/D11-1,0) -> 0.25644863
A14: Target: new share | C14: =Assumptions!F12 -> 0.3 | D14: =Assumptions!F12 -> 0.3 | E14: =Assumptions!F12 -> 0.3
A15: Target: company revenue | C15: =IF(C$5="FY24",Assumptions!F11,0) -> 0 | D15: =IF(D$5="FY24",Assumptions!F11,0) -> 0 | E15: =IF(E$5="FY24",Assumptions!F11,0) -> 900
A16: Gap to ₹900 Cr | C16: =IF(C$5="FY24",C11-C15,0) -> 0 | D16: =IF(D$5="FY24",D11-D15,0) -> 0 | E16: =IF(E$5="FY24",E11-E15,0) -> 72.033077
A17: Gap to 30% share | C17: =IF(C$5="FY24",C12-C14,0) -> 0 | D17: =IF(D$5="FY24",D12-D14,0) -> 0 | E17: =IF(E$5="FY24",E12-E14,0) -> 0.051873907
A18: Target: spices | C18: =Assumptions!B18 -> 10 | D18: =Assumptions!C18 -> 70 | E18: =Assumptions!D18 -> 135
A19: Target: premixes | C19: =Assumptions!B19 -> 8 | D19: =Assumptions!C19 -> 40 | E19: =Assumptions!D19 -> 75
A20: Target: condiments | C20: =Assumptions!B20 -> 2 | D20: =Assumptions!C20 -> 25 | E20: =Assumptions!D20 -> 60
A21: Spices gap vs plan | C21: =C7-C18 -> 7.7118624 | D21: =D7-D18 -> 20.929627 | E21: =E7-E18 -> 49.482649
A22: Premixes gap vs plan | C22: =C8-C19 -> -0.86195532 | D22: =D8-D19 -> -3.3311542 | E22: =E8-E19 -> -0.60498715
A23: Condiments gap vs plan | C23: =C9-C20 -> 5.9836316 | D23: =D9-D20 -> 16.036876 | E23: =E9-E20 -> 23.155415

Sheet P_and_L
A1: INCREMENTAL NPD P&L | ₹ Cr, FY22–FY24
A5: P&L line / ₹Cr | B5: FY22 | C5: FY23 | D5: FY24
A6: Net product sales (realisation) | B6: =SUMIFS(SKU_Channel_Model!$Q$6:$Q$113,SKU_Channel_Model!$A$6:$A$113,"FY22") -> 32.833539 | C6: =SUMIFS(SKU_Channel_Model!$Q$6:$Q$113,SKU_Channel_Model!$A$6:$A$113,"FY23") -> 168.63535 | D6: =SUMIFS(SKU_Channel_Model!$Q$6:$Q$113,SKU_Channel_Model!$A$6:$A$113,"FY24") -> 342.03308
A7: Product COGS incl. shock | B7: =SUMIFS(SKU_Channel_Model!$R$6:$R$113,SKU_Channel_Model!$A$6:$A$113,"FY22") -> 21.224118 | C7: =SUMIFS(SKU_Channel_Model!$R$6:$R$113,SKU_Channel_Model!$A$6:$A$113,"FY23") -> 109.0063 | D7: =SUMIFS(SKU_Channel_Model!$R$6:$R$113,SKU_Channel_Model!$A$6:$A$113,"FY24") -> 221.09383
A8: Gross profit | B8: =B6-B7 -> 11.609421 | C8: =C6-C7 -> 59.629051 | D8: =D6-D7 -> 120.93925
A9: Gross margin | B9: =IFERROR(B8/B6,0) -> 0.35358421 | C9: =IFERROR(C8/C6,0) -> 0.35359758 | D9: =IFERROR(D8/D6,0) -> 0.35358933
A10: Channel trade spend / schemes | B10: =SUMIFS(SKU_Channel_Model!$S$6:$S$113,SKU_Channel_Model!$A$6:$A$113,"FY22") -> 3.0207239 | C10: =SUMIFS(SKU_Channel_Model!$S$6:$S$113,SKU_Channel_Model!$A$6:$A$113,"FY23") -> 15.513718 | D10: =SUMIFS(SKU_Channel_Model!$S$6:$S$113,SKU_Channel_Model!$A$6:$A$113,"FY24") -> 31.468504
A11: Freight and fulfilment | B11: =SUMIFS(SKU_Channel_Model!$T$6:$T$113,SKU_Channel_Model!$A$6:$A$113,"FY22") -> 1.4401187 | C11: =SUMIFS(SKU_Channel_Model!$T$6:$T$113,SKU_Channel_Model!$A$6:$A$113,"FY23") -> 7.3946239 | D11: =SUMIFS(SKU_Channel_Model!$T$6:$T$113,SKU_Channel_Model!$A$6:$A$113,"FY24") -> 15.001388
A12: Contribution after variable costs | B12: =B8-SUM(B10:B11) -> 7.1485783 | C12: =C8-SUM(C10:C11) -> 36.720708 | D12: =D8-SUM(D10:D11) -> 74.469354
A13: Contribution margin | B13: =IFERROR(B12/B6,0) -> 0.21772184 | C13: =IFERROR(C12/C6,0) -> 0.21775214 | D13: =IFERROR(D12/D6,0) -> 0.21772559
A14: Programme A&P / sampling | B14: =Assumptions!B47 -> 8 | C14: =Assumptions!C47 -> 14 | D14: =Assumptions!D47 -> 13
A15: Programme R&D, testing, QA | B15: =Assumptions!B49 -> 3 | C15: =Assumptions!C49 -> 2 | D15: =Assumptions!D49 -> 2
A16: Incremental selling/training | B16: =Assumptions!B50 -> 1 | C16: =Assumptions!C50 -> 2 | D16: =Assumptions!D50 -> 2
A17: Incremental EBITDA / operating profit | B17: =B12-SUM(B14:B16) -> -4.8514217 | C17: =C12-SUM(C14:C16) -> 18.720708 | D17: =D12-SUM(D14:D16) -> 57.469354
A18: Incremental EBITDA margin | B18: =IFERROR(B17/B6,0) -> -0.14775811 | C18: =IFERROR(C17/C6,0) -> 0.11101296 | D18: =IFERROR(D17/D6,0) -> 0.1680228
A19: Variable costs / sales | B19: =IFERROR(SUM(B7,B11)/B6,0) -> 0.690277 | C19: =IFERROR(SUM(C7,C11)/C6,0) -> 0.69025221 | D19: =IFERROR(SUM(D7,D11)/D6,0) -> 0.69027013
A20: Trade costs / sales | B20: =IFERROR(B10/B6,0) -> 0.092001167 | C20: =IFERROR(C10/C6,0) -> 0.091995648 | D20: =IFERROR(D10/D6,0) -> 0.092004272
A23: Assumes programme marketing budget includes all above-the-line / sampling; avoids double-counting within per-unit trade spend.

Sheet Working_Capital
A1: INCREMENTAL WORKING CAPITAL | funding cash requirement
A5: Working capital (₹Cr) | B5: FY22 | C5: FY23 | D5: FY24
A6: GT net sales | B6: =SUMIFS(SKU_Channel_Model!$Q$6:$Q$113,SKU_Channel_Model!$A$6:$A$113,"FY22",SKU_Channel_Model!$D$6:$D$113,"GT") -> 25.787867 | C6: =SUMIFS(SKU_Channel_Model!$Q$6:$Q$113,SKU_Channel_Model!$A$6:$A$113,"FY23",SKU_Channel_Model!$D$6:$D$113,"GT") -> 132.45762 | D6: =SUMIFS(SKU_Channel_Model!$Q$6:$Q$113,SKU_Channel_Model!$A$6:$A$113,"FY24",SKU_Channel_Model!$D$6:$D$113,"GT") -> 268.62361
A7: Modern net sales | B7: =SUMIFS(SKU_Channel_Model!$Q$6:$Q$113,SKU_Channel_Model!$A$6:$A$113,"FY22",SKU_Channel_Model!$D$6:$D$113,"Modern") -> 3.4644868 | C7: =SUMIFS(SKU_Channel_Model!$Q$6:$Q$113,SKU_Channel_Model!$A$6:$A$113,"FY23",SKU_Channel_Model!$D$6:$D$113,"Modern") -> 17.786824 | D7: =SUMIFS(SKU_Channel_Model!$Q$6:$Q$113,SKU_Channel_Model!$A$6:$A$113,"FY24",SKU_Channel_Model!$D$6:$D$113,"Modern") -> 36.103014
A8: QCom net sales | B8: =SUMIFS(SKU_Channel_Model!$Q$6:$Q$113,SKU_Channel_Model!$A$6:$A$113,"FY22",SKU_Channel_Model!$D$6:$D$113,"QCom") -> 3.5811848 | C8: =SUMIFS(SKU_Channel_Model!$Q$6:$Q$113,SKU_Channel_Model!$A$6:$A$113,"FY23",SKU_Channel_Model!$D$6:$D$113,"QCom") -> 18.390908 | D8: =SUMIFS(SKU_Channel_Model!$Q$6:$Q$113,SKU_Channel_Model!$A$6:$A$113,"FY24",SKU_Channel_Model!$D$6:$D$113,"QCom") -> 37.306448
A9: Trade receivables / AR | B9: =SUMPRODUCT(B6:B8,Assumptions!$D$40:$D$42+B18)/365 -> 2.2247809 | C9: =SUMPRODUCT(C6:C8,Assumptions!$D$40:$D$42+C18)/365 -> 11.426099 | D9: =SUMPRODUCT(D6:D8,Assumptions!$D$40:$D$42+D18)/365 -> 23.176816
A10: Product cost of goods | B10: =P_and_L!B7 -> 21.224118 | C10: =P_and_L!C7 -> 109.0063 | D10: =P_and_L!D7 -> 221.09383
A11: Inventory cash tied up | B11: =IFERROR(B10*SUMPRODUCT(B6:B8,Assumptions!$F$40:$F$42)/SUM(B6:B8)/365,0) -> 1.6267048 | C11: =IFERROR(C10*SUMPRODUCT(C6:C8,Assumptions!$F$40:$F$42)/SUM(C6:C8)/365,0) -> 8.3546383 | D11: =IFERROR(D10*SUMPRODUCT(D6:D8,Assumptions!$F$40:$F$42)/SUM(D6:D8)/365,0) -> 16.945704
A12: Trade payables / AP | B12: =IFERROR(B10*SUMPRODUCT(B6:B8,Assumptions!$G$40:$G$42)/SUM(B6:B8)/365,0) -> 1.744448 | C12: =IFERROR(C10*SUMPRODUCT(C6:C8,Assumptions!$G$40:$G$42)/SUM(C6:C8)/365,0) -> 8.9594218 | D12: =IFERROR(D10*SUMPRODUCT(D6:D8,Assumptions!$G$40:$G$42)/SUM(D6:D8)/365,0) -> 18.172096
A13: Incremental net working capital | B13: =SUM(B9,B11)-B12 -> 2.1070377 | C13: =SUM(C9,C11)-C12 -> 10.821315 | D13: =SUM(D9,D11)-D12 -> 21.950424
A14: Change in NWC (cash used) | B14: =B13-0 -> 2.1070377 | C14: =C13-B13 -> 8.7142777 | D14: =D13-C13 -> 11.129109
A15: Available WC funding envelope cumulative | B15: =SUM(Assumptions!$B$48:B$48) -> 4 | C15: =SUM(Assumptions!$B$48:C$48) -> 11 | D15: =SUM(Assumptions!$B$48:D$48) -> 18
A16: NWC headroom / (shortfall) | B16: =B15-B13 -> 1.8929623 | C16: =C15-C13 -> 0.17868461 | D16: =D15-D13 -> -3.9504242
A17: NWC % of net sales | B17: =IFERROR(B13/SUM(B6:B8),0) -> 0.064173334 | C17: =IFERROR(C13/SUM(C6:C8),0) -> 0.064169911 | D17: =IFERROR(D13/SUM(D6:D8),0) -> 0.06417632
A18: Scenario DSO delta (days) | B18: =IF(Assumptions!$C$6="Downside",Assumptions!$C$10,0) -> 0 | C18: =IF(Assumptions!$C$6="Downside",Assumptions!$C$10,0) -> 0 | D18: =IF(Assumptions!$C$6="Downside",Assumptions!$C$10,0) -> 0
A21: Inventory and supplier credit use illustrative average days; channel-specific cost ratios require supplier negotiation and detailed pilots.

Sheet Cash_Flow
A1: PROJECT CASH FLOW | payback, funding & budget constraints
A5: Incremental project (₹ Cr) | B5: FY22 | C5: FY23 | D5: FY24
A6: Contribution before programme A&P | B6: =P_and_L!B12 -> 7.1485783 | C6: =P_and_L!C12 -> 36.720708 | D6: =P_and_L!D12 -> 74.469354
A7: Programme cash A&P, QA and selling | B7: =SUM(P_and_L!B14:P14) -> 35 | C7: =SUM(P_and_L!C14:P14) -> 27 | D7: =SUM(P_and_L!D14:P14) -> 13
A8: Operating cash before working capital | B8: =B6-B7 -> -27.851422 | C8: =C6-C7 -> 9.7207085 | D8: =D6-D7 -> 61.469354
A9: Change in NWC (investment) | B9: =Working_Capital!B14 -> 2.1070377 | C9: =Working_Capital!C14 -> 8.7142777 | D9: =Working_Capital!D14 -> 11.129109
A10: Capital expenditure | B10: =Assumptions!B51 -> 1 | C10: =Assumptions!C51 -> 2 | D10: =Assumptions!D51 -> 2
A11: Net project free cash flow | B11: =B8-SUM(B9:B10) -> -30.958459 | C11: =C8-SUM(C9:C10) -> -0.99356924 | D11: =D8-SUM(D9:D10) -> 48.340246
A12: Cumulative project free cash flow | B12: =0+B11 -> -30.958459 | C12: =B12+C11 -> -31.952029 | D12: =C12+D11 -> 16.388217
A13: Undrawn contingency budget | B13: =Assumptions!B52 -> 1 | C13: =Assumptions!C52 -> 2 | D13: =Assumptions!D52 -> 2
A14: Total budget commitments (all uses) | B14: =Assumptions!B53 -> 18 | C14: =Assumptions!C53 -> 29 | D14: =Assumptions!D53 -> 28
A15: Cumulative budget committed | B15: =SUM($B14:B14) -> 18 | C15: =SUM($B14:C14) -> 47 | D15: =SUM($B14:D14) -> 75
A16: Cumulative commitment capacity | B16: =Assumptions!$F$10 -> 75 | C16: =Assumptions!$F$10 -> 75 | D16: =Assumptions!$F$10 -> 75
A17: Budget headroom | B17: =B16-B15 -> 57 | C17: =C16-C15 -> 28 | D17: =D16-D15 -> 0
A18: Cumulative A&P, QA, selling and capex | B18: =SUM($B7:B7)+SUM($B10:B10) -> 36 | C18: =SUM($B7:C7)+SUM($B10:C10) -> 65 | D18: =SUM($B7:D7)+SUM($B10:D10) -> 80
A19: NWC financing requirement | B19: =Working_Capital!B13 -> 2.1070377 | C19: =Working_Capital!C13 -> 10.821315 | D19: =Working_Capital!D13 -> 21.950424
A20: Project cash recovery achieved? | B20: =IF(B12>=0,"YES","NO") -> NO | C20: =IF(C12>=0,"YES","NO") -> NO | D20: =IF(D12>=0,"YES","NO") -> YES
A21: Cumulative free cash flow incl. FY21 start 0 | B21: =B12 -> -30.958459 | C21: =C12 -> -31.952029 | D21: =D12 -> 16.388217
A24: Payback here means cumulative project FCF ≥0; cash flows exclude tax, depreciation, financing, terminal value and core-biz profit.
A25: ₹18Cr is a working-capital financing envelope, NOT cash expense. ₹5Cr contingency is a reserve, not automatically spent.

Sheet Seasonality
A1: SEASONALITY | FY24 new-product revenue allocation
A5: Category | B5: Q1 Apr–Jun | C5: Q2 Jul–Sep | D5: Q3 Oct–Dec | E5: Q4 Jan–Mar | F5: Total
A6: Spices | B6: =Portfolio!E7*Assumptions!K57 -> 40.586183 | C6: =Portfolio!E7*Assumptions!L57 -> 44.275836 | D6: =Portfolio!E7*Assumptions!M57 -> 49.810315 | E6: =Portfolio!E7*Assumptions!N57 -> 49.810315 | F6: =SUM(B6:E6) -> 184.48265
A7: Premixes | B7: =Portfolio!E8*Assumptions!K58 -> 1.4879003 | C7: =Portfolio!E8*Assumptions!L58 -> 2.9758005 | D7: =Portfolio!E8*Assumptions!M58 -> 37.197506 | E7: =Portfolio!E8*Assumptions!N58 -> 32.733806 | F7: =SUM(B7:E7) -> 74.395013
A8: Condiments | B8: =Portfolio!E9*Assumptions!K59 -> 18.294191 | C8: =Portfolio!E9*Assumptions!L59 -> 20.788854 | D8: =Portfolio!E9*Assumptions!M59 -> 23.283516 | E8: =Portfolio!E9*Assumptions!N59 -> 20.788854 | F8: =SUM(B8:E8) -> 83.155415
A9: All new products | B9: =SUM(B6:B8) -> 60.368274 | C9: =SUM(C6:C8) -> 68.04049 | D9: =SUM(D6:D8) -> 110.29134 | E9: =SUM(E6:E8) -> 103.33297 | F9: =SUM(F6:F8) -> 342.03308
A11: New product quarterly share | B11: =IFERROR(B9/$F$9,0) -> 0.17649835 | C11: =IFERROR(C9/$F$9,0) -> 0.19892956 | D11: =IFERROR(D9/$F$9,0) -> 0.32245811 | E11: =IFERROR(E9/$F$9,0) -> 0.30211398
A13: Legacy core volume seasonal proxy | B13: =Assumptions!K60 -> 0.41 | C13: =Assumptions!L60 -> 0.23 | D13: =Assumptions!M60 -> 0.15 | E13: =Assumptions!N60 -> 0.21
A14: Illustrative legacy sales using volume proxy | B14: =Portfolio!E6*B13 -> 258.3 | C14: =Portfolio!E6*C13 -> 144.9 | D14: =Portfolio!E6*D13 -> 94.5 | E14: =Portfolio!E6*E13 -> 132.3
A15: Company Qtr revenue proxy | B15: =SUM(B9,B14) -> 318.66827 | C15: =SUM(C9,C14) -> 212.94049 | D15: =SUM(D9,D14) -> 204.79134 | E15: =SUM(E9,E14) -> 235.63297
A16: Company quarterly mix proxy | B16: =IFERROR(B15/SUM($B15:$E15),0) -> 0.32783686 | C16: =IFERROR(C15/SUM($B15:$E15),0) -> 0.21906712 | D16: =IFERROR(D15/SUM($B15:$E15),0) -> 0.21068351 | E16: =IFERROR(E15/SUM($B15:$E15),0) -> 0.24241251
A19: FY21 core quarter shares are VOLUME. Applying to legacy SALES is explicitly a simplifying proxy, not case-certified quarterly revenue.
A20: With third-party food manufacturing, new-food sales do not automatically improve beverage plant utilisation.

Sheet Checks
A1: CHECKS & DECISION GATES | PASS is not proof of demand
A5: Question / requirement | B5: FY22 | C5: FY23 | D5: FY24
A6: Company sales ₹Cr | B6: =Portfolio!C11 -> 612.83354 | C6: =Portfolio!D11 -> 773.63535 | D6: =Portfolio!E11 -> 972.03308
A7: Fresh-new NPD sales ₹Cr | B7: =Portfolio!C10 -> 32.833539 | C7: =Portfolio!D10 -> 168.63535 | D7: =Portfolio!E10 -> 342.03308
A8: NPD share of sales | B8: =Portfolio!C12 -> 0.053576602 | C8: =Portfolio!D12 -> 0.21797782 | D8: =Portfolio!E12 -> 0.35187391
A9: 30% target hit in FY24 | B9: =IF(B$5="FY24",IF(Portfolio!C12>=Assumptions!F12,"PASS","GAP"),"N/A") -> N/A | C9: =IF(C$5="FY24",IF(Portfolio!D12>=Assumptions!F12,"PASS","GAP"),"N/A") -> N/A | D9: =IF(D$5="FY24",IF(Portfolio!E12>=Assumptions!F12,"PASS","GAP"),"N/A") -> PASS
A10: ₹900Cr topline target hit FY24 | B10: =IF(B$5="FY24",IF(Portfolio!C11>=Assumptions!F11,"PASS","GAP"),"N/A") -> N/A | C10: =IF(C$5="FY24",IF(Portfolio!D11>=Assumptions!F11,"PASS","GAP"),"N/A") -> N/A | D10: =IF(D$5="FY24",IF(Portfolio!E11>=Assumptions!F11,"PASS","GAP"),"N/A") -> PASS
A11: ₹75Cr programme budget | B11: =IF(Cash_Flow!B15<=Assumptions!F10,"PASS","OVER BUDGET") -> PASS | C11: =IF(Cash_Flow!C15<=Assumptions!F10,"PASS","OVER BUDGET") -> PASS | D11: =IF(Cash_Flow!D15<=Assumptions!F10,"PASS","OVER BUDGET") -> PASS
A12: Actual NWC within cumulative ₹18Cr envelope | B12: =IF(Working_Capital!B16>=0,"PASS","SHORTFALL") -> PASS | C12: =IF(Working_Capital!C16>=0,"PASS","SHORTFALL") -> PASS | D12: =IF(Working_Capital!D16>=0,"PASS","SHORTFALL") -> SHORTFALL
A13: Project FCF cumulatively positive | B13: =IF(Cash_Flow!B12>=0,"PASS","UNRECOVERED") -> UNRECOVERED | C13: =IF(Cash_Flow!C12>=0,"PASS","UNRECOVERED") -> UNRECOVERED | D13: =IF(Cash_Flow!D12>=0,"PASS","UNRECOVERED") -> PASS
A14: Product contribution positive | B14: =IF(P_and_L!B12>=0,"PASS","LOSS") -> PASS | C14: =IF(P_and_L!C12>=0,"PASS","LOSS") -> PASS | D14: =IF(P_and_L!D12>=0,"PASS","LOSS") -> PASS
A15: New revenue vs team annual target | B15: =SUM(Assumptions!B18:B20)-Portfolio!C10 -> -12.833539 | C15: =SUM(Assumptions!C18:C20)-Portfolio!D10 -> -33.635349 | D15: =SUM(Assumptions!D18:D20)-Portfolio!E10 -> -72.033077
A16: FY24 target gap in ₹Cr | B16: =IF(B$5="FY24",Portfolio!C11-Assumptions!F11,0) -> 0 | C16: =IF(C$5="FY24",Portfolio!D11-Assumptions!F11,0) -> 0 | D16: =IF(D$5="FY24",Portfolio!E11-Assumptions!F11,0) -> 72.033077
A17: Q4 / Q3 season sales share
A18: Anonymised region assumptions needed | B18: SOURCE NOT GIVEN | C18: SOURCE NOT GIVEN | D18: SOURCE NOT GIVEN
A19: Consumer demand validation status | B19: UNVALIDATED | C19: UNVALIDATED | D19: UNVALIDATED
A20: Case baseline EBITDA coverage | B20: NOT MODELED | C20: NOT MODELED | D20: NOT MODELED
A21: Working-capital DSO shock included | B21: =IF(Assumptions!C6="Downside","YES","BASE") -> BASE | C21: =IF(Assumptions!C6="Downside","YES","BASE") -> BASE | D21: =IF(Assumptions!C6="Downside","YES","BASE") -> BASE
A22: Product C legacy negative margin checked | B22: EXHIBIT 2: -₹7.1Cr | C22: EXHIBIT 2: -₹7.1Cr | D22: EXHIBIT 2: -₹7.1Cr
A23: FY24 GT distributor modeled net earnings | D23: =IF(Distributor_Econ!J19>0,"PASS","LOSS") -> PASS
A24: FY24 individual SKU/channel negative contribution rows | D24: =COUNTIFS(SKU_Channel_Model!$A$6:$A$113,"FY24",SKU_Channel_Model!$U$6:$U$113,"<0") -> 16
A25: PASS on target compares outputs to case targets; all outcomes remain projections until sales, conversion and product costs are validated.

Sheet Distributor_Econ
A1: TRADE SAFEGUARD | FY24 distributor profit by SKU
A3: Exhibit 2 retail 18% & distributor 8% (of retailer net) imply 24.56% combined margin; channel engine uses rounded 25% Exhibit 3.
A5: SKU code | B5: Pack format | C5: MRP ₹ | D5: FY24 GT net units | E5: Consumer sell-out ₹Cr | F5: Retailer margin ₹Cr | G5: Dist gross margin ₹Cr | H5: Handling ₹Cr | I5: Financing ₹Cr | J5: Dist net earnings ₹Cr | K5: Per dist annual ₹ | L5: Dist earn ₹/pack | M5: Commercial check
A6: =Assumptions!A24 -> SAB_T | B6: =Assumptions!D24 -> 8g trial | C6: =Assumptions!E24*(1+Assumptions!$C$11)^2 -> 10 | D6: =SUMIFS(SKU_Channel_Model!$O$6:$O$113,SKU_Channel_Model!$A$6:$A$113,"FY24",SKU_Channel_Model!$B$6:$B$113,A6,SKU_Channel_Model!$D$6:$D$113,"GT") -> 13807300 | E6: =D6*C6/10000000 -> 13.8073 | F6: =E6*Assumptions!$K$6 -> 2.485314 | G6: =(E6-F6)*Assumptions!$K$7 -> 0.90575888 | H6: =D6*IF(RIGHT(A6,2)="_T",Assumptions!$K$8,Assumptions!$K$9)/10000000 -> 0.552292 | I6: =(E6-SUM(F6:G6))*SUM(Assumptions!$K$10,Assumptions!$K$13)/365*Assumptions!$K$11 -> 0.15581534 | J6: =G6-SUM(H6:I6) -> 0.19765154 | K6: =IFERROR(J6*10000000/Assumptions!$K$12,0) -> 5067.9881 | L6: =IFERROR(G6*10000000/D6,0) -> 0.656 | M6: =IF(J6>0,"PASS","LOSS") -> PASS
A7: =Assumptions!A25 -> SAB_L | B7: =Assumptions!D25 -> 50g pouch | C7: =Assumptions!E25*(1+Assumptions!$C$11)^2 -> 49 | D7: =SUMIFS(SKU_Channel_Model!$O$6:$O$113,SKU_Channel_Model!$A$6:$A$113,"FY24",SKU_Channel_Model!$B$6:$B$113,A7,SKU_Channel_Model!$D$6:$D$113,"GT") -> 19266000 | E7: =D7*C7/10000000 -> 94.4034 | F7: =E7*Assumptions!$K$6 -> 16.992612 | G7: =(E7-F7)*Assumptions!$K$7 -> 6.192863 | H7: =D7*IF(RIGHT(A7,2)="_T",Assumptions!$K$8,Assumptions!$K$9)/10000000 -> 4.23852 | I7: =(E7-SUM(F7:G7))*SUM(Assumptions!$K$10,Assumptions!$K$13)/365*Assumptions!$K$11 -> 1.0653421 | J7: =G7-SUM(H7:I7) -> 0.88900093 | K7: =IFERROR(J7*10000000/Assumptions!$K$12,0) -> 22794.896 | L7: =IFERROR(G7*10000000/D7,0) -> 3.2144 | M7: =IF(J7>0,"PASS","LOSS") -> PASS
A8: =Assumptions!A26 -> GAR_T | B8: =Assumptions!D26 -> 5g trial | C8: =Assumptions!E26*(1+Assumptions!$C$11)^2 -> 10 | D8: =SUMIFS(SKU_Channel_Model!$O$6:$O$113,SKU_Channel_Model!$A$6:$A$113,"FY24",SKU_Channel_Model!$B$6:$B$113,A8,SKU_Channel_Model!$D$6:$D$113,"GT") -> 10418460 | E8: =D8*C8/10000000 -> 10.41846 | F8: =E8*Assumptions!$K$6 -> 1.8753228 | G8: =(E8-F8)*Assumptions!$K$7 -> 0.68345098 | H8: =D8*IF(RIGHT(A8,2)="_T",Assumptions!$K$8,Assumptions!$K$9)/10000000 -> 0.4167384 | I8: =(E8-SUM(F8:G8))*SUM(Assumptions!$K$10,Assumptions!$K$13)/365*Assumptions!$K$11 -> 0.11757229 | J8: =G8-SUM(H8:I8) -> 0.14914028 | K8: =IFERROR(J8*10000000/Assumptions!$K$12,0) -> 3824.1098 | L8: =IFERROR(G8*10000000/D8,0) -> 0.656 | M8: =IF(J8>0,"PASS","LOSS") -> PASS
A9: =Assumptions!A27 -> GAR_L | B9: =Assumptions!D27 -> 50g pouch | C9: =Assumptions!E27*(1+Assumptions!$C$11)^2 -> 49 | D9: =SUMIFS(SKU_Channel_Model!$O$6:$O$113,SKU_Channel_Model!$A$6:$A$113,"FY24",SKU_Channel_Model!$B$6:$B$113,A9,SKU_Channel_Model!$D$6:$D$113,"GT") -> 15215200 | E9: =D9*C9/10000000 -> 74.55448 | F9: =E9*Assumptions!$K$6 -> 13.419806 | G9: =(E9-F9)*Assumptions!$K$7 -> 4.8907739 | H9: =D9*IF(RIGHT(A9,2)="_T",Assumptions!$K$8,Assumptions!$K$9)/10000000 -> 3.347344 | I9: =(E9-SUM(F9:G9))*SUM(Assumptions!$K$10,Assumptions!$K$13)/365*Assumptions!$K$11 -> 0.8413471 | J9: =G9-SUM(H9:I9) -> 0.70208279 | K9: =IFERROR(J9*10000000/Assumptions!$K$12,0) -> 18002.123 | L9: =IFERROR(G9*10000000/D9,0) -> 3.2144 | M9: =IF(J9>0,"PASS","LOSS") -> PASS
A10: =Assumptions!A28 -> GIN_T | B10: =Assumptions!D28 -> 15g single sachet | C10: =Assumptions!E28*(1+Assumptions!$C$11)^2 -> 10 | D10: =SUMIFS(SKU_Channel_Model!$O$6:$O$113,SKU_Channel_Model!$A$6:$A$113,"FY24",SKU_Channel_Model!$B$6:$B$113,A10,SKU_Channel_Model!$D$6:$D$113,"GT") -> 6678880 | E10: =D10*C10/10000000 -> 6.67888 | F10: =E10*Assumptions!$K$6 -> 1.2021984 | G10: =(E10-F10)*Assumptions!$K$7 -> 0.43813453 | H10: =D10*IF(RIGHT(A10,2)="_T",Assumptions!$K$8,Assumptions!$K$9)/10000000 -> 0.2671552 | I10: =(E10-SUM(F10:G10))*SUM(Assumptions!$K$10,Assumptions!$K$13)/365*Assumptions!$K$11 -> 0.075371143 | J10: =G10-SUM(H10:I10) -> 0.095608185 | K10: =IFERROR(J10*10000000/Assumptions!$K$12,0) -> 2451.4919 | L10: =IFERROR(G10*10000000/D10,0) -> 0.656 | M10: =IF(J10>0,"PASS","LOSS") -> PASS
A11: =Assumptions!A29 -> GIN_L | B11: =Assumptions!D29 -> 10-sachet pack | C11: =Assumptions!E29*(1+Assumptions!$C$11)^2 -> 99 | D11: =SUMIFS(SKU_Channel_Model!$O$6:$O$113,SKU_Channel_Model!$A$6:$A$113,"FY24",SKU_Channel_Model!$B$6:$B$113,A11,SKU_Channel_Model!$D$6:$D$113,"GT") -> 4045860 | E11: =D11*C11/10000000 -> 40.054014 | F11: =E11*Assumptions!$K$6 -> 7.2097225 | G11: =(E11-F11)*Assumptions!$K$7 -> 2.6275433 | H11: =D11*IF(RIGHT(A11,2)="_T",Assumptions!$K$8,Assumptions!$K$9)/10000000 -> 0.8900892 | I11: =(E11-SUM(F11:G11))*SUM(Assumptions!$K$10,Assumptions!$K$13)/365*Assumptions!$K$11 -> 0.45200944 | J11: =G11-SUM(H11:I11) -> 1.2854447 | K11: =IFERROR(J11*10000000/Assumptions!$K$12,0) -> 32960.12 | L11: =IFERROR(G11*10000000/D11,0) -> 6.4944 | M11: =IF(J11>0,"PASS","LOSS") -> PASS
A12: =Assumptions!A30 -> BAD_T | B12: =Assumptions!D30 -> 15g single sachet | C12: =Assumptions!E30*(1+Assumptions!$C$11)^2 -> 10 | D12: =SUMIFS(SKU_Channel_Model!$O$6:$O$113,SKU_Channel_Model!$A$6:$A$113,"FY24",SKU_Channel_Model!$B$6:$B$113,A12,SKU_Channel_Model!$D$6:$D$113,"GT") -> 3734640 | E12: =D12*C12/10000000 -> 3.73464 | F12: =E12*Assumptions!$K$6 -> 0.6722352 | G12: =(E12-F12)*Assumptions!$K$7 -> 0.24499238 | H12: =D12*IF(RIGHT(A12,2)="_T",Assumptions!$K$8,Assumptions!$K$9)/10000000 -> 0.1493856 | I12: =(E12-SUM(F12:G12))*SUM(Assumptions!$K$10,Assumptions!$K$13)/365*Assumptions!$K$11 -> 0.042145402 | J12: =G12-SUM(H12:I12) -> 0.053461382 | K12: =IFERROR(J12*10000000/Assumptions!$K$12,0) -> 1370.8047 | L12: =IFERROR(G12*10000000/D12,0) -> 0.656 | M12: =IF(J12>0,"PASS","LOSS") -> PASS
A13: =Assumptions!A31 -> BAD_L | B13: =Assumptions!D31 -> 150g pouch | C13: =Assumptions!E31*(1+Assumptions!$C$11)^2 -> 99 | D13: =SUMIFS(SKU_Channel_Model!$O$6:$O$113,SKU_Channel_Model!$A$6:$A$113,"FY24",SKU_Channel_Model!$B$6:$B$113,A13,SKU_Channel_Model!$D$6:$D$113,"GT") -> 2771340 | E13: =D13*C13/10000000 -> 27.436266 | F13: =E13*Assumptions!$K$6 -> 4.9385279 | G13: =(E13-F13)*Assumptions!$K$7 -> 1.799819 | H13: =D13*IF(RIGHT(A13,2)="_T",Assumptions!$K$8,Assumptions!$K$9)/10000000 -> 0.6096948 | I13: =(E13-SUM(F13:G13))*SUM(Assumptions!$K$10,Assumptions!$K$13)/365*Assumptions!$K$11 -> 0.30961819 | J13: =G13-SUM(H13:I13) -> 0.88050606 | K13: =IFERROR(J13*10000000/Assumptions!$K$12,0) -> 22577.079 | L13: =IFERROR(G13*10000000/D13,0) -> 6.4944 | M13: =IF(J13>0,"PASS","LOSS") -> PASS
A14: =Assumptions!A32 -> CHU_T | B14: =Assumptions!D32 -> 20g sachet | C14: =Assumptions!E32*(1+Assumptions!$C$11)^2 -> 10 | D14: =SUMIFS(SKU_Channel_Model!$O$6:$O$113,SKU_Channel_Model!$A$6:$A$113,"FY24",SKU_Channel_Model!$B$6:$B$113,A14,SKU_Channel_Model!$D$6:$D$113,"GT") -> 6160180 | E14: =D14*C14/10000000 -> 6.16018 | F14: =E14*Assumptions!$K$6 -> 1.1088324 | G14: =(E14-F14)*Assumptions!$K$7 -> 0.40410781 | H14: =D14*IF(RIGHT(A14,2)="_T",Assumptions!$K$8,Assumptions!$K$9)/10000000 -> 0.2464072 | I14: =(E14-SUM(F14:G14))*SUM(Assumptions!$K$10,Assumptions!$K$13)/365*Assumptions!$K$11 -> 0.069517614 | J14: =G14-SUM(H14:I14) -> 0.088182994 | K14: =IFERROR(J14*10000000/Assumptions!$K$12,0) -> 2261.1024 | L14: =IFERROR(G14*10000000/D14,0) -> 0.656 | M14: =IF(J14>0,"PASS","LOSS") -> PASS
A15: =Assumptions!A33 -> CHU_L | B15: =Assumptions!D33 -> 200g pack | C15: =Assumptions!E33*(1+Assumptions!$C$11)^2 -> 99 | D15: =SUMIFS(SKU_Channel_Model!$O$6:$O$113,SKU_Channel_Model!$A$6:$A$113,"FY24",SKU_Channel_Model!$B$6:$B$113,A15,SKU_Channel_Model!$D$6:$D$113,"GT") -> 3586440 | E15: =D15*C15/10000000 -> 35.505756 | F15: =E15*Assumptions!$K$6 -> 6.3910361 | G15: =(E15-F15)*Assumptions!$K$7 -> 2.3291776 | H15: =D15*IF(RIGHT(A15,2)="_T",Assumptions!$K$8,Assumptions!$K$9)/10000000 -> 0.7890168 | I15: =(E15-SUM(F15:G15))*SUM(Assumptions!$K$10,Assumptions!$K$13)/365*Assumptions!$K$11 -> 0.40068236 | J15: =G15-SUM(H15:I15) -> 1.1394784 | K15: =IFERROR(J15*10000000/Assumptions!$K$12,0) -> 29217.396 | L15: =IFERROR(G15*10000000/D15,0) -> 6.4944 | M15: =IF(J15>0,"PASS","LOSS") -> PASS
A16: =Assumptions!A34 -> PIC_T | B16: =Assumptions!D34 -> 20g sachet | C16: =Assumptions!E34*(1+Assumptions!$C$11)^2 -> 10 | D16: =SUMIFS(SKU_Channel_Model!$O$6:$O$113,SKU_Channel_Model!$A$6:$A$113,"FY24",SKU_Channel_Model!$B$6:$B$113,A16,SKU_Channel_Model!$D$6:$D$113,"GT") -> 5601960 | E16: =D16*C16/10000000 -> 5.60196 | F16: =E16*Assumptions!$K$6 -> 1.0083528 | G16: =(E16-F16)*Assumptions!$K$7 -> 0.36748858 | H16: =D16*IF(RIGHT(A16,2)="_T",Assumptions!$K$8,Assumptions!$K$9)/10000000 -> 0.2240784 | I16: =(E16-SUM(F16:G16))*SUM(Assumptions!$K$10,Assumptions!$K$13)/365*Assumptions!$K$11 -> 0.063218103 | J16: =G16-SUM(H16:I16) -> 0.080192073 | K16: =IFERROR(J16*10000000/Assumptions!$K$12,0) -> 2056.207 | L16: =IFERROR(G16*10000000/D16,0) -> 0.656 | M16: =IF(J16>0,"PASS","LOSS") -> PASS
A17: =Assumptions!A35 -> PIC_L | B17: =Assumptions!D35 -> 200g pack | C17: =Assumptions!E35*(1+Assumptions!$C$11)^2 -> 99 | D17: =SUMIFS(SKU_Channel_Model!$O$6:$O$113,SKU_Channel_Model!$A$6:$A$113,"FY24",SKU_Channel_Model!$B$6:$B$113,A17,SKU_Channel_Model!$D$6:$D$113,"GT") -> 4021160 | E17: =D17*C17/10000000 -> 39.809484 | F17: =E17*Assumptions!$K$6 -> 7.1657071 | G17: =(E17-F17)*Assumptions!$K$7 -> 2.6115022 | H17: =D17*IF(RIGHT(A17,2)="_T",Assumptions!$K$8,Assumptions!$K$9)/10000000 -> 0.8846552 | I17: =(E17-SUM(F17:G17))*SUM(Assumptions!$K$10,Assumptions!$K$13)/365*Assumptions!$K$11 -> 0.44924992 | J17: =G17-SUM(H17:I17) -> 1.277597 | K17: =IFERROR(J17*10000000/Assumptions!$K$12,0) -> 32758.898 | L17: =IFERROR(G17*10000000/D17,0) -> 6.4944 | M17: =IF(J17>0,"PASS","LOSS") -> PASS
A19: TOTAL TRADE ECONOMICS | D19: =SUM(D6:D17) -> 95307420 | E19: =SUM(E6:E17) -> 358.16482 | F19: =SUM(F6:F17) -> 64.469668 | G19: =SUM(G6:G17) -> 23.495612 | H19: =SUM(H6:H17) -> 12.615377 | I19: =SUM(I6:I17) -> 4.041889 | J19: =SUM(J6:J17) -> 6.8383464 | K19: =IFERROR(J19*10000000/Assumptions!K12,0) -> 175342.21
A22: Case channel margins are blended, unlike Exhibit 2 two-step margin waterfall. Use retailer and distributor contracts to resolve difference.
A23: Model uses equal allocation across 390 distributors as a proxy. Actual profit dispersion, inventory turns and trade-credit liability must be validated.
